Workbook

Sheet Como ler
A1: Mapa de criadores · Itajaí, Balneário Camboriú, Camboriú e Itapema
A2: Coleta: 27/09/2026, Instagram, perfis públicos, via Apify (hashtags de cidade e nicho, busca por nome, menções e marcações nos posts).
A3: Métricas calculadas sobre os últimos ~12 posts públicos de cada perfil (posts fixados ignorados).
A5: Colunas
A6: Engajamento: mediana de (curtidas + comentários) por post ÷ seguidores. Mediana evita que um post viral distorça.
A7: Engaj. de referência: valor típico para a faixa de seguidores (tabela abaixo). "Engaj. vs referência" 1,00 = na média; 2,00 = o dobro.
A8: Views/seguidores: mediana de visualizações dos reels ÷ seguidores. Acima de 0,5 significa que os vídeos saem da bolha.
A9: Posts/semana e Último post: cadência e se a conta está ativa. Dias sem postar contam a partir da data de coleta.
A10: Publis (de 12): posts marcados como parceria paga ou com #publi/#publicidade. Marcas em publis: @ das marcas marcadas nesses posts.
A11: Nichos: detectados na bio (peso maior) e nas legendas/hashtags. Um criador pode ter até 4 nichos. Nicho principal = o mais forte.
A12: Como confirmei a cidade: "bio" = a pessoa escreve a cidade na bio; "N post(s) marcados" = posts com localização na cidade.
A13: Canal de contato: só indica o canal que a pessoa divulga (e-mail, WhatsApp, direct). Os dados em si não foram copiados.
... A18: Engajamento de referência por faixa
A19: Faixa | B19: Engajamento típico
A20: Nano (1k–3k) | B20: 0.04
A21: Micro (3k–30k) | B21: 0.025
A22: Média (30k–100k) | B22: 0.015
A23: Macro (100k–500k) | B23: 0.01
A24: Mega (500k+) | B24: 0.007
A25: Fonte: médias de mercado para Instagram (benchmarks públicos de 2024–2026); use como régua, não como regra.
A27: Data da coleta | B27: 46292

Sheet Resumo
A1: Resumo por cidade (cidade principal)
A3: Cidade | B3: Total | C3: Nano (1k–3k) | D3: Micro (3k–30k) | E3: Média (30k–100k) | F3: Macro (100k–500k) | G3: Mega (500k+) | H3: Mulher | I3: Homem | J3: Criador(a) | K3: Especialista | L3: Página local | M3: Fit alta | N3: Score médio
A4: Itajaí | B4: =COUNTIF('Base completa'!$A$2:$A$183,$A4) -> 58 | C4: =COUNTIFS('Base completa'!$A$2:$A$183,$A4,'Base completa'!$H$2:$H$183,"Nano (1k–3k)") -> 12 | D4: =COUNTIFS('Base completa'!$A$2:$A$183,$A4,'Base completa'!$H$2:$H$183,"Micro (3k–30k)") -> 34 | E4: =COUNTIFS('Base completa'!$A$2:$A$183,$A4,'Base completa'!$H$2:$H$183,"Média (30k–100k)") -> 9 | F4: =COUNTIFS('Base completa'!$A$2:$A$183,$A4,'Base completa'!$H$2:$H$183,"Macro (100k–500k)") -> 2 | G4: =COUNTIFS('Base completa'!$A$2:$A$183,$A4,'Base completa'!$H$2:$H$183,"Mega (500k+)") -> 1 | H4: =COUNTIFS('Base completa'!$A$2:$A$183,$A4,'Base completa'!$F$2:$F$183,"Mulher") -> 38 | I4: =COUNTIFS('Base completa'!$A$2:$A$183,$A4,'Base completa'!$F$2:$F$183,"Homem") -> 15 | J4: =COUNTIFS('Base completa'!$A$2:$A$183,$A4,'Base completa'!$E$2:$E$183,"Criador(a)") -> 35 | K4: =COUNTIFS('Base completa'!$A$2:$A$183,$A4,'Base completa'!$E$2:$E$183,"Especialista que cria conteúdo") -> 19 | L4: =COUNTIFS('Base completa'!$A$2:$A$183,$A4,'Base completa'!$E$2:$E$183,"Página local / guia") -> 4 | M4: =COUNTIFS('Base completa'!$A$2:$A$183,$A4,'Base completa'!$X$2:$X$183,"Alta") -> 28 | N4: =IFERROR(ROUND(AVERAGEIF('Base completa'!$A$2:$A$183,$A4,'Base completa'!$Y$2:$Y$183),0),"") -> 49
A5: Balneário Camboriú | B5: =COUNTIF('Base completa'!$A$2:$A$183,$A5) -> 81 | C5: =COUNTIFS('Base completa'!$A$2:$A$183,$A5,'Base completa'!$H$2:$H$183,"Nano (1k–3k)") -> 16 | D5: =COUNTIFS('Base completa'!$A$2:$A$183,$A5,'Base completa'!$H$2:$H$183,"Micro (3k–30k)") -> 42 | E5: =COUNTIFS('Base completa'!$A$2:$A$183,$A5,'Base completa'!$H$2:$H$183,"Média (30k–100k)") -> 13 | F5: =COUNTIFS('Base completa'!$A$2:$A$183,$A5,'Base completa'!$H$2:$H$183,"Macro (100k–500k)") -> 8 | G5: =COUNTIFS('Base completa'!$A$2:$A$183,$A5,'Base completa'!$H$2:$H$183,"Mega (500k+)") -> 2 | H5: =COUNTIFS('Base completa'!$A$2:$A$183,$A5,'Base completa'!$F$2:$F$183,"Mulher") -> 48 | I5: =COUNTIFS('Base completa'!$A$2:$A$183,$A5,'Base completa'!$F$2:$F$183,"Homem") -> 16 | J5: =COUNTIFS('Base completa'!$A$2:$A$183,$A5,'Base completa'!$E$2:$E$183,"Criador(a)") -> 33 | K5: =COUNTIFS('Base completa'!$A$2:$A$183,$A5,'Base completa'!$E$2:$E$183,"Especialista que cria conteúdo") -> 34 | L5: =COUNTIFS('Base completa'!$A$2:$A$183,$A5,'Base completa'!$E$2:$E$183,"Página local / guia") -> 14 | M5: =COUNTIFS('Base completa'!$A$2:$A$183,$A5,'Base completa'!$X$2:$X$183,"Alta") -> 24 | N5: =IFERROR(ROUND(AVERAGEIF('Base completa'!$A$2:$A$183,$A5,'Base completa'!$Y$2:$Y$183),0),"") -> 44
A6: Camboriú | B6: =COUNTIF('Base completa'!$A$2:$A$183,$A6) -> 9 | C6: =COUNTIFS('Base completa'!$A$2:$A$183,$A6,'Base completa'!$H$2:$H$183,"Nano (1k–3k)") -> 1 | D6: =COUNTIFS('Base completa'!$A$2:$A$183,$A6,'Base completa'!$H$2:$H$183,"Micro (3k–30k)") -> 6 | E6: =COUNTIFS('Base completa'!$A$2:$A$183,$A6,'Base completa'!$H$2:$H$183,"Média (30k–100k)") -> 2 | F6: =COUNTIFS('Base completa'!$A$2:$A$183,$A6,'Base completa'!$H$2:$H$183,"Macro (100k–500k)") -> 0 | G6: =COUNTIFS('Base completa'!$A$2:$A$183,$A6,'Base completa'!$H$2:$H$183,"Mega (500k+)") -> 0 | H6: =COUNTIFS('Base completa'!$A$2:$A$183,$A6,'Base completa'!$F$2:$F$183,"Mulher") -> 7 | I6: =COUNTIFS('Base completa'!$A$2:$A$183,$A6,'Base completa'!$F$2:$F$183,"Homem") -> 1 | J6: =COUNTIFS('Base completa'!$A$2:$A$183,$A6,'Base completa'!$E$2:$E$183,"Criador(a)") -> 4 | K6: =COUNTIFS('Base completa'!$A$2:$A$183,$A6,'Base completa'!$E$2:$E$183,"Especialista que cria conteúdo") -> 4 | L6: =COUNTIFS('Base completa'!$A$2:$A$183,$A6,'Base completa'!$E$2:$E$183,"Página local / guia") -> 1 | M6: =COUNTIFS('Base completa'!$A$2:$A$183,$A6,'Base completa'!$X$2:$X$183,"Alta") -> 3 | N6: =IFERROR(ROUND(AVERAGEIF('Base completa'!$A$2:$A$183,$A6,'Base completa'!$Y$2:$Y$183),0),"") -> 46
A7: Itapema | B7: =COUNTIF('Base completa'!$A$2:$A$183,$A7) -> 34 | C7: =COUNTIFS('Base completa'!$A$2:$A$183,$A7,'Base completa'!$H$2:$H$183,"Nano (1k–3k)") -> 13 | D7: =COUNTIFS('Base completa'!$A$2:$A$183,$A7,'Base completa'!$H$2:$H$183,"Micro (3k–30k)") -> 12 | E7: =COUNTIFS('Base completa'!$A$2:$A$183,$A7,'Base completa'!$H$2:$H$183,"Média (30k–100k)") -> 7 | F7: =COUNTIFS('Base completa'!$A$2:$A$183,$A7,'Base completa'!$H$2:$H$183,"Macro (100k–500k)") -> 2 | G7: =COUNTIFS('Base completa'!$A$2:$A$183,$A7,'Base completa'!$H$2:$H$183,"Mega (500k+)") -> 0 | H7: =COUNTIFS('Base completa'!$A$2:$A$183,$A7,'Base completa'!$F$2:$F$183,"Mulher") -> 16 | I7: =COUNTIFS('Base completa'!$A$2:$A$183,$A7,'Base completa'!$F$2:$F$183,"Homem") -> 10 | J7: =COUNTIFS('Base completa'!$A$2:$A$183,$A7,'Base completa'!$E$2:$E$183,"Criador(a)") -> 17 | K7: =COUNTIFS('Base completa'!$A$2:$A$183,$A7,'Base completa'!$E$2:$E$183,"Especialista que cria conteúdo") -> 9 | L7: =COUNTIFS('Base completa'!$A$2:$A$183,$A7,'Base completa'!$E$2:$E$183,"Página local / guia") -> 8 | M7: =COUNTIFS('Base completa'!$A$2:$A$183,$A7,'Base completa'!$X$2:$X$183,"Alta") -> 6 | N7: =IFERROR(ROUND(AVERAGEIF('Base completa'!$A$2:$A$183,$A7,'Base completa'!$Y$2:$Y$183),0),"") -> 48
A8: Total | B8: =SUM(B4:B7) -> 182 | C8: =SUM(C4:C7) -> 42 | D8: =SUM(D4:D7) -> 94 | E8: =SUM(E4:E7) -> 31 | F8: =SUM(F4:F7) -> 12 | G8: =SUM(G4:G7) -> 3 | H8: =SUM(H4:H7) -> 109 | I8: =SUM(I4:I7) -> 42 | ... M8: =SUM(M4:M7) -> 61 | N8: =IFERROR(ROUND(AVERAGE('Base completa'!$Y$2:$Y$183),0),"") -> 47
A10: Criadores por nicho e cidade (um perfil conta em cada nicho em que aparece)
A11: Nicho | B11: Itajaí | C11: Balneário Camboriú | D11: Camboriú | E11: Itapema | F11: Total
A12: UGC | B12: =COUNTIFS('Base completa'!$A$2:$A$183,"Itajaí",'Base completa'!$W$2:$W$183,"*"&$A12&"*") -> 3 | C12: =COUNTIFS('Base completa'!$A$2:$A$183,"Balneário Camboriú",'Base completa'!$W$2:$W$183,"*"&$A12&"*") -> 1 | D12: =COUNTIFS('Base completa'!$A$2:$A$183,"Camboriú",'Base completa'!$W$2:$W$183,"*"&$A12&"*") -> 0 | E12: =COUNTIFS('Base completa'!$A$2:$A$183,"Itapema",'Base completa'!$W$2:$W$183,"*"&$A12&"*") -> 1 | F12: =SUM(B12:E12) -> 5
A13: Lifestyle | B13: =COUNTIFS('Base completa'!$A$2:$A$183,"Itajaí",'Base completa'!$W$2:$W$183,"*"&$A13&"*") -> 13 | C13: =COUNTIFS('Base completa'!$A$2:$A$183,"Balneário Camboriú",'Base completa'!$W$2:$W$183,"*"&$A13&"*") -> 16 | D13: =COUNTIFS('Base completa'!$A$2:$A$183,"Camboriú",'Base completa'!$W$2:$W$183,"*"&$A13&"*") -> 0 | E13: =COUNTIFS('Base completa'!$A$2:$A$183,"Itapema",'Base completa'!$W$2:$W$183,"*"&$A13&"*") -> 4 | F13: =SUM(B13:E13) -> 33
A14: Beleza | B14: =COUNTIFS('Base completa'!$A$2:$A$183,"Itajaí",'Base completa'!$W$2:$W$183,"*"&$A14&"*") -> 5 | C14: =COUNTIFS('Base completa'!$A$2:$A$183,"Balneário Camboriú",'Base completa'!$W$2:$W$183,"*"&$A14&"*") -> 9 | D14: =COUNTIFS('Base completa'!$A$2:$A$183,"Camboriú",'Base completa'!$W$2:$W$183,"*"&$A14&"*") -> 0 | E14: =COUNTIFS('Base completa'!$A$2:$A$183,"Itapema",'Base completa'!$W$2:$W$183,"*"&$A14&"*") -> 3 | F14: =SUM(B14:E14) -> 17
A15: Moda | B15: =COUNTIFS('Base completa'!$A$2:$A$183,"Itajaí",'Base completa'!$W$2:$W$183,"*"&$A15&"*") -> 6 | C15: =COUNTIFS('Base completa'!$A$2:$A$183,"Balneário Camboriú",'Base completa'!$W$2:$W$183,"*"&$A15&"*") -> 10 | D15: =COUNTIFS('Base completa'!$A$2:$A$183,"Camboriú",'Base completa'!$W$2:$W$183,"*"&$A15&"*") -> 1 | E15: =COUNTIFS('Base completa'!$A$2:$A$183,"Itapema",'Base completa'!$W$2:$W$183,"*"&$A15&"*") -> 2 | F15: =SUM(B15:E15) -> 19
A16: Fitness e wellness | B16: =COUNTIFS('Base completa'!$A$2:$A$183,"Itajaí",'Base completa'!$W$2:$W$183,"*"&$A16&"*") -> 10 | C16: =COUNTIFS('Base completa'!$A$2:$A$183,"Balneário Camboriú",'Base completa'!$W$2:$W$183,"*"&$A16&"*") -> 18 | D16: =COUNTIFS('Base completa'!$A$2:$A$183,"Camboriú",'Base completa'!$W$2:$W$183,"*"&$A16&"*") -> 3 | E16: =COUNTIFS('Base completa'!$A$2:$A$183,"Itapema",'Base completa'!$W$2:$W$183,"*"&$A16&"*") -> 8 | F16: =SUM(B16:E16) -> 39
A17: Gastronomia | B17: =COUNTIFS('Base completa'!$A$2:$A$183,"Itajaí",'Base completa'!$W$2:$W$183,"*"&$A17&"*") -> 9 | C17: =COUNTIFS('Base completa'!$A$2:$A$183,"Balneário Camboriú",'Base completa'!$W$2:$W$183,"*"&$A17&"*") -> 12 | D17: =COUNTIFS('Base completa'!$A$2:$A$183,"Camboriú",'Base completa'!$W$2:$W$183,"*"&$A17&"*") -> 1 | E17: =COUNTIFS('Base completa'!$A$2:$A$183,"Itapema",'Base completa'!$W$2:$W$183,"*"&$A17&"*") -> 3 | F17: =SUM(B17:E17) -> 25
A18: Viagem | B18: =COUNTIFS('Base completa'!$A$2:$A$183,"Itajaí",'Base completa'!$W$2:$W$183,"*"&$A18&"*") -> 9 | C18: =COUNTIFS('Base completa'!$A$2:$A$183,"Balneário Camboriú",'Base completa'!$W$2:$W$183,"*"&$A18&"*") -> 9 | D18: =COUNTIFS('Base completa'!$A$2:$A$183,"Camboriú",'Base completa'!$W$2:$W$183,"*"&$A18&"*") -> 1 | E18: =COUNTIFS('Base completa'!$A$2:$A$183,"Itapema",'Base completa'!$W$2:$W$183,"*"&$A18&"*") -> 7 | F18: =SUM(B18:E18) -> 26
A19: Entretenimento e humor | B19: =COUNTIFS('Base completa'!$A$2:$A$183,"Itajaí",'Base completa'!$W$2:$W$183,"*"&$A19&"*") -> 7 | C19: =COUNTIFS('Base completa'!$A$2:$A$183,"Balneário Camboriú",'Base completa'!$W$2:$W$183,"*"&$A19&"*") -> 8 | D19: =COUNTIFS('Base completa'!$A$2:$A$183,"Camboriú",'Base completa'!$W$2:$W$183,"*"&$A19&"*") -> 0 | E19: =COUNTIFS('Base completa'!$A$2:$A$183,"Itapema",'Base completa'!$W$2:$W$183,"*"&$A19&"*") -> 4 | F19: =SUM(B19:E19) -> 19
A20: Finanças | B20: =COUNTIFS('Base completa'!$A$2:$A$183,"Itajaí",'Base completa'!$W$2:$W$183,"*"&$A20&"*") -> 3 | C20: =COUNTIFS('Base completa'!$A$2:$A$183,"Balneário Camboriú",'Base completa'!$W$2:$W$183,"*"&$A20&"*") -> 2 | D20: =COUNTIFS('Base completa'!$A$2:$A$183,"Camboriú",'Base completa'!$W$2:$W$183,"*"&$A20&"*") -> 0 | E20: =COUNTIFS('Base completa'!$A$2:$A$183,"Itapema",'Base completa'!$W$2:$W$183,"*"&$A20&"*") -> 4 | F20: =SUM(B20:E20) -> 9
A21: Casa e organização | B21: =COUNTIFS('Base completa'!$A$2:$A$183,"Itajaí",'Base completa'!$W$2:$W$183,"*"&$A21&"*") -> 9 | C21: =COUNTIFS('Base completa'!$A$2:$A$183,"Balneário Camboriú",'Base completa'!$W$2:$W$183,"*"&$A21&"*") -> 10 | D21: =COUNTIFS('Base completa'!$A$2:$A$183,"Camboriú",'Base completa'!$W$2:$W$183,"*"&$A21&"*") -> 2 | E21: =COUNTIFS('Base completa'!$A$2:$A$183,"Itapema",'Base completa'!$W$2:$W$183,"*"&$A21&"*") -> 2 | F21: =SUM(B21:E21) -> 23
A22: Tecnologia | B22: =COUNTIFS('Base completa'!$A$2:$A$183,"Itajaí",'Base completa'!$W$2:$W$183,"*"&$A22&"*") -> 0 | C22: =COUNTIFS('Base completa'!$A$2:$A$183,"Balneário Camboriú",'Base completa'!$W$2:$W$183,"*"&$A22&"*") -> 0 | D22: =COUNTIFS('Base completa'!$A$2:$A$183,"Camboriú",'Base completa'!$W$2:$W$183,"*"&$A22&"*") -> 0 | E22: =COUNTIFS('Base completa'!$A$2:$A$183,"Itapema",'Base completa'!$W$2:$W$183,"*"&$A22&"*") -> 0 | F22: =SUM(B22:E22) -> 0
A23: Negócios e empreendedorismo | B23: =COUNTIFS('Base completa'!$A$2:$A$183,"Itajaí",'Base completa'!$W$2:$W$183,"*"&$A23&"*") -> 16 | C23: =COUNTIFS('Base completa'!$A$2:$A$183,"Balneário Camboriú",'Base completa'!$W$2:$W$183,"*"&$A23&"*") -> 17 | D23: =COUNTIFS('Base completa'!$A$2:$A$183,"Camboriú",'Base completa'!$W$2:$W$183,"*"&$A23&"*") -> 2 | E23: =COUNTIFS('Base completa'!$A$2:$A$183,"Itapema",'Base completa'!$W$2:$W$183,"*"&$A23&"*") -> 4 | F23: =SUM(B23:E23) -> 39
... A28: Dicas locais | B28: =COUNTIFS('Base completa'!$A$2:$A$183,"Itajaí",'Base completa'!$W$2:$W$183,"*"&$A28&"*") -> 11 | C28: =COUNTIFS('Base completa'!$A$2:$A$183,"Balneário Camboriú",'Base completa'!$W$2:$W$183,"*"&$A28&"*") -> 18 | D28: =COUNTIFS('Base completa'!$A$2:$A$183,"Camboriú",'Base completa'!$W$2:$W$183,"*"&$A28&"*") -> 0 | E28: =COUNTIFS('Base completa'!$A$2:$A$183,"Itapema",'Base completa'!$W$2:$W$183,"*"&$A28&"*") -> 5 | F28: =SUM(B28:E28) -> 34

Sheet Base completa
A1: Cidade principal | B1: Também atua em | C1: Perfil | D1: Nome | E1: Tipo | F1: Criador(a) | G1: Seguidores | H1: Faixa | I1: Engajamento | J1: Engaj. de referência | K1: Engaj. vs referência | L1: Média de curtidas | M1: Média de comentários | N1: Views medianas (reels) | O1: Views/seguidores | P1: % vídeos | Q1: Posts/semana | R1: Último post | S1: Dias sem postar | T1: Publis (de 12) | U1: Marcas em publis | V1: Nicho principal | W1: Nichos | X1: Fit CRIA | Y1: Score (0-100) | Z1: Categoria no IG | AA1: Verificado | AB1: Link na bio | AC1: Canal de contato | AD1: Como confirmei a cidade | AE1: Locais marcados | AF1: Bio | AG1: Link | AH1: Status | AI1: Observações
A2: Itajaí | C2: @thaisedemari | D2: Thaise de Mari | E2: Criador(a) | F2: Mulher | G2: 1049161 | H2: Mega (500k+) | I2: 0.0015 | J2: =IFERROR(INDEX('Como ler'!$B$20:$B$24,MATCH(H2,'Como ler'!$A$20:$A$24,0)),"") -> 0.007 | K2: =IF(OR(I2="",J2=""),"",I2/J2) -> 0.21428571 | L2: 2112 | M2: 86.8 | N2: 19137 | O2: =IF(OR(N2="",G2=0),"",N2/G2) -> 0.018240289 | P2: 0.42 | Q2: 0.9 | R2: 46286 | S2: =IF(R2="","",'Como ler'!$B$27-R2) -> 6 | T2: 0 | V2: Beleza | W2: Beleza, Negócios e empreendedorismo, Lifestyle, Moda | X2: Alta | Y2: =ROUND(IF(K2="",0,MIN(40,40*K2/1.5))+IF(S2="",0,IF(S2<=7,20,IF(S2<=30,12,IF(S2<=90,5,0))))+IF(Q2="",0,MIN(15,Q2*5))+IF(O2="",0,MIN(15,O2*30))+IF(E2="Criador(a)",10,IF(E2="Especialista que cria conteúdo",6,4)),0) -> 41 | Z2: Entrepreneur | AD2: Itajaí: bio | AE2: Barcelona, España (2), Formentera, Islas Baleares, Spain (2), Ibiza, Spain (2), Rio de Janeiro, Rio de Janeiro (1) | AF2: Fashion • Beauty • Lifestyle • Travel • Real life / Founder @nowwabrand / Caixa Postal 46 Itajaí-SC Cep 88301-970 | AG2: https://instagram.com/thaisedemari | AH2: Não contatada
A3: Itajaí | C3: @lucasmirandasc | D3: Lucas Miranda | E3: Criador(a) | F3: Homem | G3: 189201 | H3: Macro (100k–500k) | I3: 0.0033 | J3: =IFERROR(INDEX('Como ler'!$B$20:$B$24,MATCH(H3,'Como ler'!$A$20:$A$24,0)),"") -> 0.01 | K3: =IF(OR(I3="",J3=""),"",I3/J3) -> 0.33 | L3: 1060 | M3: 57.3 | N3: 22196 | O3: =IF(OR(N3="",G3=0),"",N3/G3) -> 0.11731439 | P3: 0.67 | Q3: 0.7 | R3: 46292 | S3: =IF(R3="","",'Como ler'!$B$27-R3) -> 0 | T3: 0 | V3: Gastronomia | W3: Gastronomia, Fitness e wellness, Viagem | X3: Baixa | Y3: =ROUND(IF(K3="",0,MIN(40,40*K3/1.5))+IF(S3="",0,IF(S3<=7,20,IF(S3<=30,12,IF(S3<=90,5,0))))+IF(Q3="",0,MIN(15,Q3*5))+IF(O3="",0,MIN(15,O3*30))+IF(E3="Criador(a)",10,IF(E3="Especialista que cria conteúdo",6,4)),0) -> 46 | Z3: Digital creator | AD3: Itajaí: bio, 2 post(s) marcados | AE3: Itajaí- Santa Catarina (2) | AF3: Itajaí - SC📍 / Hospedagens | Gastronomia / MISTER LAS AMÉRICAS ITAJAÍ 2026 / Embaixador: @lfmen @mancluboficial @3coracoes @maxinutrioficial @academia.ad3 | AG3: https://instagram.com/lucasmirandasc | AH3: Não contatada
A4: Itajaí | C4: @superdicasnaestrada | D4: Super Dicas na Estrada - Lucas e Maitê | E4: Criador(a) | F4: Homem | G4: 100790 | H4: Macro (100k–500k) | J4: =IFERROR(INDEX('Como ler'!$B$20:$B$24,MATCH(H4,'Como ler'!$A$20:$A$24,0)),"") -> 0.01 | K4: =IF(OR(I4="",J4=""),"",I4/J4) | M4: 48.2 | N4: 2518 | O4: =IF(OR(N4="",G4=0),"",N4/G4) -> 0.024982637 | P4: 0.89 | Q4: 1.5 | R4: 46284 | S4: =IF(R4="","",'Como ler'!$B$27-R4) -> 8 | T4: 0 | V4: Dicas locais | W4: Dicas locais, Gastronomia | X4: Baixa | Y4: =ROUND(IF(K4="",0,MIN(40,40*K4/1.5))+IF(S4="",0,IF(S4<=7,20,IF(S4<=30,12,IF(S4<=90,5,0))))+IF(Q4="",0,MIN(15,Q4*5))+IF(O4="",0,MIN(15,O4*30))+IF(E4="Criador(a)",10,IF(E4="Especialista que cria conteúdo",6,4)),0) -> 30 | Z4: Digital creator | AB4: Sim | AC4: whats | AD4: Itajaí: 1 post(s) marcados | AE4: Blumenau, Santa Catarina, Brazil (2), Piçarras (1), Rodeio (1), Itajaí -SC (1) | AF4: 🌎 Super Dicas pelas estradas do Sul do Brasil! / 🚀+ de 600 empresas parceiras! / ⭐️ Divulgue sua marca aqui! / ⬇️ Contato Whats: | AG4: https://instagram.com/superdicasnaestrada | AH4: Não contatada | AI4: Curtidas ocultas: engajamento calculado só com posts visíveis ou indisponível
A5: Itajaí | C5: @raissaarcanjo | D5: Raíssa Arcanjo | E5: Criador(a) | F5: Mulher | G5: 89409 | H5: Média (30k–100k) | I5: 0.0014 | J5: =IFERROR(INDEX('Como ler'!$B$20:$B$24,MATCH(H5,'Como ler'!$A$20:$A$24,0)),"") -> 0.015 | K5: =IF(OR(I5="",J5=""),"",I5/J5) -> 0.093333333 | L5: 264 | M5: 41.7 | N5: 1456 | O5: =IF(OR(N5="",G5=0),"",N5/G5) -> 0.016284714 | P5: 0.67 | Q5: 6.2 | R5: 46289 | S5: =IF(R5="","",'Como ler'!$B$27-R5) -> 3 | T5: 0 | V5: Negócios e empreendedorismo | W5: Negócios e empreendedorismo | X5: Alta | Y5: =ROUND(IF(K5="",0,MIN(40,40*K5/1.5))+IF(S5="",0,IF(S5<=7,20,IF(S5<=30,12,IF(S5<=90,5,0))))+IF(Q5="",0,MIN(15,Q5*5))+IF(O5="",0,MIN(15,O5*30))+IF(E5="Criador(a)",10,IF(E5="Especialista que cria conteúdo",6,4)),0) -> 48 | Z5: Digital creator | AA5: Sim | AB5: Sim | AD5: Itajaí: 4 post(s) marcados | AE5: Itajaí (4), Greenvalley (1), Balneário Shopping (1), Navegantes (1) | AF5: Geralmente posto muitooo. 🗣️ / Palestrante, Mentora, Influenciadora, Empreendedora, Colunista Social. 🧠 / VICIADA EM VER GENTE VENCENDO NA VIDA! 🫀 | AG5: https://instagram.com/raissaarcanjo | AH5: Não contatada
A6: Itajaí | C6: @itajaisc_ | D6: Renildo Figueiredo 😎 | E6: Criador(a) | F6: Homem | G6: 83440 | H6: Média (30k–100k) | I6: 0.0109 | J6: =IFERROR(INDEX('Como ler'!$B$20:$B$24,MATCH(H6,'Como ler'!$A$20:$A$24,0)),"") -> 0.015 | K6: =IF(OR(I6="",J6=""),"",I6/J6) -> 0.72666667 | L6: 1267 | M6: 140 | N6: 9851 | O6: =IF(OR(N6="",G6=0),"",N6/G6) -> 0.11806088 | P6: 0.9 | Q6: 15.8 | R6: 46291 | S6: =IF(R6="","",'Como ler'!$B$27-R6) -> 1 | T6: 0 | V6: Finanças | W6: Finanças, Dicas locais, Entretenimento e humor, Família e maternidade | X6: Média | Y6: =ROUND(IF(K6="",0,MIN(40,40*K6/1.5))+IF(S6="",0,IF(S6<=7,20,IF(S6<=30,12,IF(S6<=90,5,0))))+IF(Q6="",0,MIN(15,Q6*5))+IF(O6="",0,MIN(15,O6*30))+IF(E6="Criador(a)",10,IF(E6="Especialista que cria conteúdo",6,4)),0) -> 68 | AC6: direct | AD6: Itajaí: bio, 7 post(s) marcados | AE6: Itajaí, Santa Catarina, Brasil (6), Parrilla 674 (2), Balneário Piçarras - SC (1), Itajaí (1) | AF6: Um Nortista🛫 vivendo em 🛬Itajaí😎 / 🌴 Itajaí & SC sem filtros / 🏡 Onde morar, passear e investir / 💰 Custo de vida, dicas e lazer / 📲 parceiras via Direct | AG6: https://instagram.com/itajaisc_ | AH6: Não contatada
A7: Itajaí | C7: @nubiakatyoficial | D7: Núbia | Mãe & Blogueira • Itajai | E7: Criador(a) | F7: Mulher | G7: 78728 | H7: Média (30k–100k) | I7: 0.0063 | J7: =IFERROR(INDEX('Como ler'!$B$20:$B$24,MATCH(H7,'Como ler'!$A$20:$A$24,0)),"") -> 0.015 | K7: =IF(OR(I7="",J7=""),"",I7/J7) -> 0.42 | L7: 543 | M7: 26.1 | N7: 5011 | O7: =IF(OR(N7="",G7=0),"",N7/G7) -> 0.063649527 | P7: 0.9 | Q7: 15.8 | R7: 46292 | S7: =IF(R7="","",'Como ler'!$B$27-R7) -> 0 | T7: 0 | V7: Entretenimento e humor | W7: Entretenimento e humor, Família e maternidade | X7: Média | Y7: =ROUND(IF(K7="",0,MIN(40,40*K7/1.5))+IF(S7="",0,IF(S7<=7,20,IF(S7<=30,12,IF(S7<=90,5,0))))+IF(Q7="",0,MIN(15,Q7*5))+IF(O7="",0,MIN(15,O7*30))+IF(E7="Criador(a)",10,IF(E7="Especialista que cria conteúdo",6,4)),0) -> 58 | Z7: Digital creator | AA7: Sim | AD7: Itajaí: bio, 8 post(s) marcados | AE7: Itajaí -SC (7), Itajaí (1) | AF7: 🗣️| FALA MEUX QUIRIDU. TAX TOLO ? / 🩷| MÃE DE DOIS BOCA DE SACOLA / 📍| ITAJAÍ | +70 MILHÕES DE VIEWS TÁ ? | AG7: https://instagram.com/nubiakatyoficial | AH7: Não contatada
A8: Itajaí | C8: @eogriilo | D8: Geovane José - Influencer de Itajaí | E8: Criador(a) | F8: Homem | G8: 76287 | H8: Média (30k–100k) | I8: 0.0016 | J8: =IFERROR(INDEX('Como ler'!$B$20:$B$24,MATCH(H8,'Como ler'!$A$20:$A$24,0)),"") -> 0.015 | K8: =IF(OR(I8="",J8=""),"",I8/J8) -> 0.10666667 | L8: 136 | M8: 16.4 | N8: 2219 | O8: =IF(OR(N8="",G8=0),"",N8/G8) -> 0.029087525 | P8: 0.9 | Q8: 21 | R8: 46292 | S8: =IF(R8="","",'Como ler'!$B$27-R8) -> 0 | T8: 0 | V8: Entretenimento e humor | W8: Entretenimento e humor, Negócios e empreendedorismo | X8: Alta | Y8: =ROUND(IF(K8="",0,MIN(40,40*K8/1.5))+IF(S8="",0,IF(S8<=7,20,IF(S8<=30,12,IF(S8<=90,5,0))))+IF(Q8="",0,MIN(15,Q8*5))+IF(O8="",0,MIN(15,O8*30))+IF(E8="Criador(a)",10,IF(E8="Especialista que cria conteúdo",6,4)),0) -> 49 | Z8: Digital creator | AA8: Sim | AD8: Itajaí: bio, 8 post(s) marcados | AE8: Itajaí -SC (6), São Vicente, Itajaí (2) | AF8: Fala comigo, tropa. / Empresário | Influencer | Dono de Barbearia / Proprietário da @nareguaitajai / Publicidade: @agenciachammma / Itajaí Sc | AG8: https://instagram.com/eogriilo | AH8: Não contatada
A9: Itajaí | C9: @gabryelnuness | D9: Gabryel Nunes - Influenciador de Itajaí | E9: Criador(a) | F9: Homem | G9: 69075 | H9: Média (30k–100k) | I9: 0.0037 | J9: =IFERROR(INDEX('Como ler'!$B$20:$B$24,MATCH(H9,'Como ler'!$A$20:$A$24,0)),"") -> 0.015 | K9: =IF(OR(I9="",J9=""),"",I9/J9) -> 0.24666667 | L9: 430 | M9: 51.8 | N9: 4448 | O9: =IF(OR(N9="",G9=0),"",N9/G9) -> 0.064393775 | P9: 0.83 | Q9: 77 | R9: 46291 | S9: =IF(R9="","",'Como ler'!$B$27-R9) -> 1 | T9: 0 | V9: Negócios e empreendedorismo | W9: Negócios e empreendedorismo, Entretenimento e humor | X9: Alta | Y9: =ROUND(IF(K9="",0,MIN(40,40*K9/1.5))+IF(S9="",0,IF(S9<=7,20,IF(S9<=30,12,IF(S9<=90,5,0))))+IF(Q9="",0,MIN(15,Q9*5))+IF(O9="",0,MIN(15,O9*30))+IF(E9="Criador(a)",10,IF(E9="Especialista que cria conteúdo",6,4)),0) -> 54 | Z9: Digital creator | AD9: Itajaí: 9 post(s) marcados | AE9: Itajaí (9), Estefano Jose Vanolli (1), Pizzaria Herois da Pizza (1) | AF9: 🎙️ FALA COMIGO RAPAZEADA / 🎤 Influencer • Empresário • Comunicador / 📲 Publicidades • @agenciachammma | AG9: https://instagram.com/gabryelnuness | AH9: Não contatada
A10: Itajaí | B10: Balneário Camboriú | C10: @julianadomareski | D10: Juliana Domareski | E10: Especialista que cria conteúdo | F10: Mulher | G10: 65364 | H10: Média (30k–100k) | I10: 0.0039 | J10: =IFERROR(INDEX('Como ler'!$B$20:$B$24,MATCH(H10,'Como ler'!$A$20:$A$24,0)),"") -> 0.015 | K10: =IF(OR(I10="",J10=""),"",I10/J10) -> 0.26 | L10: 339 | M10: 7.1 | N10: 5204 | O10: =IF(OR(N10="",G10=0),"",N10/G10) -> 0.079615691 | P10: 0.7 | Q10: 2.1 | R10: 46291 | S10: =IF(R10="","",'Como ler'!$B$27-R10) -> 1 | T10: 0 | V10: Viagem | W10: Viagem, Negócios e empreendedorismo, Casa e organização | X10: Alta | Y10: =ROUND(IF(K10="",0,MIN(40,40*K10/1.5))+IF(S10="",0,IF(S10<=7,20,IF(S10<=30,12,IF(S10<=90,5,0))))+IF(Q10="",0,MIN(15,Q10*5))+IF(O10="",0,MIN(15,O10*30))+IF(E10="Criador(a)",10,IF(E10="Especialista que cria conteúdo",6,4)),0) -> 46 | Z10: None | AA10: Sim | AB10: Sim | AD10: Itajaí: bio, 2 post(s) marcados; Balneário Camboriú: bio, 2 post(s) marcados | AE10: Imobiliária Terra (3), Balneário Camboriú (2), Praia Brava - Itajaí/SC (2), Copacabana, Rio de Janeiro (1) | AF10: CEO / Grupo Domma | @terra_imobiliaria / Estruturação de operações imobiliárias para quem quer multiplicar capital. / Balneário Camboriú • Praia Brava • SC | AG10: https://instagram.com/julianadomareski | AH10: Não contatada
A11: Itajaí | C11: @gabyoliveirasc | D11: Gabriela Oliveira | Casamento cristão & Vida real | E11: Especialista que cria conteúdo | F11: Mulher | G11: 52669 | H11: Média (30k–100k) | I11: 0.002 | J11: =IFERROR(INDEX('Como ler'!$B$20:$B$24,MATCH(H11,'Como ler'!$A$20:$A$24,0)),"") -> 0.015 | K11: =IF(OR(I11="",J11=""),"",I11/J11) -> 0.13333333 | L11: 92 | M11: 7.3 | N11: 1675 | O11: =IF(OR(N11="",G11=0),"",N11/G11) -> 0.031802389 | P11: 0.27 | Q11: 5 | R11: 46286 | S11: =IF(R11="","",'Como ler'!$B$27-R11) -> 6 | T11: 0 | V11: Relacionamento | W11: Relacionamento, Família e maternidade, Lifestyle, Educação e conhecimento | X11: Média | Y11: =ROUND(IF(K11="",0,MIN(40,40*K11/1.5))+IF(S11="",0,IF(S11<=7,20,IF(S11<=30,12,IF(S11<=90,5,0))))+IF(Q11="",0,MIN(15,Q11*5))+IF(O11="",0,MIN(15,O11*30))+IF(E11="Criador(a)",10,IF(E11="Especialista que cria conteúdo",6,4)),0) -> 46 | Z11: Digital creator | AD11: Itajaí: bio, 2 post(s) marcados | AE11: Itajaí -SC (2) | AF11: Psicóloga • Terapeuta de casais • Esposa / Mãe do Joaquim, à espera do Jonatas 🤰🏻 / ✝️ Fé, casamento & vida real / 📍 Itajaí/SC | AG11: https://instagram.com/gabyoliveirasc | AH11: Não contatada
A12: Itajaí | B12: Balneário Camboriú | C12: @tatypassos__ | D12: Taty Passos | Explore SC | E12: Criador(a) | F12: Mulher | G12: 48271 | H12: Média (30k–100k) | I12: 0.0009 | J12: =IFERROR(INDEX('Como ler'!$B$20:$B$24,MATCH(H12,'Como ler'!$A$20:$A$24,0)),"") -> 0.015 | K12: =IF(OR(I12="",J12=""),"",I12/J12) -> 0.06 | L12: 37 | M12: 7 | N12: 286 | O12: =IF(OR(N12="",G12=0),"",N12/G12) -> 0.0059248824 | P12: 0.56 | Q12: 0.8 | R12: 46292 | S12: =IF(R12="","",'Como ler'!$B$27-R12) -> 0 | T12: 0 | V12: Gastronomia | W12: Gastronomia, Beleza, Entretenimento e humor, Casa e organização | X12: Alta | Y12: =ROUND(IF(K12="",0,MIN(40,40*K12/1.5))+IF(S12="",0,IF(S12<=7,20,IF(S12<=30,12,IF(S12<=90,5,0))))+IF(Q12="",0,MIN(15,Q12*5))+IF(O12="",0,MIN(15,O12*30))+IF(E12="Criador(a)",10,IF(E12="Especialista que cria conteúdo",6,4)),0) -> 36 | Z12: Digital creator | AB12: Sim | AD12: Itajaí: 1 post(s) marcados; Balneário Camboriú: 1 post(s) marcados | AE12: Balneário Piçarras (2), Curitiba, Paraná (1), Balneário Piçarras - SC (1), Itajaí (1) | AF12: 🦋Os padrões de beleza que lutem para se encaixar em mim! / 🚀Foguete tem ré sim, mas não comigo / 🍽️Gastronomia & Humor / @exploresantacatarina @casadataty__ | AG12: https://instagram.com/tatypassos__ | AH12: Não contatada
A13: Itajaí | C13: @toemdrika | D13: Drika | Influenciadora em Santa Catarina | E13: Criador(a) | F13: Mulher | G13: 42854 | H13: Média (30k–100k) | I13: 0.0101 | J13: =IFERROR(INDEX('Como ler'!$B$20:$B$24,MATCH(H13,'Como ler'!$A$20:$A$24,0)),"") -> 0.015 | K13: =IF(OR(I13="",J13=""),"",I13/J13) -> 0.67333333 | L13: 769 | M13: 80.4 | N13: 3651 | O13: =IF(OR(N13="",G13=0),"",N13/G13) -> 0.085196248 | P13: 1 | Q13: 6.4 | R13: 46288 | S13: =IF(R13="","",'Como ler'!$B$27-R13) -> 4 | T13: 1 | U13: @promenacmotoshonda | V13: Fitness e wellness | W13: Fitness e wellness, Lifestyle | X13: Média | Y13: =ROUND(IF(K13="",0,MIN(40,40*K13/1.5))+IF(S13="",0,IF(S13<=7,20,IF(S13<=30,12,IF(S13<=90,5,0))))+IF(Q13="",0,MIN(15,Q13*5))+IF(O13="",0,MIN(15,O13*30))+IF(E13="Criador(a)",10,IF(E13="Especialista que cria conteúdo",6,4)),0) -> 66 | AC13: email | AD13: Itajaí: bio, 3 post(s) marcados | AE13: Itajaí (3), Piçarras (1) | AF13: 📍Baiana em Itajaí / 📧 [e-mail na bio] / 🏋🏾‍♀️Embaixadora @pratiquefitness / Quer se mudar pra SC? Eu te ajudo👇 | AG13: https://instagram.com/toemdrika | AH13: Não contatada
A14: Itajaí | B14: Itapema | C14: @mordomorodrigo_oficial | D14: Mordomo Rodrig️o | E14: Criador(a) | F14: Homem | G14: 27951 | H14: Micro (3k–30k) | I14: 0.0096 | J14: =IFERROR(INDEX('Como ler'!$B$20:$B$24,MATCH(H14,'Como ler'!$A$20:$A$24,0)),"") -> 0.025 | K14: =IF(OR(I14="",J14=""),"",I14/J14) -> 0.384 | L14: 200 | M14: 38.7 | N14: 2117 | O14: =IF(OR(N14="",G14=0),"",N14/G14) -> 0.075739687 | P14: 0.9 | Q14: 1.4 | R14: 46291 | S14: =IF(R14="","",'Como ler'!$B$27-R14) -> 1 | T14: 0 | V14: Relacionamento | W14: Relacionamento | X14: Baixa | Y14: =ROUND(IF(K14="",0,MIN(40,40*K14/1.5))+IF(S14="",0,IF(S14<=7,20,IF(S14<=30,12,IF(S14<=90,5,0))))+IF(Q14="",0,MIN(15,Q14*5))+IF(O14="",0,MIN(15,O14*30))+IF(E14="Criador(a)",10,IF(E14="Especialista que cria conteúdo",6,4)),0) -> 50 | AD14: Itajaí: bio, 1 post(s) marcados; Itapema: 2 post(s) marcados | AE14: Itapema, Santa Catarina, Brazil (2), Florianópolis, Santa Catarina, Brasil (2), Brasil Santa Catarina (1), Praia Brava - Itajaí/SC (1) | AF14: ⚫Influencer/Itajaí SC / PR 😊 / ⚫Mordomo de noivas / ⚫Mordomo das estrelas / ⚫Modelo/Ator/Bailarino / ⚫️❤️🔒🥰 | AG14: https://instagram.com/mordomorodrigo_oficial | AH14: Não contatada
A15: Itajaí | C15: @herique.finatto | D15: Herique Finato | E15: Criador(a) | F15: Homem | G15: 25575 | H15: Micro (3k–30k) | I15: 0.0076 | J15: =IFERROR(INDEX('Como ler'!$B$20:$B$24,MATCH(H15,'Como ler'!$A$20:$A$24,0)),"") -> 0.025 | K15: =IF(OR(I15="",J15=""),"",I15/J15) -> 0.304 | L15: 869 | M15: 2.4 | N15: 3882 | O15: =IF(OR(N15="",G15=0),"",N15/G15) -> 0.15178886 | P15: 0.92 | Q15: 4.8 | R15: 46292 | S15: =IF(R15="","",'Como ler'!$B$27-R15) -> 0 | T15: 0 | V15: Lifestyle | W15: Lifestyle, Fitness e wellness | X15: Média | Y15: =ROUND(IF(K15="",0,MIN(40,40*K15/1.5))+IF(S15="",0,IF(S15<=7,20,IF(S15<=30,12,IF(S15<=90,5,0))))+IF(Q15="",0,MIN(15,Q15*5))+IF(O15="",0,MIN(15,O15*30))+IF(E15="Criador(a)",10,IF(E15="Especialista que cria conteúdo",6,4)),0) -> 58 | AD15: Itajaí: 1 post(s) marcados | AE15: Praia Brava - Itajai (1) | AF15: 🔥 Criador de conteúdo / 🏋🏼 Minha rotina diária nos stories / 🌱Inspirando uma vida saudável e ativa | AG15: https://instagram.com/herique.finatto | AH15: Não contatada
A16: Itajaí | B16: Balneário Camboriú | C16: @shophome.brasil | D16: Shophome | Dicas BC, Itajaí e Região | E16: Página local / guia | F16: Página/marca | G16: 20687 | H16: Micro (3k–30k) | I16: 0.0019 | J16: =IFERROR(INDEX('Como ler'!$B$20:$B$24,MATCH(H16,'Como ler'!$A$20:$A$24,0)),"") -> 0.025 | K16: =IF(OR(I16="",J16=""),"",I16/J16) -> 0.076 | L16: 40 | M16: 7.8 | N16: 867 | O16: =IF(OR(N16="",G16=0),"",N16/G16) -> 0.041910378 | P16: 1 | Q16: 2.4 | R16: 45935 | S16: =IF(R16="","",'Como ler'!$B$27-R16) -> 357 | T16: 0 | V16: Entretenimento e humor | W16: Entretenimento e humor, Dicas locais, Lifestyle, Casa e organização | X16: Alta | Y16: =ROUND(IF(K16="",0,MIN(40,40*K16/1.5))+IF(S16="",0,IF(S16<=7,20,IF(S16<=30,12,IF(S16<=90,5,0))))+IF(Q16="",0,MIN(15,Q16*5))+IF(O16="",0,MIN(15,O16*30))+IF(E16="Criador(a)",10,IF(E16="Especialista que cria conteúdo",6,4)),0) -> 19 | Z16: None | AB16: Sim | AD16: Itajaí: bio; Balneário Camboriú: bio | AF16: 💙Dicas, dia a dia e humor / 📍 Indicações em BC, Itajaí e região / ⬇️ Entre no grupo de ofertas | AG16: https://instagram.com/shophome.brasil | AH16: Não contatada
A17: Itajaí | B17: Balneário Camboriú | C17: @isabelaonofre | D17: Isabela Onofre | E17: Criador(a) | F17: Mulher | G17: 20124 | H17: Micro (3k–30k) | I17: 0.0049 | J17: =IFERROR(INDEX('Como ler'!$B$20:$B$24,MATCH(H17,'Como ler'!$A$20:$A$24,0)),"") -> 0.025 | K17: =IF(OR(I17="",J17=""),"",I17/J17) -> 0.196 | L17: 80 | M17: 32.9 | N17: 845 | O17: =IF(OR(N17="",G17=0),"",N17/G17) -> 0.041989664 | P17: 0.89 | Q17: 5.1 | R17: 46292 | S17: =IF(R17="","",'Como ler'!$B$27-R17) -> 0 | T17: 0 | V17: Fitness e wellness | W17: Fitness e wellness, Dicas locais, Moda | X17: Média | Y17: =ROUND(IF(K17="",0,MIN(40,40*K17/1.5))+IF(S17="",0,IF(S17<=7,20,IF(S17<=30,12,IF(S17<=90,5,0))))+IF(Q17="",0,MIN(15,Q17*5))+IF(O17="",0,MIN(15,O17*30))+IF(E17="Criador(a)",10,IF(E17="Especialista que cria conteúdo",6,4)),0) -> 51 | AA17: Sim | AC17: email | AD17: Balneário Camboriú: 1 post(s) marcados; Itajaí: 3 post(s) marcados | AE17: Itajaí -SC (3), Balneário Camboriú (1), Estação Azul (1), Monthez Hotel & Eventos (1) | AF17: Dicas, treinos, looks e uns surtos de uma geminiana 30+ 💖✌🏻 / “ME DIVERTINDO NO DESCONFORTO” / 💌 Parcerias: [e-mail na bio] | AG17: https://instagram.com/isabelaonofre | AH17: Não contatada
A18: Itajaí | C18: @bevieiraa | D18: Beatriz Vieira | Maquiadora | E18: Criador(a) | F18: Mulher | G18: 17162 | H18: Micro (3k–30k) | I18: 0.0044 | J18: =IFERROR(INDEX('Como ler'!$B$20:$B$24,MATCH(H18,'Como ler'!$A$20:$A$24,0)),"") -> 0.025 | K18: =IF(OR(I18="",J18=""),"",I18/J18) -> 0.176 | L18: 102 | M18: 9.9 | N18: 581 | O18: =IF(OR(N18="",G18=0),"",N18/G18) -> 0.033853863 | P18: 0.67 | Q18: 1.8 | R18: 46291 | S18: =IF(R18="","",'Como ler'!$B$27-R18) -> 1 | T18: 0 | V18: Beleza | W18: Beleza, Viagem, Negócios e empreendedorismo, Educação e conhecimento | X18: Alta | Y18: =ROUND(IF(K18="",0,MIN(40,40*K18/1.5))+IF(S18="",0,IF(S18<=7,20,IF(S18<=30,12,IF(S18<=90,5,0))))+IF(Q18="",0,MIN(15,Q18*5))+IF(O18="",0,MIN(15,O18*30))+IF(E18="Criador(a)",10,IF(E18="Especialista que cria conteúdo",6,4)),0) -> 45 | Z18: Beauty, cosmetic & personal care | AB18: Sim | AD18: Itajaí: bio, 1 post(s) marcados | AE18: Curacao Caribe (1), Itajaí (1), Bloove • Be Vieira (1) | AF18: Beauty, viagens & vida real / Itajaí | SC / Makeup Artist há 12 anos / Fundadora da @bloovebeauty / 💌 Agendamentos • Orçamentos • Cursos • Publicidade ↓ | AG18: https://instagram.com/bevieiraa | AH18: Não contatada
A19: Itajaí | C19: @melissagmenezes | D19: Melissa Menezes | E19: Criador(a) | F19: Mulher | G19: 16490 | H19: Micro (3k–30k) | I19: 0.0101 | J19: =IFERROR(INDEX('Como ler'!$B$20:$B$24,MATCH(H19,'Como ler'!$A$20:$A$24,0)),"") -> 0.025 | K19: =IF(OR(I19="",J19=""),"",I19/J19) -> 0.404 | L19: 162 | M19: 59.8 | N19: 7430 | O19: =IF(OR(N19="",G19=0),"",N19/G19) -> 0.45057611 | P19: 0.18 | Q19: 17.5 | R19: 46292 | S19: =IF(R19="","",'Como ler'!$B$27-R19) -> 0 | T19: 0 | V19: Casa e organização | W19: Casa e organização, Família e maternidade, Educação e conhecimento, Dicas locais | X19: Alta | Y19: =ROUND(IF(K19="",0,MIN(40,40*K19/1.5))+IF(S19="",0,IF(S19<=7,20,IF(S19<=30,12,IF(S19<=90,5,0))))+IF(Q19="",0,MIN(15,Q19*5))+IF(O19="",0,MIN(15,O19*30))+IF(E19="Criador(a)",10,IF(E19="Especialista que cria conteúdo",6,4)),0) -> 69 | Z19: Digital creator | AA19: Sim | AB19: Sim | AD19: Itajaí: bio, 11 post(s) marcados | AE19: Itajaí -SC (6), Itajaí (4), Itajaí, Santa Catarina, Brasil (1) | AF19: Itajai-SC - Vegetariana 🌱 Voluntária da causa animal 🐶💖😺 Maquiadora, Profª de Inglês. Mãe de 4🐶🐶🐶🐶 Lar Temporário do Bento 🐶 | AG19: https://instagram.com/melissagmenezes | AH19: Não contatada
A20: Itajaí | C20: @divulgaitajai | D20: DIVULGA ITAJAÍ | E20: Página local / guia | F20: Página/marca | G20: 15574 | H20: Micro (3k–30k) | I20: 0.0039 | J20: =IFERROR(INDEX('Como ler'!$B$20:$B$24,MATCH(H20,'Como ler'!$A$20:$A$24,0)),"") -> 0.025 | K20: =IF(OR(I20="",J20=""),"",I20/J20) -> 0.156 | L20: 68 | M20: 7.2 | N20: 228 | O20: =IF(OR(N20="",G20=0),"",N20/G20) -> 0.014639784 | P20: 0.36 | Q20: 3.2 | R20: 46290 | S20: =IF(R20="","",'Como ler'!$B$27-R20) -> 2 | T20: 0 | V20: Dicas locais | W20: Dicas locais, Educação e conhecimento | X20: Baixa | Y20: =ROUND(IF(K20="",0,MIN(40,40*K20/1.5))+IF(S20="",0,IF(S20<=7,20,IF(S20<=30,12,IF(S20<=90,5,0))))+IF(Q20="",0,MIN(15,Q20*5))+IF(O20="",0,MIN(15,O20*30))+IF(E20="Criador(a)",10,IF(E20="Especialista que cria conteúdo",6,4)),0) -> 44 | Z20: Community | AB20: Sim | AD20: Itajaí: bio, 5 post(s) marcados | AE20: Itajaí, Santa Catarina, Brasil (2), Alfa Bile (2), Molhes da Barra Itajaí (2), Disk Água Bebí (1) | AF20: 💙 Itajaí por @alfabile / ⚓️ Paisagens | Cotidiano | Arte / ✨ O olhar mais apaixonado pela nossa cidade / 👇 Wallpapers exclusivos e Dicas no Canal | AG20: https://instagram.com/divulgaitajai | AH20: Não contatada | AI20: Curtidas ocultas: engajamento calculado só com posts visíveis ou indisponível
A21: Itajaí | B21: Balneário Camboriú | C21: @solaynesantos | D21: ꜱᴏʟ - Influencer, Social Media & Videomaker | Itajaí | E21: Criador(a) | F21: Mulher | G21: 13517 | H21: Micro (3k–30k) | I21: 0.0056 | J21: =IFERROR(INDEX('Como ler'!$B$20:$B$24,MATCH(H21,'Como ler'!$A$20:$A$24,0)),"") -> 0.025 | K21: =IF(OR(I21="",J21=""),"",I21/J21) -> 0.224 | L21: 591 | M21: 17.8 | N21: 621 | O21: =IF(OR(N21="",G21=0),"",N21/G21) -> 0.045942147 | P21: 0.67 | Q21: 4 | R21: 46290 | S21: =IF(R21="","",'Como ler'!$B$27-R21) -> 2 | T21: 0 | V21: Gastronomia | W21: Gastronomia, Social mídia e conteúdo | X21: Alta | Y21: =ROUND(IF(K21="",0,MIN(40,40*K21/1.5))+IF(S21="",0,IF(S21<=7,20,IF(S21<=30,12,IF(S21<=90,5,0))))+IF(Q21="",0,MIN(15,Q21*5))+IF(O21="",0,MIN(15,O21*30))+IF(E21="Criador(a)",10,IF(E21="Especialista que cria conteúdo",6,4)),0) -> 52 | Z21: Digital creator | AC21: email | AD21: Itajaí: bio, 4 post(s) marcados; Balneário Camboriú: 2 post(s) marcados | AE21: Itajaí, Santa Catarina, Brasil (3), Balneário Camboriú (2), New Shoes Itajaí (1), Central Pádel Br (1) | AF21: 📱Influencer, Social Media & Videomaker / ✈️ Paulista em SC |📍Itajaí SC / 💡Criando conteúdo autêntico para sua marca! / 💌 [e-mail na bio] | AG21: https://instagram.com/solaynesantos | AH21: Não contatada
A22: Itajaí | C22: @brigadeiroealecrim | D22: Brigadeiro e Alecrim ® - Balneário Camboriú | E22: Criador(a) | F22: Mulher | G22: 12449 | H22: Micro (3k–30k) | I22: 0.0036 | J22: =IFERROR(INDEX('Como ler'!$B$20:$B$24,MATCH(H22,'Como ler'!$A$20:$A$24,0)),"") -> 0.025 | K22: =IF(OR(I22="",J22=""),"",I22/J22) -> 0.144 | L22: 45 | M22: 6.3 | N22: 480 | O22: =IF(OR(N22="",G22=0),"",N22/G22) -> 0.038557314 | P22: 0.7 | Q22: 1.4 | R22: 46278 | S22: =IF(R22="","",'Como ler'!$B$27-R22) -> 14 | T22: 0 | V22: Gastronomia | W22: Gastronomia | X22: Baixa | Y22: =ROUND(IF(K22="",0,MIN(40,40*K22/1.5))+IF(S22="",0,IF(S22<=7,20,IF(S22<=30,12,IF(S22<=90,5,0))))+IF(Q22="",0,MIN(15,Q22*5))+IF(O22="",0,MIN(15,O22*30))+IF(E22="Criador(a)",10,IF(E22="Especialista que cria conteúdo",6,4)),0) -> 34 | AB22: Sim | AD22: Itajaí: 7 post(s) marcados | AE22: Itajaí (7), Fazzenda Park Resort (1) | AF22: Depois de 10 anos entre panelas e doces, / resolvi experimentar o outro lado da mesa. / Aqui tem experiências que eu realmente acho que valem a pena! | AG22: https://instagram.com/brigadeiroealecrim | AH22: Não contatada
A23: Itajaí | C23: @eubarbaraabreu | D23: Bárbara Abreu | E23: Criador(a) | F23: Mulher | G23: 12418 | H23: Micro (3k–30k) | J23: =IFERROR(INDEX('Como ler'!$B$20:$B$24,MATCH(H23,'Como ler'!$A$20:$A$24,0)),"") -> 0.025 | K23: =IF(OR(I23="",J23=""),"",I23/J23) | M23: 11 | N23: 178 | O23: =IF(OR(N23="",G23=0),"",N23/G23) -> 0.014334031 | P23: 0.2 | Q23: 0.2 | R23: 46291 | S23: =IF(R23="","",'Como ler'!$B$27-R23) -> 1 | T23: 0 | V23: Beleza | W23: Beleza, Gastronomia | X23: Média | Y23: =ROUND(IF(K23="",0,MIN(40,40*K23/1.5))+IF(S23="",0,IF(S23<=7,20,IF(S23<=30,12,IF(S23<=90,5,0))))+IF(Q23="",0,MIN(15,Q23*5))+IF(O23="",0,MIN(15,O23*30))+IF(E23="Criador(a)",10,IF(E23="Especialista que cria conteúdo",6,4)),0) -> 31 | Z23: Digital creator | AC23: email | AD23: Itajaí: bio, 7 post(s) marcados | AE23: Itajaí (2), Itajaí -SC (2), Laviér Store Itajaí (1), Mercure Itajai Navegantes (1) | AF23: Bem-vinda(o)! / 👑 Miss Supranational Itajaí 2025 / 💌 [e-mail na bio] | AG23: https://instagram.com/eubarbaraabreu | AH23: Não contatada | AI23: Curtidas ocultas: engajamento calculado só com posts visíveis ou indisponível
A24: Itajaí | C24: @omelhordeitajai | E24: Página local / guia | F24: Página/marca | G24: 12104 | H24: Micro (3k–30k) | I24: 0.0051 | J24: =IFERROR(INDEX('Como ler'!$B$20:$B$24,MATCH(H24,'Como ler'!$A$20:$A$24,0)),"") -> 0.025 | K24: =IF(OR(I24="",J24=""),"",I24/J24) -> 0.204 | L24: 94 | M24: 1.8 | N24: 882 | O24: =IF(OR(N24="",G24=0),"",N24/G24) -> 0.072868473 | P24: 0.67 | Q24: 7.7 | R24: 46289 | S24: =IF(R24="","",'Como ler'!$B$27-R24) -> 3 | T24: 0 | V24: Viagem | W24: Viagem | X24: Baixa | Y24: =ROUND(IF(K24="",0,MIN(40,40*K24/1.5))+IF(S24="",0,IF(S24<=7,20,IF(S24<=30,12,IF(S24<=90,5,0))))+IF(Q24="",0,MIN(15,Q24*5))+IF(O24="",0,MIN(15,O24*30))+IF(E24="Criador(a)",10,IF(E24="Especialista que cria conteúdo",6,4)),0) -> 47 | AB24: Sim | AD24: Itajaí: bio | AF24: O destino começa aqui. / Belezas, sabores e experiências de Itajaí. / 🌊 Explore o melhor da cidade / Por: @itajaiconvention | AG24: https://instagram.com/omelhordeitajai | AH24: Não contatada
A25: Itajaí | C25: @lu.monaly | D25: Luciana Monaly | E25: Criador(a) | F25: Mulher | G25: 11743 | H25: Micro (3k–30k) | I25: 0.0063 | J25: =IFERROR(INDEX('Como ler'!$B$20:$B$24,MATCH(H25,'Como ler'!$A$20:$A$24,0)),"") -> 0.025 | K25: =IF(OR(I25="",J25=""),"",I25/J25) -> 0.252 | L25: 143 | M25: 4.8 | N25: 1539 | O25: =IF(OR(N25="",G25=0),"",N25/G25) -> 0.1310568 | P25: 0.91 | Q25: 0.9 | R25: 46291 | S25: =IF(R25="","",'Como ler'!$B$27-R25) -> 1 | T25: 0 | X25: Baixa | Y25: =ROUND(IF(K25="",0,MIN(40,40*K25/1.5))+IF(S25="",0,IF(S25<=7,20,IF(S25<=30,12,IF(S25<=90,5,0))))+IF(Q25="",0,MIN(15,Q25*5))+IF(O25="",0,MIN(15,O25*30))+IF(E25="Criador(a)",10,IF(E25="Especialista que cria conteúdo",6,4)),0) -> 45 | AD25: Itajaí: bio, 10 post(s) marcados | AE25: Itajaí -SC (6), Santa Catarina Itajai (4) | AF25: Itajaí SC / Modelo / Maquiadora- @monaly.makeup / Publicidade e Propaganda, Atriz por: @escolawolfmaya🎬 | AG25: https://instagram.com/lu.monaly | AH25: Não contatada
A26: Itajaí | C26: @cademinhascoisas | D26: Cadê Minhas Coisas? • Soluções em Organização | E26: Especialista que cria conteúdo | F26: Página/marca | G26: 10806 | H26: Micro (3k–30k) | I26: 0.0038 | J26: =IFERROR(INDEX('Como ler'!$B$20:$B$24,MATCH(H26,'Como ler'!$A$20:$A$24,0)),"") -> 0.025 | K26: =IF(OR(I26="",J26=""),"",I26/J26) -> 0.152 | L26: 50 | M26: 4.8 | N26: 376 | O26: =IF(OR(N26="",G26=0),"",N26/G26) -> 0.034795484 | P26: 0.78 | Q26: 2.7 | R26: 46245 | S26: =IF(R26="","",'Como ler'!$B$27-R26) -> 47 | T26: 0 | V26: Casa e organização | W26: Casa e organização, Família e maternidade | X26: Alta | Y26: =ROUND(IF(K26="",0,MIN(40,40*K26/1.5))+IF(S26="",0,IF(S26<=7,20,IF(S26<=30,12,IF(S26<=90,5,0))))+IF(Q26="",0,MIN(15,Q26*5))+IF(O26="",0,MIN(15,O26*30))+IF(E26="Criador(a)",10,IF(E26="Especialista que cria conteúdo",6,4)),0) -> 30 | AA26: Sim | AB26: Sim | AD26: Itajaí: bio | AF26: Desde 2013 transformando lares (e vidas!) 💖 / 📍 Curitiba | Itajaí | BC / Para orçamentos, clique no link abaixo 👇🏼 | AG26: https://instagram.com/cademinhascoisas | AH26: Não contatada
A27: Itajaí | C27: @bruna_alika | D27: Bruna Alika | E27: Criador(a) | F27: Mulher | G27: 10620 | H27: Micro (3k–30k) | I27: 0.0017 | J27: =IFERROR(INDEX('Como ler'!$B$20:$B$24,MATCH(H27,'Como ler'!$A$20:$A$24,0)),"") -> 0.025 | K27: =IF(OR(I27="",J27=""),"",I27/J27) -> 0.068 | L27: 23 | M27: 2.5 | N27: 414 | O27: =IF(OR(N27="",G27=0),"",N27/G27) -> 0.038983051 | P27: 1 | Q27: 3.5 | R27: 46292 | S27: =IF(R27="","",'Como ler'!$B$27-R27) -> 0 | T27: 0 | V27: Negócios e empreendedorismo | W27: Negócios e empreendedorismo, Família e maternidade, Gastronomia | X27: Alta | Y27: =ROUND(IF(K27="",0,MIN(40,40*K27/1.5))+IF(S27="",0,IF(S27<=7,20,IF(S27<=30,12,IF(S27<=90,5,0))))+IF(Q27="",0,MIN(15,Q27*5))+IF(O27="",0,MIN(15,O27*30))+IF(E27="Criador(a)",10,IF(E27="Especialista que cria conteúdo",6,4)),0) -> 48 | Z27: Digital creator | AB27: Sim | AD27: Itajaí: bio, 6 post(s) marcados | AE27: Itajaí (6), Arena Bombinhas (2) | AF27: Mulher Multifunções ligada no 220🤣 / + 15mil já dançaram comigo / 💻CEO @tourpexero / 💃@grupofloreser_ / ✨Dança @prefeituradeitajai / 🙏Mãe de 3 / Parceria | AG27: https://instagram.com/bruna_alika | AH27: Não contatada
A28: Itajaí | C28: @millycristt | D28: Emilly Cristine | StoryMaker e VideoMaker | E28: Especialista que cria conteúdo | F28: Mulher | G28: 10401 | H28: Micro (3k–30k) | I28: 0.0358 | J28: =IFERROR(INDEX('Como ler'!$B$20:$B$24,MATCH(H28,'Como ler'!$A$20:$A$24,0)),"") -> 0.025 | K28: =IF(OR(I28="",J28=""),"",I28/J28) -> 1.432 | L28: 994 | M28: 47.2 | N28: 4044 | O28: =IF(OR(N28="",G28=0),"",N28/G28) -> 0.38880877 | P28: 0.64 | Q28: 1.3 | R28: 46289 | S28: =IF(R28="","",'Como ler'!$B$27-R28) -> 3 | T28: 0 | V28: Social mídia e conteúdo | W28: Social mídia e conteúdo | X28: Alta | Y28: =ROUND(IF(K28="",0,MIN(40,40*K28/1.5))+IF(S28="",0,IF(S28<=7,20,IF(S28<=30,12,IF(S28<=90,5,0))))+IF(Q28="",0,MIN(15,Q28*5))+IF(O28="",0,MIN(15,O28*30))+IF(E28="Criador(a)",10,IF(E28="Especialista que cria conteúdo",6,4)),0) -> 82 | AB28: Sim | AD28: Itajaí: bio | AE28: Santa Catarina (1) | AF28: 🚀 | Transformo a sua ideia em um conteúdo impactante / 🤳🏼 | Fotografia • Vídeo • Real Time / 📍 | Itajaí e região / Eternize seu momento ⬇️ | AG28: https://instagram.com/millycristt | AH28: Não contatada
A29: Itajaí | C29: @thais_araujo.7 | D29: Thais | E29: Criador(a) | F29: Mulher | G29: 10330 | H29: Micro (3k–30k) | I29: 0.0251 | J29: =IFERROR(INDEX('Como ler'!$B$20:$B$24,MATCH(H29,'Como ler'!$A$20:$A$24,0)),"") -> 0.025 | K29: =IF(OR(I29="",J29=""),"",I29/J29) -> 1.004 | L29: 301 | M29: 9.9 | N29: 2782 | O29: =IF(OR(N29="",G29=0),"",N29/G29) -> 0.26931268 | P29: 0.43 | Q29: 0 | R29: 46267 | S29: =IF(R29="","",'Como ler'!$B$27-R29) -> 25 | T29: 0 | V29: UGC | W29: UGC, Dicas locais | X29: Alta | Y29: =ROUND(IF(K29="",0,MIN(40,40*K29/1.5))+IF(S29="",0,IF(S29<=7,20,IF(S29<=30,12,IF(S29<=90,5,0))))+IF(Q29="",0,MIN(15,Q29*5))+IF(O29="",0,MIN(15,O29*30))+IF(E29="Criador(a)",10,IF(E29="Especialista que cria conteúdo",6,4)),0) -> 57 | Z29: Digital creator | AB29: Sim | AD29: Itajaí: bio | AE29: Speedway Music Park (1), Chile (1), Lagoa Misteriosa (1) | AF29: 🌎 Lugares, sabores & aventuras / ✨ Transformando experiências em histórias / 📍 Itajaí • SC | UGC Creator / Bora viver essa experiência comigo? | AG29: https://instagram.com/thais_araujo.7 | AH29: Não contatada
A30: Itajaí | C30: @gabxmelo | D30: Gabi Melo 🌻 | E30: Criador(a) | F30: Mulher | G30: 9953 | H30: Micro (3k–30k) | I30: 0.0202 | J30: =IFERROR(INDEX('Como ler'!$B$20:$B$24,MATCH(H30,'Como ler'!$A$20:$A$24,0)),"") -> 0.025 | K30: =IF(OR(I30="",J30=""),"",I30/J30) -> 0.808 | L30: 255 | M30: 16.5 | O30: =IF(OR(N30="",G30=0),"",N30/G30) | P30: 0 | Q30: 0.3 | R30: 46258 | S30: =IF(R30="","",'Como ler'!$B$27-R30) -> 34 | T30: 0 | V30: Moda | W30: Moda | X30: Média | Y30: =ROUND(IF(K30="",0,MIN(40,40*K30/1.5))+IF(S30="",0,IF(S30<=7,20,IF(S30<=30,12,IF(S30<=90,5,0))))+IF(Q30="",0,MIN(15,Q30*5))+IF(O30="",0,MIN(15,O30*30))+IF(E30="Criador(a)",10,IF(E30="Especialista que cria conteúdo",6,4)),0) -> 38 | Z30: Personal blog | AD30: Itajaí: 3 post(s) marcados | AE30: Itajaí -SC (1), Praia Brava - Itajaí/SC (1), Santa Catarina Itajai (1) | AF30: SC 📍 / Comércio exterior 🛳️ / 🏳️‍🌈 | AG30: https://instagram.com/gabxmelo | AH30: Não contatada
A31: Itajaí | C31: @joanakathelen | D31: Joana Kathelen | E31: Criador(a) | F31: Mulher | G31: 9612 | H31: Micro (3k–30k) | I31: 0.0031 | J31: =IFERROR(INDEX('Como ler'!$B$20:$B$24,MATCH(H31,'Como ler'!$A$20:$A$24,0)),"") -> 0.025 | K31: =IF(OR(I31="",J31=""),"",I31/J31) -> 0.124 | L31: 28 | M31: 3.7 | N31: 336 | O31: =IF(OR(N31="",G31=0),"",N31/G31) -> 0.034956305 | P31: 0.5 | Q31: 0.2 | R31: 46263 | S31: =IF(R31="","",'Como ler'!$B$27-R31) -> 29 | T31: 0 | V31: Família e maternidade | W31: Família e maternidade | X31: Média | Y31: =ROUND(IF(K31="",0,MIN(40,40*K31/1.5))+IF(S31="",0,IF(S31<=7,20,IF(S31<=30,12,IF(S31<=90,5,0))))+IF(Q31="",0,MIN(15,Q31*5))+IF(O31="",0,MIN(15,O31*30))+IF(E31="Criador(a)",10,IF(E31="Especialista que cria conteúdo",6,4)),0) -> 27 | AD31: Itajaí: 11 post(s) marcados | AE31: Itajaí (8), Centro De Itajai Santa Catarina. (3) | AF31: 🌸 Mãe de dois príncipes / 💙@heitorbitencourt1 / 💚@henriquebitencourt2 / 💼 @serpa.log | AG31: https://instagram.com/joanakathelen | AH31: Não contatada
A32: Itajaí | C32: @n1kx_x | D32: Nicolly Machado - UGC Creator | E32: Criador(a) | F32: Mulher | G32: 9577 | H32: Micro (3k–30k) | I32: 0.0242 | J32: =IFERROR(INDEX('Como ler'!$B$20:$B$24,MATCH(H32,'Como ler'!$A$20:$A$24,0)),"") -> 0.025 | K32: =IF(OR(I32="",J32=""),"",I32/J32) -> 0.968 | L32: 258 | M32: 14.4 | O32: =IF(OR(N32="",G32=0),"",N32/G32) | P32: 0 | Q32: 0.1 | R32: 46253 | S32: =IF(R32="","",'Como ler'!$B$27-R32) -> 39 | T32: 0 | V32: UGC | W32: UGC, Casa e organização | X32: Alta | Y32: =ROUND(IF(K32="",0,MIN(40,40*K32/1.5))+IF(S32="",0,IF(S32<=7,20,IF(S32<=30,12,IF(S32<=90,5,0))))+IF(Q32="",0,MIN(15,Q32*5))+IF(O32="",0,MIN(15,O32*30))+IF(E32="Criador(a)",10,IF(E32="Especialista que cria conteúdo",6,4)),0) -> 41 | Z32: Public figure | AD32: Itajaí: 1 post(s) marcados | AE32: Goiânia, Brazil (1), Piscina Natural da Barra da Lagoa (1), Ilha da Magia - Floripa (1), Trancoso, Bahia, Brazil (1) | AF32: Design de interiores / 💼@campeche.joias | AG32: https://instagram.com/n1kx_x | AH32: Não contatada
A33: Itajaí | B33: Balneário Camboriú | C33: @itajaimilgr4u | D33: Itajai Mil Grau | E33: Página local / guia | F33: Página/marca | G33: 7887 | H33: Micro (3k–30k) | I33: 0.0075 | J33: =IFERROR(INDEX('Como ler'!$B$20:$B$24,MATCH(H33,'Como ler'!$A$20:$A$24,0)),"") -> 0.025 | K33: =IF(OR(I33="",J33=""),"",I33/J33) -> 0.3 | L33: 70 | M33: 5.8 | N33: 102 | O33: =IF(OR(N33="",G33=0),"",N33/G33) -> 0.012932674 | P33: 0.58 | Q33: 1.1 | R33: 46235 | S33: =IF(R33="","",'Como ler'!$B$27-R33) -> 57 | T33: 0 | V33: Moda | W33: Moda, Entretenimento e humor | X33: Baixa | Y33: =ROUND(IF(K33="",0,MIN(40,40*K33/1.5))+IF(S33="",0,IF(S33<=7,20,IF(S33<=30,12,IF(S33<=90,5,0))))+IF(Q33="",0,MIN(15,Q33*5))+IF(O33="",0,MIN(15,O33*30))+IF(E33="Criador(a)",10,IF(E33="Especialista que cria conteúdo",6,4)),0) -> 23 | Z33: Digital creator | AD33: Itajaí: bio, 6 post(s) marcados; Balneário Camboriú: 1 post(s) marcados | AE33: Itajaí -SC (4), Itajaí (1), Praia Do Atalaia - Itajaí (1), Balneário Camboriú - Praia (1) | AF33: Entretenimento, humor e curiosidades de Itajaí e Região / 🎯Conectando moradores,turistas e marcas locais / 💌Anuncie sua empresa com estilo e alcance real⚓ | AG33: https://instagram.com/itajaimilgr4u | AH33: Não contatada
A34: Itajaí | C34: @danielipickering | D34: Dani Pickering | E34: Criador(a) | F34: Mulher | G34: 7430 | H34: Micro (3k–30k) | I34: 0.0106 | J34: =IFERROR(INDEX('Como ler'!$B$20:$B$24,MATCH(H34,'Como ler'!$A$20:$A$24,0)),"") -> 0.025 | K34: =IF(OR(I34="",J34=""),"",I34/J34) -> 0.424 | L34: 82 | M34: 13.2 | N34: 653 | O34: =IF(OR(N34="",G34=0),"",N34/G34) -> 0.087886945 | P34: 0.75 | Q34: 0.3 | R34: 46292 | S34: =IF(R34="","",'Como ler'!$B$27-R34) -> 0 | T34: 0 | V34: Família e maternidade | W34: Família e maternidade, Fitness e wellness, Lifestyle, Negócios e empreendedorismo | X34: Alta | Y34: =ROUND(IF(K34="",0,MIN(40,40*K34/1.5))+IF(S34="",0,IF(S34<=7,20,IF(S34<=30,12,IF(S34<=90,5,0))))+IF(Q34="",0,MIN(15,Q34*5))+IF(O34="",0,MIN(15,O34*30))+IF(E34="Criador(a)",10,IF(E34="Especialista que cria conteúdo",6,4)),0) -> 45 | AD34: Itajaí: 4 post(s) marcados | AE34: Itajaí (3), Itajaí -SC (1), Greenvalley (1) | AF34: Mãe da Kali 💓 / Movimento, trabalho e vida real ✨ / Marketing do Grupo Health Brasil / @healthycann @healthimporter / @healthimporter @nexpurepharma | AG34: https://instagram.com/danielipickering | AH34: Não contatada
A35: Itajaí | C35: @ana_paula_videomaker | D35: VIDEOMAKER MOBILE | ITAJAÍ | E35: Especialista que cria conteúdo | F35: Mulher | G35: 7365 | H35: Micro (3k–30k) | I35: 0.0036 | J35: =IFERROR(INDEX('Como ler'!$B$20:$B$24,MATCH(H35,'Como ler'!$A$20:$A$24,0)),"") -> 0.025 | K35: =IF(OR(I35="",J35=""),"",I35/J35) -> 0.144 | L35: 41 | M35: 4.9 | N35: 228 | O35: =IF(OR(N35="",G35=0),"",N35/G35) -> 0.03095723 | P35: 1 | Q35: 0.4 | R35: 46099 | S35: =IF(R35="","",'Como ler'!$B$27-R35) -> 193 | T35: 5 | U35: @ericaalme_, @lucasfelipexavier, @mariana_talamini, @esquina_doacairs | V35: Social mídia e conteúdo | W35: Social mídia e conteúdo, Relacionamento | X35: Alta | Y35: =ROUND(IF(K35="",0,MIN(40,40*K35/1.5))+IF(S35="",0,IF(S35<=7,20,IF(S35<=30,12,IF(S35<=90,5,0))))+IF(Q35="",0,MIN(15,Q35*5))+IF(O35="",0,MIN(15,O35*30))+IF(E35="Criador(a)",10,IF(E35="Especialista que cria conteúdo",6,4)),0) -> 13 | Z35: Reel creator | AD35: Itajaí: bio | AE35: Itaipava Club Residence (1) | AF35: 🎥 Videomaker Mobile | Itajaí-SC / 🎬 Transformo momentos em memória pelo celular 📲 ✨ Capto emoções reais em vídeo / 📱 Acesse o link e veja meu portfólio ⬇️ | AG35: https://instagram.com/ana_paula_videomaker | AH35: Não contatada
A36: Itajaí | C36: @marcelabontorin | D36: Marcela Bontorin | Estrategista de Imagem e Mentora | E36: Especialista que cria conteúdo | F36: Mulher | G36: 6620 | H36: Micro (3k–30k) | I36: 0.0115 | J36: =IFERROR(INDEX('Como ler'!$B$20:$B$24,MATCH(H36,'Como ler'!$A$20:$A$24,0)),"") -> 0.025 | K36: =IF(OR(I36="",J36=""),"",I36/J36) -> 0.46 | L36: 61 | M36: 18.5 | N36: 961 | O36: =IF(OR(N36="",G36=0),"",N36/G36) -> 0.14516616 | P36: 0.27 | Q36: 0.1 | R36: 46289 | S36: =IF(R36="","",'Como ler'!$B$27-R36) -> 3 | T36: 0 | V36: Negócios e empreendedorismo | W36: Negócios e empreendedorismo, Social mídia e conteúdo, Moda | X36: Alta | Y36: =ROUND(IF(K36="",0,MIN(40,40*K36/1.5))+IF(S36="",0,IF(S36<=7,20,IF(S36<=30,12,IF(S36<=90,5,0))))+IF(Q36="",0,MIN(15,Q36*5))+IF(O36="",0,MIN(15,O36*30))+IF(E36="Criador(a)",10,IF(E36="Especialista que cria conteúdo",6,4)),0) -> 43 | Z36: None | AA36: Sim | AB36: Sim | AD36: Itajaí: 2 post(s) marcados | AE36: Estaleiro Guest House (1), Luvcoffee (1), Itajaí -SC (1), Santa Catarina Itajai (1) | AF36: “Autoridade não se veste, se constrói” / Empreendedora | Mentora | Palestrante / @ecossdosucesso @arlinkinternet @moda_circula_ @literariasdovale | AG36: https://instagram.com/marcelabontorin | AH36: Não contatada
A37: Itajaí | C37: @tonsdeana | D37: Ana Antonelo | Comunicadora de Moda | E37: Criador(a) | F37: Mulher | G37: 6134 | H37: Micro (3k–30k) | J37: =IFERROR(INDEX('Como ler'!$B$20:$B$24,MATCH(H37,'Como ler'!$A$20:$A$24,0)),"") -> 0.025 | K37: =IF(OR(I37="",J37=""),"",I37/J37) | M37: 19 | N37: 388 | O37: =IF(OR(N37="",G37=0),"",N37/G37) -> 0.063253994 | P37: 0.7 | Q37: 10.5 | R37: 46292 | S37: =IF(R37="","",'Como ler'!$B$27-R37) -> 0 | T37: 0 | V37: Moda | W37: Moda | X37: Média | Y37: =ROUND(IF(K37="",0,MIN(40,40*K37/1.5))+IF(S37="",0,IF(S37<=7,20,IF(S37<=30,12,IF(S37<=90,5,0))))+IF(Q37="",0,MIN(15,Q37*5))+IF(O37="",0,MIN(15,O37*30))+IF(E37="Criador(a)",10,IF(E37="Especialista que cria conteúdo",6,4)),0) -> 47 | Z37: None | AB37: Sim | AD37: Itajaí: 9 post(s) marcados | AE37: Itajaí, Santa Catarina, Brasil (8), Joinville Santa Catarina (1), Mercado Velho Itajaí (1) | AF37: Hoje eu acordei querendo te irritar, / será que eu consigo? 👀 / Aqui tem moda com borogodó & muito brechó! ✨ / Crio conteúdos autênticos para sua marca 🫵🏻 | AG37: https://instagram.com/tonsdeana | AH37: Não contatada | AI37: Curtidas ocultas: engajamento calculado só com posts visíveis ou indisponível
A38: Itajaí | C38: @brunasamanthas | D38: Bruna Samantha | Corretora de Imóveis | E38: Especialista que cria conteúdo | F38: Mulher | G38: 5771 | H38: Micro (3k–30k) | I38: 0.0113 | J38: =IFERROR(INDEX('Como ler'!$B$20:$B$24,MATCH(H38,'Como ler'!$A$20:$A$24,0)),"") -> 0.025 | K38: =IF(OR(I38="",J38=""),"",I38/J38) -> 0.452 | L38: 58 | M38: 7.3 | N38: 392 | O38: =IF(OR(N38="",G38=0),"",N38/G38) -> 0.067925836 | P38: 0.83 | Q38: 0.4 | R38: 46265 | S38: =IF(R38="","",'Como ler'!$B$27-R38) -> 27 | T38: 0 | V38: Finanças | W38: Finanças, Viagem, Negócios e empreendedorismo, Família e maternidade | X38: Alta | Y38: =ROUND(IF(K38="",0,MIN(40,40*K38/1.5))+IF(S38="",0,IF(S38<=7,20,IF(S38<=30,12,IF(S38<=90,5,0))))+IF(Q38="",0,MIN(15,Q38*5))+IF(O38="",0,MIN(15,O38*30))+IF(E38="Criador(a)",10,IF(E38="Especialista que cria conteúdo",6,4)),0) -> 34 | Z38: Digital creator | AB38: Sim | AD38: Itajaí: bio, 6 post(s) marcados | AE38: Praia Brava - Itajaí/SC (6) | AF38: Imóveis únicos, localizações desejadas. / Investimentos inteligentes. / Corretora Associada @jeancarloexclusive / 📍Itajaí | Praia Brava | BC / CRECI SC 68926F | AG38: https://instagram.com/brunasamanthas | AH38: Não contatada
A39: Itajaí | B39: Itapema | C39: @andreza.marinho_22 | D39: Andreza Marinho | Atleta | E39: Criador(a) | F39: Mulher | G39: 5648 | H39: Micro (3k–30k) | I39: 0.0282 | J39: =IFERROR(INDEX('Como ler'!$B$20:$B$24,MATCH(H39,'Como ler'!$A$20:$A$24,0)),"") -> 0.025 | K39: =IF(OR(I39="",J39=""),"",I39/J39) -> 1.128 | L39: 148 | M39: 6.8 | N39: 1382 | O39: =IF(OR(N39="",G39=0),"",N39/G39) -> 0.24468839 | P39: 0.5 | Q39: 0.6 | R39: 46290 | S39: =IF(R39="","",'Como ler'!$B$27-R39) -> 2 | T39: 0 | V39: Fitness e wellness | W39: Fitness e wellness | X39: Baixa | Y39: =ROUND(IF(K39="",0,MIN(40,40*K39/1.5))+IF(S39="",0,IF(S39<=7,20,IF(S39<=30,12,IF(S39<=90,5,0))))+IF(Q39="",0,MIN(15,Q39*5))+IF(O39="",0,MIN(15,O39*30))+IF(E39="Criador(a)",10,IF(E39="Especialista que cria conteúdo",6,4)),0) -> 70 | Z39: Personal blog | AD39: Itajaí: bio; Itapema: 1 post(s) marcados | AE39: Hard Rock Cafe Itapema (1) | AF39: 🏃🏻‍♀️ Corredora | Itajaí-SC / 🏅 9 pódios em 1 ano / 📈 Evolução, disciplina & constância / 🧸 Respeita o pace fofo / 🤝 Parcerias & patrocínios | AG39: https://instagram.com/andreza.marinho_22 | AH39: Não contatada
A40: Itajaí | B40: Itapema | C40: @brunoleon.blm | D40: Bruno Leon | Corrida e Vida Real | E40: Criador(a) | F40: Homem | G40: 4593 | H40: Micro (3k–30k) | I40: 0.047 | J40: =IFERROR(INDEX('Como ler'!$B$20:$B$24,MATCH(H40,'Como ler'!$A$20:$A$24,0)),"") -> 0.025 | K40: =IF(OR(I40="",J40=""),"",I40/J40) -> 1.88 | L40: 285 | M40: 40.6 | N40: 2529 | O40: =IF(OR(N40="",G40=0),"",N40/G40) -> 0.55062051 | P40: 0.67 | Q40: 2.3 | R40: 46291 | S40: =IF(R40="","",'Como ler'!$B$27-R40) -> 1 | T40: 0 | V40: Fitness e wellness | W40: Fitness e wellness, Lifestyle, Negócios e empreendedorismo, Família e maternidade | X40: Alta | Y40: =ROUND(IF(K40="",0,MIN(40,40*K40/1.5))+IF(S40="",0,IF(S40<=7,20,IF(S40<=30,12,IF(S40<=90,5,0))))+IF(Q40="",0,MIN(15,Q40*5))+IF(O40="",0,MIN(15,O40*30))+IF(E40="Criador(a)",10,IF(E40="Especialista que cria conteúdo",6,4)),0) -> 97 | Z40: Athlete | AB40: Sim | AD40: Itajaí: 2 post(s) marcados; Itapema: 1 post(s) marcados | AE40: Pista De Atletismo De Itajai (2), Itapema, Brazil (1), Beira Mar.. Floripa.. (1), Maratona Internacional de Floripa (1) | AF40: ✞ JESUS ✞ / 👶🏻 Pai da Milena - 610g 🎀 / 🏅MARATONISTA - 02:49:28 / CEO 🏃🏻 @assessoria.leon / 💍 @luujohann / 💼 @donaruiva.pijamas / Faça parte da ASSESSORIA ⬇️ | AG40: https://instagram.com/brunoleon.blm | AH40: Não contatada
A41: Itajaí | C41: @karinawbauer | D41: Karina Bauer | Real Estate | E41: Especialista que cria conteúdo | F41: Mulher | G41: 4422 | H41: Micro (3k–30k) | I41: 0.0096 | J41: =IFERROR(INDEX('Como ler'!$B$20:$B$24,MATCH(H41,'Como ler'!$A$20:$A$24,0)),"") -> 0.025 | K41: =IF(OR(I41="",J41=""),"",I41/J41) -> 0.384 | L41: 53 | M41: 12.4 | N41: 638 | O41: =IF(OR(N41="",G41=0),"",N41/G41) -> 0.14427861 | P41: 0.5 | Q41: 3.2 | R41: 46286 | S41: =IF(R41="","",'Como ler'!$B$27-R41) -> 6 | T41: 0 | V41: Viagem | W41: Viagem, Finanças, Casa e organização, Educação e conhecimento | X41: Alta | Y41: =ROUND(IF(K41="",0,MIN(40,40*K41/1.5))+IF(S41="",0,IF(S41<=7,20,IF(S41<=30,12,IF(S41<=90,5,0))))+IF(Q41="",0,MIN(15,Q41*5))+IF(O41="",0,MIN(15,O41*30))+IF(E41="Criador(a)",10,IF(E41="Especialista que cria conteúdo",6,4)),0) -> 56 | Z41: Digital creator | AB41: Sim | AD41: Itajaí: bio | AF41: Curadoria de imóveis & oportunidades / Patrimônio • Investimento / 📍 Praia Brava, Itajaí • Florianópolis | SC / ↓ Atendimento exclusivo | AG41: https://instagram.com/karinawbauer | AH41: Não contatada
A42: Itajaí | B42: Balneário Camboriú | C42: @rurikdrone | D42: Rurik | Filmmaker | E42: Especialista que cria conteúdo | F42: Homem | G42: 4378 | H42: Micro (3k–30k) | I42: 0.0046 | J42: =IFERROR(INDEX('Como ler'!$B$20:$B$24,MATCH(H42,'Como ler'!$A$20:$A$24,0)),"") -> 0.025 | K42: =IF(OR(I42="",J42=""),"",I42/J42) -> 0.184 | L42: 51 | M42: 0.3 | N42: 318 | O42: =IF(OR(N42="",G42=0),"",N42/G42) -> 0.072635907 | P42: 0.33 | Q42: 2.3 | R42: 46239 | S42: =IF(R42="","",'Como ler'!$B$27-R42) -> 53 | T42: 0 | V42: Viagem | W42: Viagem, Dicas locais | X42: Baixa | Y42: =ROUND(IF(K42="",0,MIN(40,40*K42/1.5))+IF(S42="",0,IF(S42<=7,20,IF(S42<=30,12,IF(S42<=90,5,0))))+IF(Q42="",0,MIN(15,Q42*5))+IF(O42="",0,MIN(15,O42*30))+IF(E42="Criador(a)",10,IF(E42="Especialista que cria conteúdo",6,4)),0) -> 30 | Z42: Digital creator | AB42: Sim | AD42: Itajaí: bio, 10 post(s) marcados; Balneário Camboriú: 2 post(s) marcados | AE42: Itajaí (5), Praia Brava - Itajaí/SC (4), Balneário Camboriú (2), Praia Brava - Itajaí SC (1) | AF42: 📍 Itajaí & Litoral SC / 🎥 Fotografia aérea | Imóveis | Tours 360 / 🏙️ Descobrindo lugares incríveis. / 🔗 Projetos e parcerias 👇 | AG42: https://instagram.com/rurikdrone | AH42: Não contatada
A43: Itajaí | C43: @annacarolgarimpo | D43: Anna Carol | Influenciadora e UGC Creator- Itajaí | E43: Criador(a) | F43: Mulher | G43: 3941 | H43: Micro (3k–30k) | I43: 0.0192 | J43: =IFERROR(INDEX('Como ler'!$B$20:$B$24,MATCH(H43,'Como ler'!$A$20:$A$24,0)),"") -> 0.025 | K43: =IF(OR(I43="",J43=""),"",I43/J43) -> 0.768 | L43: 209 | M43: 12.9 | N43: 1163 | O43: =IF(OR(N43="",G43=0),"",N43/G43) -> 0.29510277 | P43: 0.7 | Q43: 3.5 | R43: 46289 | S43: =IF(R43="","",'Como ler'!$B$27-R43) -> 3 | T43: 0 | V43: Beleza | W43: Beleza, UGC, Lifestyle, Dicas locais | X43: Alta | Y43: =ROUND(IF(K43="",0,MIN(40,40*K43/1.5))+IF(S43="",0,IF(S43<=7,20,IF(S43<=30,12,IF(S43<=90,5,0))))+IF(Q43="",0,MIN(15,Q43*5))+IF(O43="",0,MIN(15,O43*30))+IF(E43="Criador(a)",10,IF(E43="Especialista que cria conteúdo",6,4)),0) -> 74 | Z43: Digital creator | AB43: Sim | AD43: Itajaí: 6 post(s) marcados | AE43: Itajaí (6), Espinheiros, Santa Catarina (1), Conforto visual (1), Canela - Serra Gaúcha/rs (1) | AF43: Oi amigas, / Dicas | Beleza | Lifestyle / & um pouquinho de tudo que me faz ser eu / ✨🧚‍♀️🌞🧜🏼‍♀️🔮 | AG43: https://instagram.com/annacarolgarimpo | AH43: Não contatada
A44: Itajaí | C44: @enfbapereira | D44: Bárbara Pereira | E44: Criador(a) | F44: Mulher | G44: 3759 | H44: Micro (3k–30k) | I44: 0.0067 | J44: =IFERROR(INDEX('Como ler'!$B$20:$B$24,MATCH(H44,'Como ler'!$A$20:$A$24,0)),"") -> 0.025 | K44: =IF(OR(I44="",J44=""),"",I44/J44) -> 0.268 | L44: 45 | M44: 2.7 | N44: 202 | O44: =IF(OR(N44="",G44=0),"",N44/G44) -> 0.053737696 | P44: 0.58 | Q44: 1.6 | R44: 46291 | S44: =IF(R44="","",'Como ler'!$B$27-R44) -> 1 | T44: 0 | V44: Lifestyle | W44: Lifestyle, Dicas locais | X44: Média | Y44: =ROUND(IF(K44="",0,MIN(40,40*K44/1.5))+IF(S44="",0,IF(S44<=7,20,IF(S44<=30,12,IF(S44<=90,5,0))))+IF(Q44="",0,MIN(15,Q44*5))+IF(O44="",0,MIN(15,O44*30))+IF(E44="Criador(a)",10,IF(E44="Especialista que cria conteúdo",6,4)),0) -> 47 | Z44: Personal blog | AB44: Sim | AD44: Itajaí: 2 post(s) marcados | AE44: Itajaí -SC (1), Igreja Matriz Itajai (1), Brusque, Santa Catarina (1), Limeira Baixa (1) | AF44: Corpo ativo • equilíbrio • fé sem rótulo / Vida real, sem romantizar. / Enf. do Trabalho em formação 🩺 / Profissional: @enfermagemvivasc | AG44: https://instagram.com/enfbapereira | AH44: Não contatada
A45: Itajaí | B45: Balneário Camboriú | C45: @isabbelle_m | D45: Isabelle Moraes | RE/MAX | E45: Especialista que cria conteúdo | F45: Mulher | G45: 3647 | H45: Micro (3k–30k) | I45: 0.0337 | J45: =IFERROR(INDEX('Como ler'!$B$20:$B$24,MATCH(H45,'Como ler'!$A$20:$A$24,0)),"") -> 0.025 | K45: =IF(OR(I45="",J45=""),"",I45/J45) -> 1.348 | L45: 105 | M45: 16.9 | N45: 428 | O45: =IF(OR(N45="",G45=0),"",N45/G45) -> 0.11735673 | P45: 0.33 | Q45: 0.9 | R45: 46286 | S45: =IF(R45="","",'Como ler'!$B$27-R45) -> 6 | T45: 0 | V45: Negócios e empreendedorismo | W45: Negócios e empreendedorismo | X45: Alta | Y45: =ROUND(IF(K45="",0,MIN(40,40*K45/1.5))+IF(S45="",0,IF(S45<=7,20,IF(S45<=30,12,IF(S45<=90,5,0))))+IF(Q45="",0,MIN(15,Q45*5))+IF(O45="",0,MIN(15,O45*30))+IF(E45="Criador(a)",10,IF(E45="Especialista que cria conteúdo",6,4)),0) -> 70 | AB45: Sim | AC45: direct | AD45: Itajaí: bio; Balneário Camboriú: 1 post(s) marcados | AE45: Chile (2), Balneário Camboriú (1), Cajón del Maipo (1) | AF45: Franqueada @remaxdreamon / Transição de carreira com estrutura, formação e direção para corretores / 📍BC• Itajaí • NVT / 📩Fale comigo no direct | AG45: https://instagram.com/isabbelle_m | AH45: Não contatada
A46: Itajaí | C46: @eudanielabonet | D46: Daniela Bonet | E46: Criador(a) | F46: Mulher | G46: 3375 | H46: Micro (3k–30k) | I46: 0.0166 | J46: =IFERROR(INDEX('Como ler'!$B$20:$B$24,MATCH(H46,'Como ler'!$A$20:$A$24,0)),"") -> 0.025 | K46: =IF(OR(I46="",J46=""),"",I46/J46) -> 0.664 | L46: 54 | M46: 8.4 | N46: 372 | O46: =IF(OR(N46="",G46=0),"",N46/G46) -> 0.11022222 | P46: 0.55 | Q46: 0.1 | R46: 46290 | S46: =IF(R46="","",'Como ler'!$B$27-R46) -> 2 | T46: 0 | V46: Viagem | W46: Viagem | X46: Baixa | Y46: =ROUND(IF(K46="",0,MIN(40,40*K46/1.5))+IF(S46="",0,IF(S46<=7,20,IF(S46<=30,12,IF(S46<=90,5,0))))+IF(Q46="",0,MIN(15,Q46*5))+IF(O46="",0,MIN(15,O46*30))+IF(E46="Criador(a)",10,IF(E46="Especialista que cria conteúdo",6,4)),0) -> 52 | AD46: Itajaí: 4 post(s) marcados | AE46: Itajaí (3), Grindelwald First 2200m, First Cliff Walk (1), Itajaí -SC (1), Marrocos (1) | AF46: 📍SC | AG46: https://instagram.com/eudanielabonet | AH46: Não contatada
A47: Itajaí | C47: @psicologademae | D47: Terapia gestação, depressão pós-parto. Grupo de mães Itajaí/BC | E47: Especialista que cria conteúdo | F47: Mulher | G47: 3121 | H47: Micro (3k–30k) | I47: 0.0061 | J47: =IFERROR(INDEX('Como ler'!$B$20:$B$24,MATCH(H47,'Como ler'!$A$20:$A$24,0)),"") -> 0.025 | K47: =IF(OR(I47="",J47=""),"",I47/J47) -> 0.244 | L47: 21 | M47: 7 | N47: 226 | O47: =IF(OR(N47="",G47=0),"",N47/G47) -> 0.072412688 | P47: 0.44 | Q47: 1.2 | R47: 46287 | S47: =IF(R47="","",'Como ler'!$B$27-R47) -> 5 | T47: 0 | V47: Educação e conhecimento | W47: Educação e conhecimento, Família e maternidade | X47: Média | Y47: =ROUND(IF(K47="",0,MIN(40,40*K47/1.5))+IF(S47="",0,IF(S47<=7,20,IF(S47<=30,12,IF(S47<=90,5,0))))+IF(Q47="",0,MIN(15,Q47*5))+IF(O47="",0,MIN(15,O47*30))+IF(E47="Criador(a)",10,IF(E47="Especialista que cria conteúdo",6,4)),0) -> 41 | Z47: Psychologist | AB47: Sim | AD47: Itajaí: bio, 4 post(s) marcados | AE47: Itajaí, Santa Catarina, Brasil (2), Praia Central - Baln. Camburiu (2), Itajaí -SC (2), Curitiba (1) | AF47: 🛋️Terapia para mulheres que querem se reencontrar após a maternidade / 🤰Pré-natal psicológico para gestantes / 📍Atendimentos on-line, Itajaí e BC / Clique⤵️ | AG47: https://instagram.com/psicologademae | AH47: Não contatada
A48: Itajaí | C48: @rafaeldoutore | D48: Rafael Dias Inácio | E48: Criador(a) | F48: Homem | G48: 2821 | H48: Nano (1k–3k) | I48: 0.0349 | J48: =IFERROR(INDEX('Como ler'!$B$20:$B$24,MATCH(H48,'Como ler'!$A$20:$A$24,0)),"") -> 0.04 | K48: =IF(OR(I48="",J48=""),"",I48/J48) -> 0.8725 | L48: 89 | M48: 4.9 | N48: 984 | O48: =IF(OR(N48="",G48=0),"",N48/G48) -> 0.34881248 | P48: 0.25 | Q48: 0.3 | R48: 46275 | S48: =IF(R48="","",'Como ler'!$B$27-R48) -> 17 | T48: 0 | X48: Baixa | Y48: =ROUND(IF(K48="",0,MIN(40,40*K48/1.5))+IF(S48="",0,IF(S48<=7,20,IF(S48<=30,12,IF(S48<=90,5,0))))+IF(Q48="",0,MIN(15,Q48*5))+IF(O48="",0,MIN(15,O48*30))+IF(E48="Criador(a)",10,IF(E48="Especialista que cria conteúdo",6,4)),0) -> 57 | AD48: Itajaí: 1 post(s) marcados | AE48: Kartódromo dos Ingleses (6), Autódromo de Tarumã (1), MRT / RG3 suspension Brasil (1), HONDA-TAKAI (FL) ITAJAI (1) | AF48: 🏍️ Rider / 🏆 2x Catarinense Motovelocidade 25 - 26 / 🏆 Endurance 12H 25 🏎️ - 2H 26 🏍️ / 🎮 PRO / 👔 Lawyer / ⚖️ Pós D. do Trabalho | Previdenciário | Sucessório | AG48: https://instagram.com/rafaeldoutore | AH48: Não contatada
A49: Itajaí | C49: @treinador_veiga | D49: 🇧🇷 𝕀𝕤𝕣𝕒𝕖𝕝 𝕍𝕖𝕚𝕘𝕒 🇧🇷 | E49: Especialista que cria conteúdo | F49: Homem | G49: 2614 | H49: Nano (1k–3k) | I49: 0.0042 | J49: =IFERROR(INDEX('Como ler'!$B$20:$B$24,MATCH(H49,'Como ler'!$A$20:$A$24,0)),"") -> 0.04 | K49: =IF(OR(I49="",J49=""),"",I49/J49) -> 0.105 | L49: 19 | M49: 2.1 | N49: 198 | O49: =IF(OR(N49="",G49=0),"",N49/G49) -> 0.075745983 | P49: 0.11 | Q49: 1.1 | R49: 46286 | S49: =IF(R49="","",'Como ler'!$B$27-R49) -> 6 | T49: 0 | V49: Fitness e wellness | W49: Fitness e wellness, Lifestyle, Família e maternidade | X49: Média | Y49: =ROUND(IF(K49="",0,MIN(40,40*K49/1.5))+IF(S49="",0,IF(S49<=7,20,IF(S49<=30,12,IF(S49<=90,5,0))))+IF(Q49="",0,MIN(15,Q49*5))+IF(O49="",0,MIN(15,O49*30))+IF(E49="Criador(a)",10,IF(E49="Especialista que cria conteúdo",6,4)),0) -> 37 | Z49: Entrepreneur | AD49: Itajaí: 9 post(s) marcados | AE49: Itajaí -SC (7), Bistek Itajaí (2) | AF49: 🌄 𝕃𝔾ℕ𝔻: 𝟙𝟘𝟙𝟙𝟝𝟟 - ℂℝ𝔼𝔽/𝕊ℂ: 𝟘𝟚𝟙𝟟𝟚𝟜 / 🧬 ℂ𝕠𝕒𝕔𝕙 𝕖𝕞 𝕡𝕣𝕖𝕤𝕔𝕣𝕚çõ𝕖𝕤 𝕖𝕤𝕡𝕖𝕔𝕚𝕒𝕝 / 💼 @studiogv_ / 💕@kahh_farias | AG49: https://instagram.com/treinador_veiga | AH49: Não contatada
A50: Itajaí | C50: @clebercoragem | D50: Cleber Coragem | E50: Especialista que cria conteúdo | F50: Homem | G50: 2377 | H50: Nano (1k–3k) | I50: 0.0093 | J50: =IFERROR(INDEX('Como ler'!$B$20:$B$24,MATCH(H50,'Como ler'!$A$20:$A$24,0)),"") -> 0.04 | K50: =IF(OR(I50="",J50=""),"",I50/J50) -> 0.2325 | L50: 24 | M50: 2.6 | N50: 72 | O50: =IF(OR(N50="",G50=0),"",N50/G50) -> 0.030290282 | P50: 0.67 | Q50: 2.8 | R50: 46280 | S50: =IF(R50="","",'Como ler'!$B$27-R50) -> 12 | T50: 0 | V50: Negócios e empreendedorismo | W50: Negócios e empreendedorismo, Educação e conhecimento, Família e maternidade | X50: Alta | Y50: =ROUND(IF(K50="",0,MIN(40,40*K50/1.5))+IF(S50="",0,IF(S50<=7,20,IF(S50<=30,12,IF(S50<=90,5,0))))+IF(Q50="",0,MIN(15,Q50*5))+IF(O50="",0,MIN(15,O50*30))+IF(E50="Criador(a)",10,IF(E50="Especialista que cria conteúdo",6,4)),0) -> 39 | AB50: Sim | AD50: Itajaí: 1 post(s) marcados | AE50: Itajaí (1) | AF50: 🏆 SIM, VOCÊ PODE! ACREDITE / ❤️‍🔥 Mentor e Terapeuta / 💪🏾 Transformando vidas | AG50: https://instagram.com/clebercoragem | AH50: Não contatada
A51: Itajaí | C51: @amandadumbrofsqui | D51: Amanda Dumbrofsqui | E51: Criador(a) | F51: Mulher | G51: 2266 | H51: Nano (1k–3k) | I51: 0.0677 | J51: =IFERROR(INDEX('Como ler'!$B$20:$B$24,MATCH(H51,'Como ler'!$A$20:$A$24,0)),"") -> 0.04 | K51: =IF(OR(I51="",J51=""),"",I51/J51) -> 1.6925 | L51: 257 | M51: 10.2 | N51: 1874 | O51: =IF(OR(N51="",G51=0),"",N51/G51) -> 0.82700794 | P51: 0.83 | Q51: 5.9 | R51: 46289 | S51: =IF(R51="","",'Como ler'!$B$27-R51) -> 3 | T51: 0 | V51: Lifestyle | W51: Lifestyle, Gastronomia, Dicas locais | X51: Média | Y51: =ROUND(IF(K51="",0,MIN(40,40*K51/1.5))+IF(S51="",0,IF(S51<=7,20,IF(S51<=30,12,IF(S51<=90,5,0))))+IF(Q51="",0,MIN(15,Q51*5))+IF(O51="",0,MIN(15,O51*30))+IF(E51="Criador(a)",10,IF(E51="Especialista que cria conteúdo",6,4)),0) -> 100 | AD51: Itajaí: bio, 5 post(s) marcados | AE51: Itajaí, Santa Catarina, Brasil (5), Italiana Garden Café (1), Beto Carrero World (1) | AF51: 📍SC / publicitária, criativa, fã de itajaí, aspirante a uma vida de Heleninha & outras coisas mais ✨ / pode reparar a bagunça 🧚🏼‍♀️ | AG51: https://instagram.com/amandadumbrofsqui | AH51: Não contatada
A52: Itajaí | C52: @leandrogatelli_personal | D52: Leandro Gatelli | E52: Especialista que cria conteúdo | F52: Homem | G52: 2203 | H52: Nano (1k–3k) | I52: 0.0045 | J52: =IFERROR(INDEX('Como ler'!$B$20:$B$24,MATCH(H52,'Como ler'!$A$20:$A$24,0)),"") -> 0.04 | K52: =IF(OR(I52="",J52=""),"",I52/J52) -> 0.1125 | L52: 12 | M52: 1.4 | O52: =IF(OR(N52="",G52=0),"",N52/G52) | P52: 0 | Q52: 1.3 | R52: 46286 | S52: =IF(R52="","",'Como ler'!$B$27-R52) -> 6 | T52: 0 | V52: Fitness e wellness | W52: Fitness e wellness, Educação e conhecimento, Lifestyle, Negócios e empreendedorismo | X52: Alta | Y52: =ROUND(IF(K52="",0,MIN(40,40*K52/1.5))+IF(S52="",0,IF(S52<=7,20,IF(S52<=30,12,IF(S52<=90,5,0))))+IF(Q52="",0,MIN(15,Q52*5))+IF(O52="",0,MIN(15,O52*30))+IF(E52="Criador(a)",10,IF(E52="Especialista que cria conteúdo",6,4)),0) -> 36 | Z52: Coach | AB52: Sim | AD52: Itajaí: 11 post(s) marcados | AE52: Itajaí -SC (10), Bistek Itajaí (1) | AF52: 🏋️‍♂️ Sócio fundador da GVs Studio / 🎓 Licenciatura Plena em Educação Física / 📚 +13 anos de experiência na área / 🎯 Musculação para Grupos Especiais | AG52: https://instagram.com/leandrogatelli_personal | AH52: Não contatada
A53: Itajaí | B53: Balneário Camboriú | C53: @ddiegoo.martins | D53: Diego Martins | E53: Especialista que cria conteúdo | F53: Homem | G53: 2109 | H53: Nano (1k–3k) | I53: 0.0133 | J53: =IFERROR(INDEX('Como ler'!$B$20:$B$24,MATCH(H53,'Como ler'!$A$20:$A$24,0)),"") -> 0.04 | K53: =IF(OR(I53="",J53=""),"",I53/J53) -> 0.3325 | L53: 32 | M53: 2.8 | N53: 61 | O53: =IF(OR(N53="",G53=0),"",N53/G53) -> 0.028923661 | P53: 0.27 | Q53: 2.2 | R53: 46291 | S53: =IF(R53="","",'Como ler'!$B$27-R53) -> 1 | T53: 0 | V53: Negócios e empreendedorismo | W53: Negócios e empreendedorismo, Educação e conhecimento, Casa e organização, Gastronomia | X53: Alta | Y53: =ROUND(IF(K53="",0,MIN(40,40*K53/1.5))+IF(S53="",0,IF(S53<=7,20,IF(S53<=30,12,IF(S53<=90,5,0))))+IF(Q53="",0,MIN(15,Q53*5))+IF(O53="",0,MIN(15,O53*30))+IF(E53="Criador(a)",10,IF(E53="Especialista que cria conteúdo",6,4)),0) -> 47 | AB53: Sim | AD53: Itajaí: bio; Balneário Camboriú: 1 post(s) marcados | AE53: Mexico City, Mexico (3), São João Batista, Santa Catarina (2), Balneário Camboriú (1), Centro Cultural Teatro Usiminas (1) | AF53: 🎤 Palestrante / 📈 Desenvolvimento de líderes / 🫶🏼 Presidente @abrh.sc / 👨‍🏫 Professor @senacitajai / 🍷Apaixonado por café e vinho | AG53: https://instagram.com/ddiegoo.martins | AH53: Não contatada
A54: Itajaí | C54: @silviaandreamota | D54: SILVIA MOTA | E54: Especialista que cria conteúdo | F54: Mulher | G54: 2074 | H54: Nano (1k–3k) | I54: 0.0068 | J54: =IFERROR(INDEX('Como ler'!$B$20:$B$24,MATCH(H54,'Como ler'!$A$20:$A$24,0)),"") -> 0.04 | K54: =IF(OR(I54="",J54=""),"",I54/J54) -> 0.17 | L54: 12 | M54: 1.2 | N54: 4 | O54: =IF(OR(N54="",G54=0),"",N54/G54) -> 0.0019286403 | P54: 0.11 | Q54: 0.5 | R54: 46288 | S54: =IF(R54="","",'Como ler'!$B$27-R54) -> 4 | T54: 0 | V54: Família e maternidade | W54: Família e maternidade, Relacionamento, Lifestyle, Fitness e wellness | X54: Média | Y54: =ROUND(IF(K54="",0,MIN(40,40*K54/1.5))+IF(S54="",0,IF(S54<=7,20,IF(S54<=30,12,IF(S54<=90,5,0))))+IF(Q54="",0,MIN(15,Q54*5))+IF(O54="",0,MIN(15,O54*30))+IF(E54="Criador(a)",10,IF(E54="Especialista que cria conteúdo",6,4)),0) -> 33 | Z54: Personal Coach | AB54: Sim | AD54: Itajaí: 1 post(s) marcados | AE54: Espinheiros, Santa Catarina (1), PIBI - Primeira Igreja Batista em Itajaí (1) | AF54: • Cristã •Esposa • Mãe / • Te ajudo a liderar sua rotina com propósito 🎯 / Mais de 2k Mulheres Impactadas | AG54: https://instagram.com/silviaandreamota | AH54: Não contatada
A55: Itajaí | C55: @doulacriscurvello | D55: Doula Itajaí | Ed. Perinatal | Maternidade Cristã | E55: Especialista que cria conteúdo | F55: Mulher | G55: 2028 | H55: Nano (1k–3k) | I55: 0.1706 | J55: =IFERROR(INDEX('Como ler'!$B$20:$B$24,MATCH(H55,'Como ler'!$A$20:$A$24,0)),"") -> 0.04 | K55: =IF(OR(I55="",J55=""),"",I55/J55) -> 4.265 | L55: 611 | M55: 23.3 | N55: 8807 | O55: =IF(OR(N55="",G55=0),"",N55/G55) -> 4.3427022 | P55: 0.09 | Q55: 0.2 | R55: 46266 | S55: =IF(R55="","",'Como ler'!$B$27-R55) -> 26 | T55: 0 | V55: Família e maternidade | W55: Família e maternidade, Relacionamento | X55: Média | Y55: =ROUND(IF(K55="",0,MIN(40,40*K55/1.5))+IF(S55="",0,IF(S55<=7,20,IF(S55<=30,12,IF(S55<=90,5,0))))+IF(Q55="",0,MIN(15,Q55*5))+IF(O55="",0,MIN(15,O55*30))+IF(E55="Criador(a)",10,IF(E55="Especialista que cria conteúdo",6,4)),0) -> 74 | AB55: Sim | AD55: Itajaí: 4 post(s) marcados | AE55: Itajaí -SC (3), Itajaí (1) | AF55: Ajudo mulheres viverem uma maternidade sobre[natural]💡📖 / 👩‍❤️‍💋‍👨Esposa | Mãe de 6 👦🏻👦🏻👦🏻👧🏼👦🏻👶🏻 / 🫂Apoio físico, emocional e espiritual / Fale comigo💜👇🏻 | AG55: https://instagram.com/doulacriscurvello | AH55: Não contatada
A56: Itajaí | C56: @personalorganizer.karen | D56: KAREN COLAMARIA - Personal Organizer Designer™️ | Mentora | E56: Especialista que cria conteúdo | F56: Mulher | G56: 2025 | H56: Nano (1k–3k) | J56: =IFERROR(INDEX('Como ler'!$B$20:$B$24,MATCH(H56,'Como ler'!$A$20:$A$24,0)),"") -> 0.04 | K56: =IF(OR(I56="",J56=""),"",I56/J56) | M56: 0 | O56: =IF(OR(N56="",G56=0),"",N56/G56) | P56: 0 | Q56: 3.1 | R56: 46288 | S56: =IF(R56="","",'Como ler'!$B$27-R56) -> 4 | T56: 0 | V56: Casa e organização | W56: Casa e organização, Viagem, Negócios e empreendedorismo | X56: Alta | Y56: =ROUND(IF(K56="",0,MIN(40,40*K56/1.5))+IF(S56="",0,IF(S56<=7,20,IF(S56<=30,12,IF(S56<=90,5,0))))+IF(Q56="",0,MIN(15,Q56*5))+IF(O56="",0,MIN(15,O56*30))+IF(E56="Criador(a)",10,IF(E56="Especialista que cria conteúdo",6,4)),0) -> 41 | Z56: Entrepreneur | AB56: Sim | AD56: Itajaí: 1 post(s) marcados | AE56: Curitiba, Paraná (2), Navegantes, Santa Catarina, Brasil (1), Brava Beach - Praia Brava (1), Curitiba, Brazil (1) | AF56: ● PRIMEIRA e ÚNICA Personal Organizer DESIGNER™ do BRASIL / ● Escritório SC e SP / ● 10 anos de Expertise / ● CRIADORA Organização Sensorial™ e Hotel Style™ | AG56: https://instagram.com/personalorganizer.karen | AH56: Não contatada | AI56: Curtidas ocultas: engajamento calculado só com posts visíveis ou indisponível
A57: Itajaí | C57: @byleticiagartner | D57: Letícia Rauber Gartner - Projeto de Influenciadora em Itajaí | E57: Criador(a) | F57: Mulher | G57: 1693 | H57: Nano (1k–3k) | I57: 0.031 | J57: =IFERROR(INDEX('Como ler'!$B$20:$B$24,MATCH(H57,'Como ler'!$A$20:$A$24,0)),"") -> 0.04 | K57: =IF(OR(I57="",J57=""),"",I57/J57) -> 0.775 | L57: 129 | M57: 7.3 | N57: 622 | O57: =IF(OR(N57="",G57=0),"",N57/G57) -> 0.36739516 | P57: 0.83 | Q57: 0.6 | R57: 46279 | S57: =IF(R57="","",'Como ler'!$B$27-R57) -> 13 | T57: 0 | V57: Família e maternidade | W57: Família e maternidade | X57: Média | Y57: =ROUND(IF(K57="",0,MIN(40,40*K57/1.5))+IF(S57="",0,IF(S57<=7,20,IF(S57<=30,12,IF(S57<=90,5,0))))+IF(Q57="",0,MIN(15,Q57*5))+IF(O57="",0,MIN(15,O57*30))+IF(E57="Criador(a)",10,IF(E57="Especialista que cria conteúdo",6,4)),0) -> 57 | Z57: Personal blog | AD57: Itajaí: 3 post(s) marcados | AE57: Itajaí (3), Brasil (1), Santa Catarina, Brasil (1) | AF57: Bastidores de uma vida entre eventos, trabalho e maternidade 🤎 / Acompanhe nos storys 🔥 / 💍 @matheusg.gartner / 💼 @gartnereventos | AG57: https://instagram.com/byleticiagartner | AH57: Não contatada
A58: Itajaí | C58: @o.clebernunes | D58: Cleber Nunes | E58: Criador(a) | F58: Homem | G58: 1399 | H58: Nano (1k–3k) | I58: 0.0172 | J58: =IFERROR(INDEX('Como ler'!$B$20:$B$24,MATCH(H58,'Como ler'!$A$20:$A$24,0)),"") -> 0.04 | K58: =IF(OR(I58="",J58=""),"",I58/J58) -> 0.43 | L58: 24269 | M58: 136.3 | N58: 718 | O58: =IF(OR(N58="",G58=0),"",N58/G58) -> 0.51322373 | P58: 0.83 | Q58: 0.5 | R58: 46292 | S58: =IF(R58="","",'Como ler'!$B$27-R58) -> 0 | T58: 0 | V58: Relacionamento | W58: Relacionamento | X58: Baixa | Y58: =ROUND(IF(K58="",0,MIN(40,40*K58/1.5))+IF(S58="",0,IF(S58<=7,20,IF(S58<=30,12,IF(S58<=90,5,0))))+IF(Q58="",0,MIN(15,Q58*5))+IF(O58="",0,MIN(15,O58*30))+IF(E58="Criador(a)",10,IF(E58="Especialista que cria conteúdo",6,4)),0) -> 59 | AB58: Sim | AC58: email | AD58: Itajaí: 5 post(s) marcados | AE58: Itajaí -SC (5) | AF58: Tudo aleatório mas que faz sentido🤔😅 / Marido • Corredor amador • Futuro Surfista / [e-mail na bio] 📨 | AG58: https://instagram.com/o.clebernunes | AH58: Não contatada
A59: Itajaí | C59: @brunamarqes | D59: Bruna Marques | Estrategista do Reino | E59: Especialista que cria conteúdo | F59: Mulher | G59: 1347 | H59: Nano (1k–3k) | I59: 0.0475 | J59: =IFERROR(INDEX('Como ler'!$B$20:$B$24,MATCH(H59,'Como ler'!$A$20:$A$24,0)),"") -> 0.04 | K59: =IF(OR(I59="",J59=""),"",I59/J59) -> 1.1875 | L59: 52 | M59: 26.4 | N59: 187 | O59: =IF(OR(N59="",G59=0),"",N59/G59) -> 0.13882702 | P59: 0.64 | Q59: 1.3 | R59: 46287 | S59: =IF(R59="","",'Como ler'!$B$27-R59) -> 5 | T59: 0 | V59: Social mídia e conteúdo | W59: Social mídia e conteúdo, Educação e conhecimento | X59: Alta | Y59: =ROUND(IF(K59="",0,MIN(40,40*K59/1.5))+IF(S59="",0,IF(S59<=7,20,IF(S59<=30,12,IF(S59<=90,5,0))))+IF(Q59="",0,MIN(15,Q59*5))+IF(O59="",0,MIN(15,O59*30))+IF(E59="Criador(a)",10,IF(E59="Especialista que cria conteúdo",6,4)),0) -> 68 | AD59: Itajaí: 1 post(s) marcados | AE59: Marlborough, Massachusetts (1), Itajaí (1) | AF59: Ativo o Posicionamento de mulheres que carregam uma mensagem do Reino. / IDENTIDADE 》AUTOGOVERNO 》CHAMADO / Da essência ao legado ❤️‍🔥 | AG59: https://instagram.com/brunamarqes | AH59: Não contatada
A60: Balneário Camboriú | C60: @brunarotta_ | D60: Bruna Rotta | E60: Criador(a) | F60: Mulher | G60: 1589475 | H60: Mega (500k+) | I60: 0.0168 | J60: =IFERROR(INDEX('Como ler'!$B$20:$B$24,MATCH(H60,'Como ler'!$A$20:$A$24,0)),"") -> 0.007 | K60: =IF(OR(I60="",J60=""),"",I60/J60) -> 2.4 | L60: 29876 | M60: 142.6 | N60: 252204 | O60: =IF(OR(N60="",G60=0),"",N60/G60) -> 0.15867126 | P60: 0.5 | Q60: 1.3 | R60: 46289 | S60: =IF(R60="","",'Como ler'!$B$27-R60) -> 3 | T60: 0 | V60: Família e maternidade | W60: Família e maternidade | X60: Média | Y60: =ROUND(IF(K60="",0,MIN(40,40*K60/1.5))+IF(S60="",0,IF(S60<=7,20,IF(S60<=30,12,IF(S60<=90,5,0))))+IF(Q60="",0,MIN(15,Q60*5))+IF(O60="",0,MIN(15,O60*30))+IF(E60="Criador(a)",10,IF(E60="Especialista que cria conteúdo",6,4)),0) -> 81 | AA60: Sim | AC60: email | AD60: Balneário Camboriú: bio, 6 post(s) marcados | AE60: Balneário Camboriú (5), São Paulo, Brazil (1), Balneário Camboriú - SC (1) | AF60: Balneário Camboriú, SC 🇧🇷 / publicidades: [e-mail na bio] / @growthsupplements cupom BRUNAROTTA | AG60: https://instagram.com/brunarotta_ | AH60: Não contatada
A61: Balneário Camboriú | B61: Itapema | C61: @letsbalneario | D61: Lets Balneário - Nelson e Bru | E61: Página local / guia | F61: Casal | G61: 540119 | H61: Mega (500k+) | I61: 0.0042 | J61: =IFERROR(INDEX('Como ler'!$B$20:$B$24,MATCH(H61,'Como ler'!$A$20:$A$24,0)),"") -> 0.007 | K61: =IF(OR(I61="",J61=""),"",I61/J61) -> 0.6 | L61: 3129 | M61: 70.8 | N61: 53460 | O61: =IF(OR(N61="",G61=0),"",N61/G61) -> 0.098978188 | P61: 1 | Q61: 5.5 | R61: 46292 | S61: =IF(R61="","",'Como ler'!$B$27-R61) -> 0 | T61: 0 | V61: Gastronomia | W61: Gastronomia, Viagem, Dicas locais | X61: Baixa | Y61: =ROUND(IF(K61="",0,MIN(40,40*K61/1.5))+IF(S61="",0,IF(S61<=7,20,IF(S61<=30,12,IF(S61<=90,5,0))))+IF(Q61="",0,MIN(15,Q61*5))+IF(O61="",0,MIN(15,O61*30))+IF(E61="Criador(a)",10,IF(E61="Especialista que cria conteúdo",6,4)),0) -> 58 | Z61: Digital creator | AC61: direct | AD61: Balneário Camboriú: 5 post(s) marcados; Itapema: 1 post(s) marcados | AE61: Balneário Camboriú (5), Meia Praia, Itapema (1) | AF61: 🏖️Te mostramos o que fazer em Santa Catarina. / ⭐️Apareça aqui! Chama no DIRECT. / 🚀1 MILHÃO de seguidores somando as redes. / 🤔 Já apertou em Seguir??? ⤵️ | AG61: https://instagram.com/letsbalneario | AH61: Não contatada
A62: Balneário Camboriú | C62: @blogueiracamilar | D62: CAMILA G RAMOS | E62: Criador(a) | F62: Mulher | G62: 251019 | H62: Macro (100k–500k) | I62: 0.0016 | J62: =IFERROR(INDEX('Como ler'!$B$20:$B$24,MATCH(H62,'Como ler'!$A$20:$A$24,0)),"") -> 0.01 | K62: =IF(OR(I62="",J62=""),"",I62/J62) -> 0.16 | L62: 329 | M62: 109 | N62: 2422 | O62: =IF(OR(N62="",G62=0),"",N62/G62) -> 0.009648672 | P62: 0.91 | Q62: 11.7 | R62: 46292 | S62: =IF(R62="","",'Como ler'!$B$27-R62) -> 0 | T62: 0 | V62: Beleza | W62: Beleza, Moda, Negócios e empreendedorismo | X62: Alta | Y62: =ROUND(IF(K62="",0,MIN(40,40*K62/1.5))+IF(S62="",0,IF(S62<=7,20,IF(S62<=30,12,IF(S62<=90,5,0))))+IF(Q62="",0,MIN(15,Q62*5))+IF(O62="",0,MIN(15,O62*30))+IF(E62="Criador(a)",10,IF(E62="Especialista que cria conteúdo",6,4)),0) -> 50 | Z62: Digital creator | AA62: Sim | AB62: Sim | AD62: Balneário Camboriú: bio | AE62: Teatro Dionísio (1), Las Vegas, Nevada (1), São Paulo, Brazil (1) | AF62: Moda, Perfumes, Mkt de Influência / ✨ Entre fragrâncias, tendências e looks / Fundadora @agencyinspira / Balneário Camboriú | AG62: https://instagram.com/blogueiracamilar | AH62: Não contatada
A63: Balneário Camboriú | C63: @_balneario_camboriu | D63: 𝑨 𝑫𝒖𝒃𝒂𝒊 𝑩𝒓𝒂𝒔𝒊𝒍𝒆𝒊𝒓𝒂 🇧🇷®️ | E63: Página local / guia | F63: Página/marca | G63: 212079 | H63: Macro (100k–500k) | I63: 0.0032 | J63: =IFERROR(INDEX('Como ler'!$B$20:$B$24,MATCH(H63,'Como ler'!$A$20:$A$24,0)),"") -> 0.01 | K63: =IF(OR(I63="",J63=""),"",I63/J63) -> 0.32 | L63: 1106 | M63: 54.3 | N63: 18950 | O63: =IF(OR(N63="",G63=0),"",N63/G63) -> 0.089353496 | P63: 1 | Q63: 0.6 | R63: 46075 | S63: =IF(R63="","",'Como ler'!$B$27-R63) -> 217 | T63: 0 | V63: Dicas locais | W63: Dicas locais | X63: Baixa | Y63: =ROUND(IF(K63="",0,MIN(40,40*K63/1.5))+IF(S63="",0,IF(S63<=7,20,IF(S63<=30,12,IF(S63<=90,5,0))))+IF(Q63="",0,MIN(15,Q63*5))+IF(O63="",0,MIN(15,O63*30))+IF(E63="Criador(a)",10,IF(E63="Especialista que cria conteúdo",6,4)),0) -> 18 | Z63: None | AD63: Balneário Camboriú: 11 post(s) marcados | AE63: Balneário Camboriú (10), Balneário Camboriú - SC - A Dubai Brasileira (1) | AG63: https://instagram.com/_balneario_camboriu | AH63: Não contatada
A64: Balneário Camboriú | B64: Camboriú | C64: @bccity_ | D64: BC City | E64: Página local / guia | F64: Página/marca | G64: 169872 | H64: Macro (100k–500k) | I64: 0.0013 | J64: =IFERROR(INDEX('Como ler'!$B$20:$B$24,MATCH(H64,'Como ler'!$A$20:$A$24,0)),"") -> 0.01 | K64: =IF(OR(I64="",J64=""),"",I64/J64) -> 0.13 | L64: 494 | M64: 14.4 | N64: 1136 | O64: =IF(OR(N64="",G64=0),"",N64/G64) -> 0.0066873882 | P64: 1 | Q64: 15.4 | R64: 46291 | S64: =IF(R64="","",'Como ler'!$B$27-R64) -> 1 | T64: 0 | V64: Dicas locais | W64: Dicas locais | X64: Baixa | Y64: =ROUND(IF(K64="",0,MIN(40,40*K64/1.5))+IF(S64="",0,IF(S64<=7,20,IF(S64<=30,12,IF(S64<=90,5,0))))+IF(Q64="",0,MIN(15,Q64*5))+IF(O64="",0,MIN(15,O64*30))+IF(E64="Criador(a)",10,IF(E64="Especialista que cria conteúdo",6,4)),0) -> 43 | Z64: Digital creator | AC64: direct | AD64: Balneário Camboriú: bio, 8 post(s) marcados; Camboriú: 1 post(s) marcados | AE64: Balneário Camboriú (7), Parque Unipraias Camboriú (1), Balneário Camboriú - SC (1) | AF64: Balneário Camboriú 🇧🇷 / Parcerias Direct📲 Use#bccity | AG64: https://instagram.com/bccity_ | AH64: Não contatada
A65: Balneário Camboriú | C65: @balneariocamboriuemfocoo | D65: Balneário Camboriú em foco | E65: Página local / guia | F65: Página/marca | G65: 166537 | H65: Macro (100k–500k) | I65: 0.0021 | J65: =IFERROR(INDEX('Como ler'!$B$20:$B$24,MATCH(H65,'Como ler'!$A$20:$A$24,0)),"") -> 0.01 | K65: =IF(OR(I65="",J65=""),"",I65/J65) -> 0.21 | L65: 596 | M65: 93.5 | N65: 14105 | O65: =IF(OR(N65="",G65=0),"",N65/G65) -> 0.084695893 | P65: 1 | Q65: 24.5 | R65: 46108 | S65: =IF(R65="","",'Como ler'!$B$27-R65) -> 184 | T65: 0 | V65: Dicas locais | W65: Dicas locais | X65: Baixa | Y65: =ROUND(IF(K65="",0,MIN(40,40*K65/1.5))+IF(S65="",0,IF(S65<=7,20,IF(S65<=30,12,IF(S65<=90,5,0))))+IF(Q65="",0,MIN(15,Q65*5))+IF(O65="",0,MIN(15,O65*30))+IF(E65="Criador(a)",10,IF(E65="Especialista que cria conteúdo",6,4)),0) -> 27 | Z65: Digital creator | AC65: direct | AD65: Balneário Camboriú: bio, 5 post(s) marcados | AE65: Balneário Camboriú (5), Navegantes, Santa Catarina, Brasil (1) | AF65: Balneário Camboriú 🏠📍🏖️ / A única Pagina que mostra tudo sobre Balneário Camboriú. / Melhor cidade do Brasil 🇧🇷 / PARCERIAS NO DIRECT. | AG65: https://instagram.com/balneariocamboriuemfocoo | AH65: Não contatada
A66: Balneário Camboriú | B66: Itapema | C66: @kcrespi | D66: Ketlyn Crespi Haag | E66: Criador(a) | F66: Mulher | G66: 164287 | H66: Macro (100k–500k) | I66: 0.0003 | J66: =IFERROR(INDEX('Como ler'!$B$20:$B$24,MATCH(H66,'Como ler'!$A$20:$A$24,0)),"") -> 0.01 | K66: =IF(OR(I66="",J66=""),"",I66/J66) -> 0.03 | L66: 49 | M66: 5.4 | N66: 530 | O66: =IF(OR(N66="",G66=0),"",N66/G66) -> 0.0032260617 | P66: 0.5 | Q66: 19.2 | R66: 46292 | S66: =IF(R66="","",'Como ler'!$B$27-R66) -> 0 | T66: 0 | V66: Lifestyle | W66: Lifestyle, Moda, Família e maternidade | X66: Média | Y66: =ROUND(IF(K66="",0,MIN(40,40*K66/1.5))+IF(S66="",0,IF(S66<=7,20,IF(S66<=30,12,IF(S66<=90,5,0))))+IF(Q66="",0,MIN(15,Q66*5))+IF(O66="",0,MIN(15,O66*30))+IF(E66="Criador(a)",10,IF(E66="Especialista que cria conteúdo",6,4)),0) -> 46 | Z66: Digital creator | AA66: Sim | AB66: Sim | AC66: email | AD66: Balneário Camboriú: 6 post(s) marcados; Itapema: 2 post(s) marcados | AE66: Balneário Camboriú (6), Santa Catarina (4), Itapema, Brazil (2) | AF66: 🇺🇸 • 🇧🇷 / Fashion | Lifestyle l Mom / 𝑔𝑜𝒹 𝒾𝓈 𝑔𝑜𝑜𝒹 - Sl 91 / 💌 [e-mail na bio] | AG66: https://instagram.com/kcrespi | AH66: Não contatada
A67: Balneário Camboriú | C67: @maduwebberr | D67: Influencer digital Santa Catarina e Rio Grande do Sul | E67: Criador(a) | F67: Mulher | G67: 128899 | H67: Macro (100k–500k) | I67: 0.0187 | J67: =IFERROR(INDEX('Como ler'!$B$20:$B$24,MATCH(H67,'Como ler'!$A$20:$A$24,0)),"") -> 0.01 | K67: =IF(OR(I67="",J67=""),"",I67/J67) -> 1.87 | L67: 6264 | M67: 34.1 | N67: 8514 | O67: =IF(OR(N67="",G67=0),"",N67/G67) -> 0.066051715 | P67: 0.56 | Q67: 18.7 | R67: 46291 | S67: =IF(R67="","",'Como ler'!$B$27-R67) -> 1 | T67: 0 | V67: Lifestyle | W67: Lifestyle | X67: Média | Y67: =ROUND(IF(K67="",0,MIN(40,40*K67/1.5))+IF(S67="",0,IF(S67<=7,20,IF(S67<=30,12,IF(S67<=90,5,0))))+IF(Q67="",0,MIN(15,Q67*5))+IF(O67="",0,MIN(15,O67*30))+IF(E67="Criador(a)",10,IF(E67="Especialista que cria conteúdo",6,4)),0) -> 87 | Z67: Digital creator | AB67: Sim | AD67: Balneário Camboriú: 1 post(s) marcados | AE67: Balneário Camboriú - SC (1) | AF67: RS e SC Vida real sem filtro! 💖 / • Divulgações de empresas 🏆 / • embaixadora @usedivaslim / • Maquidora @studiomaduwebber | AG67: https://instagram.com/maduwebberr | AH67: Não contatada
A68: Balneário Camboriú | B68: Itajaí | C68: @ondeirbc | D68: Mell - Onde ir Balneário Camboriú | E68: Criador(a) | F68: Mulher | G68: 119845 | H68: Macro (100k–500k) | I68: 0.0038 | J68: =IFERROR(INDEX('Como ler'!$B$20:$B$24,MATCH(H68,'Como ler'!$A$20:$A$24,0)),"") -> 0.01 | K68: =IF(OR(I68="",J68=""),"",I68/J68) -> 0.38 | L68: 489 | M68: 24.9 | N68: 9245 | O68: =IF(OR(N68="",G68=0),"",N68/G68) -> 0.077141308 | P68: 0.75 | Q68: 1.6 | R68: 46289 | S68: =IF(R68="","",'Como ler'!$B$27-R68) -> 3 | T68: 0 | V68: Gastronomia | W68: Gastronomia, Dicas locais | X68: Baixa | Y68: =ROUND(IF(K68="",0,MIN(40,40*K68/1.5))+IF(S68="",0,IF(S68<=7,20,IF(S68<=30,12,IF(S68<=90,5,0))))+IF(Q68="",0,MIN(15,Q68*5))+IF(O68="",0,MIN(15,O68*30))+IF(E68="Criador(a)",10,IF(E68="Especialista que cria conteúdo",6,4)),0) -> 50 | AA68: Sim | AB68: Sim | AC68: direct | AD68: Balneário Camboriú: 2 post(s) marcados; Itajaí: 1 post(s) marcados | AE68: Balneário Camboriú (2), Itajaí (1) | AF68: 🙋🏻‍♀️Sou a Mell! Falo tudo que você precisa saber antes de entrar num restaurante! / 🏅Referência em dicas desde 2016 / 💌Parcerias link bio ou direct | AG68: https://instagram.com/ondeirbc | AH68: Não contatada
A69: Balneário Camboriú | C69: @lugaresdebc | D69: Balneário Camboriú: O que fazer - Blog Local Connect | E69: Página local / guia | F69: Página/marca | G69: 110843 | H69: Macro (100k–500k) | I69: 0.0005 | J69: =IFERROR(INDEX('Como ler'!$B$20:$B$24,MATCH(H69,'Como ler'!$A$20:$A$24,0)),"") -> 0.01 | K69: =IF(OR(I69="",J69=""),"",I69/J69) -> 0.05 | L69: 761 | M69: 17.8 | N69: 2944 | O69: =IF(OR(N69="",G69=0),"",N69/G69) -> 0.026560089 | P69: 0.7 | Q69: 0.4 | R69: 46292 | S69: =IF(R69="","",'Como ler'!$B$27-R69) -> 0 | T69: 0 | V69: Dicas locais | W69: Dicas locais, Viagem, Gastronomia, Entretenimento e humor | X69: Baixa | Y69: =ROUND(IF(K69="",0,MIN(40,40*K69/1.5))+IF(S69="",0,IF(S69<=7,20,IF(S69<=30,12,IF(S69<=90,5,0))))+IF(Q69="",0,MIN(15,Q69*5))+IF(O69="",0,MIN(15,O69*30))+IF(E69="Criador(a)",10,IF(E69="Especialista que cria conteúdo",6,4)),0) -> 28 | Z69: Digital creator | AA69: Sim | AB69: Sim | AD69: Balneário Camboriú: bio, 5 post(s) marcados | AE69: Balneário Camboriú - SC (5), Beto Carrero World, Penha - Santa Catarina (2) | AF69: 📍O que fazer em Balneário Camboriú / 🏖️ Praias • 🌳 Passeios • 🍝 Gastronomia • 🎟️ Eventos • 🗺️ Roteiros e dicas / 👇 Ingressos com Desconto | AG69: https://instagram.com/lugaresdebc | AH69: Não contatada
A70: Balneário Camboriú | B70: Itajaí | C70: @coisasquecomo | D70: Tábata (Coisas Que Como) | E70: Criador(a) | F70: Mulher | G70: 96473 | H70: Média (30k–100k) | I70: 0.0045 | J70: =IFERROR(INDEX('Como ler'!$B$20:$B$24,MATCH(H70,'Como ler'!$A$20:$A$24,0)),"") -> 0.015 | K70: =IF(OR(I70="",J70=""),"",I70/J70) -> 0.3 | L70: 574 | M70: 23.2 | N70: 6330 | O70: =IF(OR(N70="",G70=0),"",N70/G70) -> 0.065614213 | P70: 1 | Q70: 5.1 | R70: 46291 | S70: =IF(R70="","",'Como ler'!$B$27-R70) -> 1 | T70: 3 | U70: @superkochoficial, @lojaskoerich | V70: Gastronomia | W70: Gastronomia, Entretenimento e humor, Casa e organização | X70: Alta | Y70: =ROUND(IF(K70="",0,MIN(40,40*K70/1.5))+IF(S70="",0,IF(S70<=7,20,IF(S70<=30,12,IF(S70<=90,5,0))))+IF(Q70="",0,MIN(15,Q70*5))+IF(O70="",0,MIN(15,O70*30))+IF(E70="Criador(a)",10,IF(E70="Especialista que cria conteúdo",6,4)),0) -> 55 | AA70: Sim | AD70: Itajaí: bio, 2 post(s) marcados; Balneário Camboriú: bio, 3 post(s) marcados | AE70: Balneário Camboriú (3), Itajaí (2), Beto Carrero World (1) | AF70: 👩‍🍳 Tábata, Cozinheira Profissional fazendo reviews de restaurantes e receitas com humor / 📍Balneário Camboriú, Itajaí e por SC | AG70: https://instagram.com/coisasquecomo | AH70: Não contatada
A71: Balneário Camboriú | B71: Itajaí | C71: @eucarolinaalbuquerque | D71: Carolina Albuquerque | E71: Criador(a) | F71: Mulher | G71: 91438 | H71: Média (30k–100k) | I71: 0.0013 | J71: =IFERROR(INDEX('Como ler'!$B$20:$B$24,MATCH(H71,'Como ler'!$A$20:$A$24,0)),"") -> 0.015 | K71: =IF(OR(I71="",J71=""),"",I71/J71) -> 0.086666667 | L71: 190 | M71: 22.2 | N71: 1811 | O71: =IF(OR(N71="",G71=0),"",N71/G71) -> 0.01980577 | P71: 0.45 | Q71: 3.2 | R71: 46291 | S71: =IF(R71="","",'Como ler'!$B$27-R71) -> 1 | T71: 0 | V71: Gastronomia | W71: Gastronomia, Lifestyle, Negócios e empreendedorismo | X71: Alta | Y71: =ROUND(IF(K71="",0,MIN(40,40*K71/1.5))+IF(S71="",0,IF(S71<=7,20,IF(S71<=30,12,IF(S71<=90,5,0))))+IF(Q71="",0,MIN(15,Q71*5))+IF(O71="",0,MIN(15,O71*30))+IF(E71="Criador(a)",10,IF(E71="Especialista que cria conteúdo",6,4)),0) -> 48 | AA71: Sim | AD71: Balneário Camboriú: 3 post(s) marcados; Itajaí: 1 post(s) marcados | AE71: Balneário Camboriú (3), Buenos Aires, Argentina (1), Puerto Madero (1), Praia Brava - Itajaí SC (1) | AF71: Minha rotina: Experiências, Jesus, Receitas & muito Café ☕️ / Do Direito para as telas: influenciadora e empresária @aurahclube 🪐🤎 | AG71: https://instagram.com/eucarolinaalbuquerque | AH71: Não contatada
A72: Balneário Camboriú | C72: @paulafpaiva | D72: Paula Paiva | E72: Criador(a) | F72: Mulher | G72: 86311 | H72: Média (30k–100k) | I72: 0.0013 | J72: =IFERROR(INDEX('Como ler'!$B$20:$B$24,MATCH(H72,'Como ler'!$A$20:$A$24,0)),"") -> 0.015 | K72: =IF(OR(I72="",J72=""),"",I72/J72) -> 0.086666667 | L72: 110 | M72: 5.7 | N72: 1998 | O72: =IF(OR(N72="",G72=0),"",N72/G72) -> 0.023148845 | P72: 0.78 | Q72: 11.2 | R72: 46292 | S72: =IF(R72="","",'Como ler'!$B$27-R72) -> 0 | T72: 1 | U72: @desincha, @desincoffee, @super.nutrition | V72: Lifestyle | W72: Lifestyle | X72: Média | Y72: =ROUND(IF(K72="",0,MIN(40,40*K72/1.5))+IF(S72="",0,IF(S72<=7,20,IF(S72<=30,12,IF(S72<=90,5,0))))+IF(Q72="",0,MIN(15,Q72*5))+IF(O72="",0,MIN(15,O72*30))+IF(E72="Criador(a)",10,IF(E72="Especialista que cria conteúdo",6,4)),0) -> 48 | AB72: Sim | AC72: email | AD72: Balneário Camboriú: 9 post(s) marcados | AE72: Balneário Camboriú (9) | AF72: -36kg | Moébius | vida real | 💌 [e-mail na bio] / 🏷️ PAIVA: @gocasebr / 🏷️ PAULAPAIVA: @desincha @mafit_ @mexidonabrasil / links/cupons👇🏻 | AG72: https://instagram.com/paulafpaiva | AH72: Não contatada
A73: Balneário Camboriú | C73: @leidy_knowles | D73: Olívia Knowles | Lifestyle Feminino | E73: Criador(a) | F73: Mulher | G73: 69246 | H73: Média (30k–100k) | I73: 0.0014 | J73: =IFERROR(INDEX('Como ler'!$B$20:$B$24,MATCH(H73,'Como ler'!$A$20:$A$24,0)),"") -> 0.015 | K73: =IF(OR(I73="",J73=""),"",I73/J73) -> 0.093333333 | L73: 818 | M73: 19 | N73: 899 | O73: =IF(OR(N73="",G73=0),"",N73/G73) -> 0.012982699 | P73: 0.56 | Q73: 2.7 | R73: 46292 | S73: =IF(R73="","",'Como ler'!$B$27-R73) -> 0 | T73: 0 | V73: Fitness e wellness | W73: Fitness e wellness, Moda, Viagem, Lifestyle | X73: Média | Y73: =ROUND(IF(K73="",0,MIN(40,40*K73/1.5))+IF(S73="",0,IF(S73<=7,20,IF(S73<=30,12,IF(S73<=90,5,0))))+IF(Q73="",0,MIN(15,Q73*5))+IF(O73="",0,MIN(15,O73*30))+IF(E73="Criador(a)",10,IF(E73="Especialista que cria conteúdo",6,4)),0) -> 46 | Z73: Digital creator | AD73: Balneário Camboriú: bio, 8 post(s) marcados | AE73: Balneário Camboriú (7), Beira Mar De Balneario Camboriu - Sc (1), Santa Catarina, Brasil (1) | AF73: Apaixonada por viagens e cafés ☕️ / Autocuidado e estilo de vida saudável 🧘‍♀️ / Criando a vida que sempre sonhei 🤎 / 📍Balneário Camboriú | AG73: https://instagram.com/leidy_knowles | AH73: Não contatada
A74: Balneário Camboriú | C74: @rolezandoembcc | D74: Rolezando em balneario | E74: Página local / guia | F74: Página/marca | G74: 60353 | H74: Média (30k–100k) | I74: 0.0081 | J74: =IFERROR(INDEX('Como ler'!$B$20:$B$24,MATCH(H74,'Como ler'!$A$20:$A$24,0)),"") -> 0.015 | K74: =IF(OR(I74="",J74=""),"",I74/J74) -> 0.54 | L74: 552 | M74: 29.7 | N74: 13208 | O74: =IF(OR(N74="",G74=0),"",N74/G74) -> 0.21884579 | P74: 1 | Q74: 0.3 | R74: 45722 | S74: =IF(R74="","",'Como ler'!$B$27-R74) -> 570 | T74: 0 | V74: Gastronomia | W74: Gastronomia, Dicas locais | X74: Baixa | Y74: =ROUND(IF(K74="",0,MIN(40,40*K74/1.5))+IF(S74="",0,IF(S74<=7,20,IF(S74<=30,12,IF(S74<=90,5,0))))+IF(Q74="",0,MIN(15,Q74*5))+IF(O74="",0,MIN(15,O74*30))+IF(E74="Criador(a)",10,IF(E74="Especialista que cria conteúdo",6,4)),0) -> 26 | Z74: Digital creator | AC74: whats | AD74: Balneário Camboriú: 3 post(s) marcados | AE74: Balneário Camboriú (3) | AF74: 📍Dicas do que há de melhor em balneário! / Parcerias [telefone na bio] | AG74: https://instagram.com/rolezandoembcc | AH74: Não contatada
A75: Balneário Camboriú | C75: @nicoleborsatto | D75: Nicole Borsatto Antunes | E75: Criador(a) | F75: Mulher | G75: 57917 | H75: Média (30k–100k) | I75: 0.0033 | J75: =IFERROR(INDEX('Como ler'!$B$20:$B$24,MATCH(H75,'Como ler'!$A$20:$A$24,0)),"") -> 0.015 | K75: =IF(OR(I75="",J75=""),"",I75/J75) -> 0.22 | L75: 1435 | M75: 29.2 | N75: 4004 | O75: =IF(OR(N75="",G75=0),"",N75/G75) -> 0.069133415 | P75: 0.67 | Q75: 3 | R75: 46292 | S75: =IF(R75="","",'Como ler'!$B$27-R75) -> 0 | T75: 0 | V75: Moda | W75: Moda, UGC, Negócios e empreendedorismo, Entretenimento e humor | X75: Alta | Y75: =ROUND(IF(K75="",0,MIN(40,40*K75/1.5))+IF(S75="",0,IF(S75<=7,20,IF(S75<=30,12,IF(S75<=90,5,0))))+IF(Q75="",0,MIN(15,Q75*5))+IF(O75="",0,MIN(15,O75*30))+IF(E75="Criador(a)",10,IF(E75="Especialista que cria conteúdo",6,4)),0) -> 53 | AA75: Sim | AD75: Balneário Camboriú: 2 post(s) marcados | AE75: Balneário Camboriú (2), Greenvalley (1), Acampamento Farroupilha - Parque Harmonia (1), Arena do Grêmio (1) | AF75: • Influencer de moda & Empresária • / • Provadores | Campanhas | Conteúdo para marcas / • Coidealizadora & Marketing @ranchoassador | AG75: https://instagram.com/nicoleborsatto | AH75: Não contatada
A76: Balneário Camboriú | C76: @gabrielabrenda_ | D76: GABRIELA BRENDA 𓃮 | E76: Criador(a) | F76: Mulher | G76: 49027 | H76: Média (30k–100k) | I76: 0.0156 | J76: =IFERROR(INDEX('Como ler'!$B$20:$B$24,MATCH(H76,'Como ler'!$A$20:$A$24,0)),"") -> 0.015 | K76: =IF(OR(I76="",J76=""),"",I76/J76) -> 1.04 | L76: 2757 | M76: 43.8 | N76: 14307 | O76: =IF(OR(N76="",G76=0),"",N76/G76) -> 0.29181879 | P76: 1 | Q76: 2.4 | R76: 46279 | S76: =IF(R76="","",'Como ler'!$B$27-R76) -> 13 | T76: 0 | V76: Família e maternidade | W76: Família e maternidade, Fitness e wellness | X76: Média | Y76: =ROUND(IF(K76="",0,MIN(40,40*K76/1.5))+IF(S76="",0,IF(S76<=7,20,IF(S76<=30,12,IF(S76<=90,5,0))))+IF(Q76="",0,MIN(15,Q76*5))+IF(O76="",0,MIN(15,O76*30))+IF(E76="Criador(a)",10,IF(E76="Especialista que cria conteúdo",6,4)),0) -> 70 | AA76: Sim | AD76: Balneário Camboriú: bio | AF76: Filha do Deus vivo || Balneário Camboriú 🏇 / • Advogada • Unfiltered • Fitness • Bem-estar / ✨ Biomedicina 🎓 | AG76: https://instagram.com/gabrielabrenda_ | AH76: Não contatada
A77: Balneário Camboriú | C77: @dra.alynnegalindo | D77: Dra Alynne Galindo - Ginecologista em Balneário Camboriú | E77: Especialista que cria conteúdo | F77: Mulher | G77: 46025 | H77: Média (30k–100k) | I77: 0.0021 | J77: =IFERROR(INDEX('Como ler'!$B$20:$B$24,MATCH(H77,'Como ler'!$A$20:$A$24,0)),"") -> 0.015 | K77: =IF(OR(I77="",J77=""),"",I77/J77) -> 0.14 | L77: 109 | M77: 6.4 | N77: 2141 | O77: =IF(OR(N77="",G77=0),"",N77/G77) -> 0.046518197 | P77: 0.78 | Q77: 2.1 | R77: 46286 | S77: =IF(R77="","",'Como ler'!$B$27-R77) -> 6 | T77: 0 | V77: Casa e organização | W77: Casa e organização, Educação e conhecimento | X77: Alta | Y77: =ROUND(IF(K77="",0,MIN(40,40*K77/1.5))+IF(S77="",0,IF(S77<=7,20,IF(S77<=30,12,IF(S77<=90,5,0))))+IF(Q77="",0,MIN(15,Q77*5))+IF(O77="",0,MIN(15,O77*30))+IF(E77="Criador(a)",10,IF(E77="Especialista que cria conteúdo",6,4)),0) -> 42 | Z77: None | AA77: Sim | AB77: Sim | AC77: whats | AD77: Balneário Camboriú: 8 post(s) marcados | AE77: Balneário Camboriú (8) | AF77: 👩‍⚕️Saúde da Mulher e Autoestima / 🦋Estética e Cirurgia Íntima • Laser • Menopausa / 📲 [telefone na bio] / CRM: 17276 | RQE: 12391 | AG77: https://instagram.com/dra.alynnegalindo | AH77: Não contatada
A78: Balneário Camboriú | C78: @karina_smaniotto | D78: KARINA SMANIOTTO | Corretora e Mentora | E78: Especialista que cria conteúdo | F78: Mulher | G78: 44110 | H78: Média (30k–100k) | I78: 0.0034 | J78: =IFERROR(INDEX('Como ler'!$B$20:$B$24,MATCH(H78,'Como ler'!$A$20:$A$24,0)),"") -> 0.015 | K78: =IF(OR(I78="",J78=""),"",I78/J78) -> 0.22666667 | L78: 168 | M78: 27.3 | N78: 1115 | O78: =IF(OR(N78="",G78=0),"",N78/G78) -> 0.025277715 | P78: 0.56 | Q78: 7 | R78: 46291 | S78: =IF(R78="","",'Como ler'!$B$27-R78) -> 1 | T78: 0 | V78: Negócios e empreendedorismo | W78: Negócios e empreendedorismo, Educação e conhecimento | X78: Alta | Y78: =ROUND(IF(K78="",0,MIN(40,40*K78/1.5))+IF(S78="",0,IF(S78<=7,20,IF(S78<=30,12,IF(S78<=90,5,0))))+IF(Q78="",0,MIN(15,Q78*5))+IF(O78="",0,MIN(15,O78*30))+IF(E78="Criador(a)",10,IF(E78="Especialista que cria conteúdo",6,4)),0) -> 48 | AB78: Sim | AD78: Balneário Camboriú: 4 post(s) marcados | AE78: Balneário Camboriú (4), A I Livraria (1) | AF78: 🏆 Tricampeã Melhor Corretora do Sul do BR / 🤝 Embaixadora @dwvapp | @housioficial / 👠 Criadora do @mulhertambemvende / 🇺🇸 Vendo casas na Disney / 📈 15824F | AG78: https://instagram.com/karina_smaniotto | AH78: Não contatada
A79: Balneário Camboriú | C79: @alanazandonai | D79: Alana Zandonai | E79: Especialista que cria conteúdo | F79: Mulher | G79: 40058 | H79: Média (30k–100k) | I79: 0.0029 | J79: =IFERROR(INDEX('Como ler'!$B$20:$B$24,MATCH(H79,'Como ler'!$A$20:$A$24,0)),"") -> 0.015 | K79: =IF(OR(I79="",J79=""),"",I79/J79) -> 0.19333333 | L79: 79 | M79: 40.7 | N79: 568 | O79: =IF(OR(N79="",G79=0),"",N79/G79) -> 0.01417944 | P79: 0.42 | Q79: 4.8 | R79: 46288 | S79: =IF(R79="","",'Como ler'!$B$27-R79) -> 4 | T79: 0 | V79: Viagem | W79: Viagem, Lifestyle | X79: Média | Y79: =ROUND(IF(K79="",0,MIN(40,40*K79/1.5))+IF(S79="",0,IF(S79<=7,20,IF(S79<=30,12,IF(S79<=90,5,0))))+IF(Q79="",0,MIN(15,Q79*5))+IF(O79="",0,MIN(15,O79*30))+IF(E79="Criador(a)",10,IF(E79="Especialista que cria conteúdo",6,4)),0) -> 47 | Z79: Architectural Designer | AD79: Balneário Camboriú: bio, 3 post(s) marcados | AE79: Jaguariúna Rodeo Festival (4), Balneário Camboriú (3), Aeroporto Internacional de Viracopos (1), Valle Nevado Chile (1) | AF79: 📍Paranaense morando em Balneário Camboriú / 🇧🇷🇵🇾🇦🇷🇫🇷🇮🇪🇵🇹🇺🇸🇵🇪🇨🇦🇨🇱 / 🇮🇹Ítalo-brasileira / 👷🏻‍♀️Architecture @solttz.br | Travel @globalive_ | Lifestyle | AG79: https://instagram.com/alanazandonai | AH79: Não contatada
A80: Balneário Camboriú | B80: Itajaí | C80: @balneariomilgrau_ | D80: Balneário Camboriú Mil Grau 😎 | E80: Página local / guia | F80: Página/marca | G80: 37995 | H80: Média (30k–100k) | I80: 0.0079 | J80: =IFERROR(INDEX('Como ler'!$B$20:$B$24,MATCH(H80,'Como ler'!$A$20:$A$24,0)),"") -> 0.015 | K80: =IF(OR(I80="",J80=""),"",I80/J80) -> 0.52666667 | L80: 3265 | M80: 83 | N80: 131 | O80: =IF(OR(N80="",G80=0),"",N80/G80) -> 0.0034478221 | P80: 1 | Q80: 2.1 | R80: 46229 | S80: =IF(R80="","",'Como ler'!$B$27-R80) -> 63 | T80: 0 | V80: Dicas locais | W80: Dicas locais | X80: Baixa | Y80: =ROUND(IF(K80="",0,MIN(40,40*K80/1.5))+IF(S80="",0,IF(S80<=7,20,IF(S80<=30,12,IF(S80<=90,5,0))))+IF(Q80="",0,MIN(15,Q80*5))+IF(O80="",0,MIN(15,O80*30))+IF(E80="Criador(a)",10,IF(E80="Especialista que cria conteúdo",6,4)),0) -> 34 | Z80: Personal blog | AC80: direct | AD80: Itajaí: 1 post(s) marcados; Balneário Camboriú: 9 post(s) marcados | AE80: Balneário Camboriú (8), Itajaí (1), Roda Gigante Balneário Camboriú (1), Brasil (1) | AF80: 🔰PÁGINA OFICIAL | 2019 / ⚠️ Conta Reserva @balneariomilgrau_reserva / 📢 Quer anunciar sua empresa:chama direct. / 📍Marque @balneariomilgrau_ nos stories. | AG80: https://instagram.com/balneariomilgrau_ | AH80: Não contatada
A81: Balneário Camboriú | C81: @fabioframeup | D81: Fábio Ferreira | E81: Especialista que cria conteúdo | F81: Homem | G81: 37833 | H81: Média (30k–100k) | I81: 0.001 | J81: =IFERROR(INDEX('Como ler'!$B$20:$B$24,MATCH(H81,'Como ler'!$A$20:$A$24,0)),"") -> 0.015 | K81: =IF(OR(I81="",J81=""),"",I81/J81) -> 0.066666667 | L81: 54 | M81: 6.7 | N81: 845 | O81: =IF(OR(N81="",G81=0),"",N81/G81) -> 0.022334999 | P81: 0.08 | Q81: 7 | R81: 46292 | S81: =IF(R81="","",'Como ler'!$B$27-R81) -> 0 | T81: 0 | X81: Baixa | Y81: =ROUND(IF(K81="",0,MIN(40,40*K81/1.5))+IF(S81="",0,IF(S81<=7,20,IF(S81<=30,12,IF(S81<=90,5,0))))+IF(Q81="",0,MIN(15,Q81*5))+IF(O81="",0,MIN(15,O81*30))+IF(E81="Criador(a)",10,IF(E81="Especialista que cria conteúdo",6,4)),0) -> 43 | AD81: Balneário Camboriú: 1 post(s) marcados | AE81: Desert Safari (4), Autódromo Potenza (2), Balneário Camboriú - SC - A Dubai Brasileira (1), Emirados Arabes Abu Dahbi (1) | AF81: Se for viver, deixe um legado… faça uma marca no mundo que não possa ser apagada! @frameupjf @solucoesaereas @passocinco @gruponetworkjf | AG81: https://instagram.com/fabioframeup | AH81: Não contatada
A82: Balneário Camboriú | B82: Itapema | C82: @bcemfotos | D82: 📸BC - ITAPEMA📸 | E82: Página local / guia | F82: Página/marca | G82: 35099 | H82: Média (30k–100k) | I82: 0.0062 | J82: =IFERROR(INDEX('Como ler'!$B$20:$B$24,MATCH(H82,'Como ler'!$A$20:$A$24,0)),"") -> 0.015 | K82: =IF(OR(I82="",J82=""),"",I82/J82) -> 0.41333333 | L82: 387 | M82: 34.1 | N82: 1973 | O82: =IF(OR(N82="",G82=0),"",N82/G82) -> 0.056212428 | P82: 0.82 | Q82: 0.3 | R82: 46285 | S82: =IF(R82="","",'Como ler'!$B$27-R82) -> 7 | T82: 0 | V82: Dicas locais | W82: Dicas locais | X82: Baixa | Y82: =ROUND(IF(K82="",0,MIN(40,40*K82/1.5))+IF(S82="",0,IF(S82<=7,20,IF(S82<=30,12,IF(S82<=90,5,0))))+IF(Q82="",0,MIN(15,Q82*5))+IF(O82="",0,MIN(15,O82*30))+IF(E82="Criador(a)",10,IF(E82="Especialista que cria conteúdo",6,4)),0) -> 38 | Z82: Blogger | AC82: direct | AD82: Balneário Camboriú: bio, 6 post(s) marcados; Itapema: bio | AE82: Balneário Camboriú (6), Beto Carrero World (1) | AF82: 📸 • Fotos de BC, itapema e região / 🏝 • Balneário Camboriú / Itapema / 😉 • Dicas e Lugares / 💼 • Contato / Publicidade - Direct | AG82: https://instagram.com/bcemfotos | AH82: Não contatada
A83: Balneário Camboriú | B83: Camboriú | C83: @letiiciaramosss | D83: Leticia Ramos | E83: Criador(a) | F83: Mulher | G83: 29874 | H83: Micro (3k–30k) | I83: 0.0218 | J83: =IFERROR(INDEX('Como ler'!$B$20:$B$24,MATCH(H83,'Como ler'!$A$20:$A$24,0)),"") -> 0.025 | K83: =IF(OR(I83="",J83=""),"",I83/J83) -> 0.872 | L83: 726 | M83: 31.4 | N83: 2510 | O83: =IF(OR(N83="",G83=0),"",N83/G83) -> 0.084019549 | P83: 0.67 | Q83: 14 | R83: 46292 | S83: =IF(R83="","",'Como ler'!$B$27-R83) -> 0 | T83: 0 | V83: Fitness e wellness | W83: Fitness e wellness, Entretenimento e humor, Lifestyle, Família e maternidade | X83: Média | Y83: =ROUND(IF(K83="",0,MIN(40,40*K83/1.5))+IF(S83="",0,IF(S83<=7,20,IF(S83<=30,12,IF(S83<=90,5,0))))+IF(Q83="",0,MIN(15,Q83*5))+IF(O83="",0,MIN(15,O83*30))+IF(E83="Criador(a)",10,IF(E83="Especialista que cria conteúdo",6,4)),0) -> 71 | Z83: Digital creator | AB83: Sim | AC83: direct | AD83: Camboriú: 1 post(s) marcados; Balneário Camboriú: 2 post(s) marcados | AE83: Balneário Camboriú (2), Camboriú-SC (1), Píer Turístico de Porto Belo (1) | AF83: 🏃‍♀️ Corredora / 🔓 5km | 🔓 8km | 🔓 10km / 🤱 Maternidade real, Rotina & Humor / 💪 Fitness & Motivação / 📩 Parcerias: chame no direct | AG83: https://instagram.com/letiiciaramosss | AH83: Não contatada
A84: Balneário Camboriú | C84: @paulinhocatarina | D84: Paulinho Catarina 👨‍💻 | E84: Especialista que cria conteúdo | F84: Homem | G84: 27825 | H84: Micro (3k–30k) | I84: 0.0048 | J84: =IFERROR(INDEX('Como ler'!$B$20:$B$24,MATCH(H84,'Como ler'!$A$20:$A$24,0)),"") -> 0.025 | K84: =IF(OR(I84="",J84=""),"",I84/J84) -> 0.192 | L84: 258 | M84: 10.2 | N84: 1288 | O84: =IF(OR(N84="",G84=0),"",N84/G84) -> 0.046289308 | P84: 0.45 | Q84: 0.1 | R84: 46140 | S84: =IF(R84="","",'Como ler'!$B$27-R84) -> 152 | T84: 0 | X84: Baixa | Y84: =ROUND(IF(K84="",0,MIN(40,40*K84/1.5))+IF(S84="",0,IF(S84<=7,20,IF(S84<=30,12,IF(S84<=90,5,0))))+IF(Q84="",0,MIN(15,Q84*5))+IF(O84="",0,MIN(15,O84*30))+IF(E84="Criador(a)",10,IF(E84="Especialista que cria conteúdo",6,4)),0) -> 13 | AB84: Sim | AD84: Balneário Camboriú: 3 post(s) marcados | AE84: Balneário Camboriú (2), Ariri - Cananeia SP (1), Sepultura - Bombinhas - SC (1), Av. Atlântica - Balneário Camboriú/sc (1) | AF84: 👷🏼‍♂️ Production Engineer / ⚓️ @imperiumnautica / ⚓️ @netunocotas.bc / 🚗 @lavegobc / 🔮 @tarot.cartasonline | AG84: https://instagram.com/paulinhocatarina | AH84: Não contatada
A85: Balneário Camboriú | C85: @scorphousebc | D85: Scorp House - Balneário Camboriú | E85: Criador(a) | F85: Página/marca | G85: 26445 | H85: Micro (3k–30k) | I85: 0.0069 | J85: =IFERROR(INDEX('Como ler'!$B$20:$B$24,MATCH(H85,'Como ler'!$A$20:$A$24,0)),"") -> 0.025 | K85: =IF(OR(I85="",J85=""),"",I85/J85) -> 0.276 | L85: 175 | M85: 9 | N85: 6938 | O85: =IF(OR(N85="",G85=0),"",N85/G85) -> 0.26235583 | P85: 0.67 | Q85: 1.8 | R85: 45087 | S85: =IF(R85="","",'Como ler'!$B$27-R85) -> 1205 | T85: 0 | X85: Baixa | Y85: =ROUND(IF(K85="",0,MIN(40,40*K85/1.5))+IF(S85="",0,IF(S85<=7,20,IF(S85<=30,12,IF(S85<=90,5,0))))+IF(Q85="",0,MIN(15,Q85*5))+IF(O85="",0,MIN(15,O85*30))+IF(E85="Criador(a)",10,IF(E85="Especialista que cria conteúdo",6,4)),0) -> 34 | AB85: Sim | AD85: Balneário Camboriú: bio, 1 post(s) marcados | AE85: Balneário Camboriú (1) | AF85: 🟣Sejam bem-vindos a ScorpHouse‼️ / 🟣Balneário Camboriú - SC / 🟣A mansão de Influencers mais luxuosa que vc já viu! / 👇Deposite e ganhe 300% de Bônus👇🔞 | AG85: https://instagram.com/scorphousebc | AH85: Não contatada
A86: Balneário Camboriú | B86: Itajaí | C86: @vivipotrich | D86: Vivi Potrich | Massoterapeuta | E86: Especialista que cria conteúdo | F86: Mulher | G86: 26203 | H86: Micro (3k–30k) | I86: 0.02 | J86: =IFERROR(INDEX('Como ler'!$B$20:$B$24,MATCH(H86,'Como ler'!$A$20:$A$24,0)),"") -> 0.025 | K86: =IF(OR(I86="",J86=""),"",I86/J86) -> 0.8 | L86: 738 | M86: 8 | N86: 1466 | O86: =IF(OR(N86="",G86=0),"",N86/G86) -> 0.055947792 | P86: 0.11 | Q86: 0.8 | R86: 46250 | S86: =IF(R86="","",'Como ler'!$B$27-R86) -> 42 | T86: 0 | V86: Educação e conhecimento | W86: Educação e conhecimento | X86: Média | Y86: =ROUND(IF(K86="",0,MIN(40,40*K86/1.5))+IF(S86="",0,IF(S86<=7,20,IF(S86<=30,12,IF(S86<=90,5,0))))+IF(Q86="",0,MIN(15,Q86*5))+IF(O86="",0,MIN(15,O86*30))+IF(E86="Criador(a)",10,IF(E86="Especialista que cria conteúdo",6,4)),0) -> 38 | Z86: Digital creator | AB86: Sim | AD86: Balneário Camboriú: bio, 6 post(s) marcados; Itajaí: 1 post(s) marcados | AE86: Balneário Camboriú - SC (4), Cabeçudas Beach, Itajaí SC (1), Wave Academia - Barra Sul (1), Balneário Camboriú (1) | AF86: 💆‍♀️Massoterapeuta / 🤍@vivahbeleza_ebemestar / 👩‍🎓Estudante de Biomedicina / 📍Balneário Camboriú SC / 🌿Toque terapêutico com amor:clique no link ⤵️ | AG86: https://instagram.com/vivipotrich | AH86: Não contatada
A87: Balneário Camboriú | C87: @matheus_ramosc | D87: 𝗠𝗔𝗧𝗛𝗘𝗨𝗦 𝗥𝗔𝗠𝗢𝗦 | Mechas & Visagismo | E87: Especialista que cria conteúdo | F87: Homem | G87: 25962 | H87: Micro (3k–30k) | I87: 0.003 | J87: =IFERROR(INDEX('Como ler'!$B$20:$B$24,MATCH(H87,'Como ler'!$A$20:$A$24,0)),"") -> 0.025 | K87: =IF(OR(I87="",J87=""),"",I87/J87) -> 0.12 | L87: 89 | M87: 40 | N87: 3780 | O87: =IF(OR(N87="",G87=0),"",N87/G87) -> 0.14559741 | P87: 0.11 | Q87: 1.6 | R87: 46290 | S87: =IF(R87="","",'Como ler'!$B$27-R87) -> 2 | T87: 0 | V87: Beleza | W87: Beleza | X87: Média | Y87: =ROUND(IF(K87="",0,MIN(40,40*K87/1.5))+IF(S87="",0,IF(S87<=7,20,IF(S87<=30,12,IF(S87<=90,5,0))))+IF(Q87="",0,MIN(15,Q87*5))+IF(O87="",0,MIN(15,O87*30))+IF(E87="Criador(a)",10,IF(E87="Especialista que cria conteúdo",6,4)),0) -> 42 | Z87: Digital creator | AA87: Sim | AB87: Sim | AD87: Balneário Camboriú: bio, 7 post(s) marcados | AE87: Balneário Camboriú (7), Ramos Concept Hair (1), Transamerica Expo Center (1) | AF87: 𝙃𝙖𝙞𝙧 𝘼𝙧𝙩𝙞𝙨𝙩 & 𝙑𝙞𝙨𝙖𝙜𝙞𝙨𝙩𝙖 / 📍Balneário Camboriú | SC / 🔘Revelo identidade e Poder através da beleza,Transformações que unem emoção + técnica. / AGENDAMENTO⬇️ | AG87: https://instagram.com/matheus_ramosc | AH87: Não contatada
A88: Balneário Camboriú | C88: @annarafaellanogueira | D88: Anna Rafaella | E88: Criador(a) | F88: Mulher | G88: 24991 | H88: Micro (3k–30k) | I88: 0.022 | J88: =IFERROR(INDEX('Como ler'!$B$20:$B$24,MATCH(H88,'Como ler'!$A$20:$A$24,0)),"") -> 0.025 | K88: =IF(OR(I88="",J88=""),"",I88/J88) -> 0.88 | L88: 598 | M88: 6.7 | N88: 344 | O88: =IF(OR(N88="",G88=0),"",N88/G88) -> 0.013764955 | P88: 0.22 | Q88: 0.1 | R88: 46226 | S88: =IF(R88="","",'Como ler'!$B$27-R88) -> 66 | T88: 1 | V88: Beleza | W88: Beleza, Lifestyle, Moda | X88: Média | Y88: =ROUND(IF(K88="",0,MIN(40,40*K88/1.5))+IF(S88="",0,IF(S88<=7,20,IF(S88<=30,12,IF(S88<=90,5,0))))+IF(Q88="",0,MIN(15,Q88*5))+IF(O88="",0,MIN(15,O88*30))+IF(E88="Criador(a)",10,IF(E88="Especialista que cria conteúdo",6,4)),0) -> 39 | Z88: Digital creator | AA88: Sim | AD88: Balneário Camboriú: bio, 3 post(s) marcados | AE88: Balneario Camboriu, SC, Brazil (3), O Pharol (1), Centro, Florianópolis (1), Praia da Joaquina - Florianópolis (1) | AF88: 💫 Criando beleza nos detalhes / 📍 Balneário Camboriú / 🎀 Lifestyle | moda | experiências / 💌 Parcerias no direc | AG88: https://instagram.com/annarafaellanogueira | AH88: Não contatada
A89: Balneário Camboriú | B89: Camboriú | C89: @balneariocamboriubr | D89: BALNEÁRIO CAMBORIÚ 🇧🇷 | E89: Página local / guia | F89: Página/marca | G89: 24560 | H89: Micro (3k–30k) | I89: 0.0014 | J89: =IFERROR(INDEX('Como ler'!$B$20:$B$24,MATCH(H89,'Como ler'!$A$20:$A$24,0)),"") -> 0.025 | K89: =IF(OR(I89="",J89=""),"",I89/J89) -> 0.056 | L89: 226 | M89: 5.3 | N89: 212 | O89: =IF(OR(N89="",G89=0),"",N89/G89) -> 0.0086319218 | P89: 1 | Q89: 0.7 | R89: 46222 | S89: =IF(R89="","",'Como ler'!$B$27-R89) -> 70 | T89: 0 | V89: Dicas locais | W89: Dicas locais | X89: Baixa | Y89: =ROUND(IF(K89="",0,MIN(40,40*K89/1.5))+IF(S89="",0,IF(S89<=7,20,IF(S89<=30,12,IF(S89<=90,5,0))))+IF(Q89="",0,MIN(15,Q89*5))+IF(O89="",0,MIN(15,O89*30))+IF(E89="Criador(a)",10,IF(E89="Especialista que cria conteúdo",6,4)),0) -> 14 | AB89: Sim | AD89: Balneário Camboriú: bio, 6 post(s) marcados; Camboriú: bio | AE89: Balneário Camboriú (5), Balneário Camboriú - SC - A Dubai Brasileira (1) | AF89: 🎡🏖️🌊BALNEÁRIO CAMBORIÚ BR🌊🏖️🎡 / 🛩 ☀ ☁ 🚁 / 📸 🐬 🏖️🌊🏄🐬 / Tiktok 👇 / balneariocamboriubrasil | AG89: https://instagram.com/balneariocamboriubr | AH89: Não contatada
A90: Balneário Camboriú | C90: @lucianomastria | D90: Luciano Mastria / Noivas + loiros + maquiagem | E90: Especialista que cria conteúdo | F90: Homem | G90: 23216 | H90: Micro (3k–30k) | I90: 0.0034 | J90: =IFERROR(INDEX('Como ler'!$B$20:$B$24,MATCH(H90,'Como ler'!$A$20:$A$24,0)),"") -> 0.025 | K90: =IF(OR(I90="",J90=""),"",I90/J90) -> 0.136 | L90: 105 | M90: 17.5 | N90: 510 | O90: =IF(OR(N90="",G90=0),"",N90/G90) -> 0.021967609 | P90: 0.83 | Q90: 0.1 | R90: 46284 | S90: =IF(R90="","",'Como ler'!$B$27-R90) -> 8 | T90: 0 | V90: Beleza | W90: Beleza, Relacionamento, Moda | X90: Média | Y90: =ROUND(IF(K90="",0,MIN(40,40*K90/1.5))+IF(S90="",0,IF(S90<=7,20,IF(S90<=30,12,IF(S90<=90,5,0))))+IF(Q90="",0,MIN(15,Q90*5))+IF(O90="",0,MIN(15,O90*30))+IF(E90="Criador(a)",10,IF(E90="Especialista que cria conteúdo",6,4)),0) -> 23 | Z90: Artist | AA90: Sim | AB90: Sim | AD90: Balneário Camboriú: 2 post(s) marcados | AE90: Balneário Camboriú (2) | AF90: INTERNATIONAL BEAUTY ARTIST 🌎 / NOIVAS • MAKEUP • HAIR / MECHAS • COR • CORTES / ⚡ CREATOR OF EASYBEAUTY / 💄 EASYBEAUTY AUTOMAKEUP / ⬇️ BRIDE’S NEWS ⬇️ | AG90: https://instagram.com/lucianomastria | AH90: Não contatada
A91: Balneário Camboriú | B91: Itajaí | C91: @lidianyazevedocantora | D91: Lidiany Azevedo | E91: Criador(a) | F91: Mulher | G91: 22210 | H91: Micro (3k–30k) | I91: 0.0009 | J91: =IFERROR(INDEX('Como ler'!$B$20:$B$24,MATCH(H91,'Como ler'!$A$20:$A$24,0)),"") -> 0.025 | K91: =IF(OR(I91="",J91=""),"",I91/J91) -> 0.036 | L91: 36 | M91: 2.4 | N91: 222 | O91: =IF(OR(N91="",G91=0),"",N91/G91) -> 0.0099954975 | P91: 1 | Q91: 6.2 | R91: 46292 | S91: =IF(R91="","",'Como ler'!$B$27-R91) -> 0 | T91: 0 | V91: Entretenimento e humor | W91: Entretenimento e humor, Gastronomia | X91: Baixa | Y91: =ROUND(IF(K91="",0,MIN(40,40*K91/1.5))+IF(S91="",0,IF(S91<=7,20,IF(S91<=30,12,IF(S91<=90,5,0))))+IF(Q91="",0,MIN(15,Q91*5))+IF(O91="",0,MIN(15,O91*30))+IF(E91="Criador(a)",10,IF(E91="Especialista que cria conteúdo",6,4)),0) -> 46 | Z91: Musician/band | AB91: Sim | AD91: Balneário Camboriú: 5 post(s) marcados; Itajaí: 1 post(s) marcados | AE91: Balneário Camboriú - SC (2), Balneário Camboriú (2), Itajaí -SC (1), Balneario Camboriu, SC, Brazil (1) | AF91: CANTORA🎙️ / 💍 / Deus na frente / 🇧🇷🇵🇹🇺🇾🇪🇸🇧🇪✈️ / Hoje a capivara morde a boca da garrucha🤠 / @azevedosbrand_ / @tempoatempo.gv | AG91: https://instagram.com/lidianyazevedocantora | AH91: Não contatada
A92: Balneário Camboriú | C92: @visitebceregiao | D92: Visite BC e Região Costa Verde & Mar | E92: Página local / guia | F92: Página/marca | G92: 20487 | H92: Micro (3k–30k) | I92: 0.001 | J92: =IFERROR(INDEX('Como ler'!$B$20:$B$24,MATCH(H92,'Como ler'!$A$20:$A$24,0)),"") -> 0.025 | K92: =IF(OR(I92="",J92=""),"",I92/J92) -> 0.04 | L92: 22 | M92: 2.1 | N92: 305 | O92: =IF(OR(N92="",G92=0),"",N92/G92) -> 0.01488749 | P92: 0.56 | Q92: 4.7 | R92: 46292 | S92: =IF(R92="","",'Como ler'!$B$27-R92) -> 0 | T92: 0 | V92: Viagem | W92: Viagem, Família e maternidade | X92: Baixa | Y92: =ROUND(IF(K92="",0,MIN(40,40*K92/1.5))+IF(S92="",0,IF(S92<=7,20,IF(S92<=30,12,IF(S92<=90,5,0))))+IF(Q92="",0,MIN(15,Q92*5))+IF(O92="",0,MIN(15,O92*30))+IF(E92="Criador(a)",10,IF(E92="Especialista que cria conteúdo",6,4)),0) -> 41 | Z92: None | AB92: Sim | AD92: Balneário Camboriú: bio, 5 post(s) marcados | AE92: Balneário Camboriú (5) | AF92: 🌍 Bem-Vindos a Balneário Camboriú e Região Costa Verde & Mar / 🔹As informações que você precisa para nos visitar! ⬇️⬇️ | AG92: https://instagram.com/visitebceregiao | AH92: Não contatada
A93: Balneário Camboriú | C93: @ovendedorderua | D93: O Vendedor de Rua | Paulo Farias | E93: Criador(a) | F93: Homem | G93: 19134 | H93: Micro (3k–30k) | I93: 0.0013 | J93: =IFERROR(INDEX('Como ler'!$B$20:$B$24,MATCH(H93,'Como ler'!$A$20:$A$24,0)),"") -> 0.025 | K93: =IF(OR(I93="",J93=""),"",I93/J93) -> 0.052 | L93: 19 | M93: 7.9 | N93: 140 | O93: =IF(OR(N93="",G93=0),"",N93/G93) -> 0.0073168182 | P93: 0.1 | Q93: 0.2 | R93: 46292 | S93: =IF(R93="","",'Como ler'!$B$27-R93) -> 0 | T93: 0 | V93: Gastronomia | W93: Gastronomia, Família e maternidade | X93: Média | Y93: =ROUND(IF(K93="",0,MIN(40,40*K93/1.5))+IF(S93="",0,IF(S93<=7,20,IF(S93<=30,12,IF(S93<=90,5,0))))+IF(Q93="",0,MIN(15,Q93*5))+IF(O93="",0,MIN(15,O93*30))+IF(E93="Criador(a)",10,IF(E93="Especialista que cria conteúdo",6,4)),0) -> 33 | Z93: Digital creator | AD93: Balneário Camboriú: 10 post(s) marcados | AE93: Balneário Camboriú (10) | AG93: https://instagram.com/ovendedorderua | AH93: Não contatada
A94: Balneário Camboriú | C94: @andresonlindemberg | D94: Andreson Lindemberg | Cabeleireiro Maquiador-Balneário Camboriú | E94: Especialista que cria conteúdo | F94: Homem | G94: 18373 | H94: Micro (3k–30k) | I94: 0.0059 | J94: =IFERROR(INDEX('Como ler'!$B$20:$B$24,MATCH(H94,'Como ler'!$A$20:$A$24,0)),"") -> 0.025 | K94: =IF(OR(I94="",J94=""),"",I94/J94) -> 0.236 | L94: 98 | M94: 16.1 | N94: 893 | O94: =IF(OR(N94="",G94=0),"",N94/G94) -> 0.04860393 | P94: 0.1 | Q94: 0.2 | R94: 46290 | S94: =IF(R94="","",'Como ler'!$B$27-R94) -> 2 | T94: 0 | V94: Beleza | W94: Beleza, Dicas locais | X94: Média | Y94: =ROUND(IF(K94="",0,MIN(40,40*K94/1.5))+IF(S94="",0,IF(S94<=7,20,IF(S94<=30,12,IF(S94<=90,5,0))))+IF(Q94="",0,MIN(15,Q94*5))+IF(O94="",0,MIN(15,O94*30))+IF(E94="Criador(a)",10,IF(E94="Especialista que cria conteúdo",6,4)),0) -> 35 | AB94: Sim | AD94: Balneário Camboriú: 1 post(s) marcados | AE94: Beauty Shop Cabeleireiros (4), Joinville, Santa Catarina, Brazil (2), Santa Catarina - Blumenau (1), Balneário Camboriú (1) | AF94: ✈️ Disp.Int/Nac | Agenda aberta / • Especialista em Prod. de Misses 👑 | 50+ títulos nac & int / • Expert em loiros /+3.000 atendimentos / • 3xPremiado SC/BR | AG94: https://instagram.com/andresonlindemberg | AH94: Não contatada
A95: Balneário Camboriú | C95: @guilhermefiguero | D95: Guilherme Figueró | E95: Especialista que cria conteúdo | F95: Homem | G95: 16144 | H95: Micro (3k–30k) | I95: 0.0022 | J95: =IFERROR(INDEX('Como ler'!$B$20:$B$24,MATCH(H95,'Como ler'!$A$20:$A$24,0)),"") -> 0.025 | K95: =IF(OR(I95="",J95=""),"",I95/J95) -> 0.088 | L95: 27 | M95: 4.7 | N95: 273 | O95: =IF(OR(N95="",G95=0),"",N95/G95) -> 0.016910307 | P95: 0.67 | Q95: 0.5 | R95: 46254 | S95: =IF(R95="","",'Como ler'!$B$27-R95) -> 38 | T95: 0 | V95: Fitness e wellness | W95: Fitness e wellness | X95: Baixa | Y95: =ROUND(IF(K95="",0,MIN(40,40*K95/1.5))+IF(S95="",0,IF(S95<=7,20,IF(S95<=30,12,IF(S95<=90,5,0))))+IF(Q95="",0,MIN(15,Q95*5))+IF(O95="",0,MIN(15,O95*30))+IF(E95="Criador(a)",10,IF(E95="Especialista que cria conteúdo",6,4)),0) -> 16 | AD95: Balneário Camboriú: 2 post(s) marcados | AE95: Balneário Camboriú (2), FIFA World Cup (1), Academia Wave (1) | AF95: Personal Trainer 🔪💀 / @academiawave há 20 anos / Assessoria Esportiva TEAM @netoscardovelli / Longevidade Biomecânica / Amazon Marketplace Seller 💼 | AG95: https://instagram.com/guilhermefiguero | AH95: Não contatada
A96: Balneário Camboriú | C96: @jessica.santtosp | D96: Jéssica Santos | E96: Especialista que cria conteúdo | F96: Mulher | G96: 16024 | H96: Micro (3k–30k) | I96: 0.0107 | J96: =IFERROR(INDEX('Como ler'!$B$20:$B$24,MATCH(H96,'Como ler'!$A$20:$A$24,0)),"") -> 0.025 | K96: =IF(OR(I96="",J96=""),"",I96/J96) -> 0.428 | L96: 250 | M96: 35.4 | N96: 2898 | O96: =IF(OR(N96="",G96=0),"",N96/G96) -> 0.18085372 | P96: 0.78 | Q96: 1.5 | R96: 46288 | S96: =IF(R96="","",'Como ler'!$B$27-R96) -> 4 | T96: 0 | V96: Moda | W96: Moda | X96: Média | Y96: =ROUND(IF(K96="",0,MIN(40,40*K96/1.5))+IF(S96="",0,IF(S96<=7,20,IF(S96<=30,12,IF(S96<=90,5,0))))+IF(Q96="",0,MIN(15,Q96*5))+IF(O96="",0,MIN(15,O96*30))+IF(E96="Criador(a)",10,IF(E96="Especialista que cria conteúdo",6,4)),0) -> 50 | Z96: Entrepreneur | AB96: Sim | AD96: Balneário Camboriú: 1 post(s) marcados | AE96: Green Valley (1), Balneário Camboriú (1) | AF96: 🎙️LIVE SELLER / 📈 Ajudo marcas a venderem mais com lives e conteúdos que convertem. / 🎯 Criadora do método LIVE PRO / + de 1000 lives | AG96: https://instagram.com/jessica.santtosp | AH96: Não contatada
A97: Balneário Camboriú | C97: @brunafarias.93 | D97: Bruna Santos | E97: Criador(a) | F97: Mulher | G97: 14144 | H97: Micro (3k–30k) | I97: 0.0008 | J97: =IFERROR(INDEX('Como ler'!$B$20:$B$24,MATCH(H97,'Como ler'!$A$20:$A$24,0)),"") -> 0.025 | K97: =IF(OR(I97="",J97=""),"",I97/J97) -> 0.032 | L97: 14 | M97: 1.7 | N97: 168 | O97: =IF(OR(N97="",G97=0),"",N97/G97) -> 0.011877828 | P97: 1 | Q97: 1.2 | R97: 46292 | S97: =IF(R97="","",'Como ler'!$B$27-R97) -> 0 | T97: 0 | V97: Educação e conhecimento | W97: Educação e conhecimento, Relacionamento | X97: Média | Y97: =ROUND(IF(K97="",0,MIN(40,40*K97/1.5))+IF(S97="",0,IF(S97<=7,20,IF(S97<=30,12,IF(S97<=90,5,0))))+IF(Q97="",0,MIN(15,Q97*5))+IF(O97="",0,MIN(15,O97*30))+IF(E97="Criador(a)",10,IF(E97="Especialista que cria conteúdo",6,4)),0) -> 37 | AB97: Sim | AC97: whats | AD97: Balneário Camboriú: bio, 1 post(s) marcados | AE97: Balneário Shopping (1), Balneário Camboriú (1) | AF97: 📍| Balneário Camboriú / 🎓| Psicoterapeuta / 🎥| +de 10M de views no tiktok / 🔥| +de 20M de Views no Geral / 🚀| Parcerias via WhatsApp | AG97: https://instagram.com/brunafarias.93 | AH97: Não contatada
A98: Balneário Camboriú | C98: @jordanamedeirosb | D98: JORDANA MEDEIROS | Comunicação para Líderes | E98: Especialista que cria conteúdo | F98: Mulher | G98: 12333 | H98: Micro (3k–30k) | I98: 0.004 | J98: =IFERROR(INDEX('Como ler'!$B$20:$B$24,MATCH(H98,'Como ler'!$A$20:$A$24,0)),"") -> 0.025 | K98: =IF(OR(I98="",J98=""),"",I98/J98) -> 0.16 | L98: 57 | M98: 5 | N98: 307 | O98: =IF(OR(N98="",G98=0),"",N98/G98) -> 0.024892565 | P98: 0.67 | Q98: 4.7 | R98: 46280 | S98: =IF(R98="","",'Como ler'!$B$27-R98) -> 12 | T98: 0 | V98: Negócios e empreendedorismo | W98: Negócios e empreendedorismo, Educação e conhecimento | X98: Alta | Y98: =ROUND(IF(K98="",0,MIN(40,40*K98/1.5))+IF(S98="",0,IF(S98<=7,20,IF(S98<=30,12,IF(S98<=90,5,0))))+IF(Q98="",0,MIN(15,Q98*5))+IF(O98="",0,MIN(15,O98*30))+IF(E98="Criador(a)",10,IF(E98="Especialista que cria conteúdo",6,4)),0) -> 38 | AA98: Sim | AB98: Sim | AD98: Balneário Camboriú: 6 post(s) marcados | AE98: Balneário Camboriú (6), Tubarão (1) | AF98: Te ensino a potencializar sua voz de LÍDER! / Há quase 10 anos na área | Uma vida nos palcos / Formação em Comunicação e Oratória / ⬇️ PRÓXIMA TURMA 📍BC | AG98: https://instagram.com/jordanamedeirosb | AH98: Não contatada
A99: Balneário Camboriú | C99: @thiagohlopes.treinador | D99: Thiago Henrique • Entrenador Personal 🇪🇸 | E99: Especialista que cria conteúdo | F99: Homem | G99: 12154 | H99: Micro (3k–30k) | I99: 0.0035 | J99: =IFERROR(INDEX('Como ler'!$B$20:$B$24,MATCH(H99,'Como ler'!$A$20:$A$24,0)),"") -> 0.025 | K99: =IF(OR(I99="",J99=""),"",I99/J99) -> 0.14 | L99: 65 | M99: 0.8 | N99: 510 | O99: =IF(OR(N99="",G99=0),"",N99/G99) -> 0.041961494 | P99: 0.67 | Q99: 0.1 | R99: 46218 | S99: =IF(R99="","",'Como ler'!$B$27-R99) -> 74 | T99: 0 | V99: Fitness e wellness | W99: Fitness e wellness, Educação e conhecimento | X99: Média | Y99: =ROUND(IF(K99="",0,MIN(40,40*K99/1.5))+IF(S99="",0,IF(S99<=7,20,IF(S99<=30,12,IF(S99<=90,5,0))))+IF(Q99="",0,MIN(15,Q99*5))+IF(O99="",0,MIN(15,O99*30))+IF(E99="Criador(a)",10,IF(E99="Especialista que cria conteúdo",6,4)),0) -> 16 | AB99: Sim | AD99: Balneário Camboriú: 1 post(s) marcados | AE99: Campo Grande, MS (1), Governador Celso Ramos (1), Juistreet Complexo (1), Balneário Camboriú (1) | AF99: 🏋️‍♀️ + de 50 alunas tiveram resultados e aprenderam a treinar com minha metodologia de treino e meu trabalho de Personal Trainer. / 📍SC / MS | AG99: https://instagram.com/thiagohlopes.treinador | AH99: Não contatada
A100: Balneário Camboriú | C100: @draamanda_rodrigues | D100: Amanda Ramos Rodrigues | E100: Especialista que cria conteúdo | F100: Mulher | G100: 11685 | H100: Micro (3k–30k) | I100: 0.005 | J100: =IFERROR(INDEX('Como ler'!$B$20:$B$24,MATCH(H100,'Como ler'!$A$20:$A$24,0)),"") -> 0.025 | K100: =IF(OR(I100="",J100=""),"",I100/J100) -> 0.2 | L100: 42 | M100: 14.2 | N100: 334 | O100: =IF(OR(N100="",G100=0),"",N100/G100) -> 0.028583654 | P100: 0.11 | Q100: 4.3 | R100: 46292 | S100: =IF(R100="","",'Como ler'!$B$27-R100) -> 0 | T100: 0 | X100: Baixa | Y100: =ROUND(IF(K100="",0,MIN(40,40*K100/1.5))+IF(S100="",0,IF(S100<=7,20,IF(S100<=30,12,IF(S100<=90,5,0))))+IF(Q100="",0,MIN(15,Q100*5))+IF(O100="",0,MIN(15,O100*30))+IF(E100="Criador(a)",10,IF(E100="Especialista que cria conteúdo",6,4)),0) -> 47 | Z100: Digital creator | AA100: Sim | AB100: Sim | AD100: Balneário Camboriú: bio, 8 post(s) marcados | AE100: Balneário Camboriú (8), Greenvalley (1) | AF100: Cirurgiã-dentista CRO/SC 15221 / A arte de criar sorrisos únicos 🎨🖌️✨ / 🦷 Lentes em resina e porcelanas / 🔩Implantodontista / 📍Balneário Camboriú - SC | AG100: https://instagram.com/draamanda_rodrigues | AH100: Não contatada
...

Sheet Itajaí
A1: Cidade principal | B1: Também atua em | C1: Perfil | D1: Nome | E1: Tipo | F1: Criador(a) | G1: Seguidores | H1: Faixa | I1: Engajamento | J1: Engaj. de referência | K1: Engaj. vs referência | L1: Média de curtidas | M1: Média de comentários | N1: Views medianas (reels) | O1: Views/seguidores | P1: % vídeos | Q1: Posts/semana | R1: Último post | S1: Dias sem postar | T1: Publis (de 12) | U1: Marcas em publis | V1: Nicho principal | W1: Nichos | X1: Fit CRIA | Y1: Score (0-100) | Z1: Categoria no IG | AA1: Verificado | AB1: Link na bio | AC1: Canal de contato | AD1: Como confirmei a cidade | AE1: Locais marcados | AF1: Bio | AG1: Link | AH1: Status | AI1: Observações
A2: Itajaí | C2: @thaisedemari | D2: Thaise de Mari | E2: Criador(a) | F2: Mulher | G2: 1049161 | H2: Mega (500k+) | I2: 0.0015 | J2: =IFERROR(INDEX('Como ler'!$B$20:$B$24,MATCH(H2,'Como ler'!$A$20:$A$24,0)),"") -> 0.007 | K2: =IF(OR(I2="",J2=""),"",I2/J2) -> 0.21428571 | L2: 2112 | M2: 86.8 | N2: 19137 | O2: =IF(OR(N2="",G2=0),"",N2/G2) -> 0.018240289 | P2: 0.42 | Q2: 0.9 | R2: 46286 | S2: =IF(R2="","",'Como ler'!$B$27-R2) -> 6 | T2: 0 | V2: Beleza | W2: Beleza, Negócios e empreendedorismo, Lifestyle, Moda | X2: Alta | Y2: =ROUND(IF(K2="",0,MIN(40,40*K2/1.5))+IF(S2="",0,IF(S2<=7,20,IF(S2<=30,12,IF(S2<=90,5,0))))+IF(Q2="",0,MIN(15,Q2*5))+IF(O2="",0,MIN(15,O2*30))+IF(E2="Criador(a)",10,IF(E2="Especialista que cria conteúdo",6,4)),0) -> 41 | Z2: Entrepreneur | AD2: Itajaí: bio | AE2: Barcelona, España (2), Formentera, Islas Baleares, Spain (2), Ibiza, Spain (2), Rio de Janeiro, Rio de Janeiro (1) | AF2: Fashion • Beauty • Lifestyle • Travel • Real life / Founder @nowwabrand / Caixa Postal 46 Itajaí-SC Cep 88301-970 | AG2: https://instagram.com/thaisedemari | AH2: Não contatada
A3: Itajaí | C3: @lucasmirandasc | D3: Lucas Miranda | E3: Criador(a) | F3: Homem | G3: 189201 | H3: Macro (100k–500k) | I3: 0.0033 | J3: =IFERROR(INDEX('Como ler'!$B$20:$B$24,MATCH(H3,'Como ler'!$A$20:$A$24,0)),"") -> 0.01 | K3: =IF(OR(I3="",J3=""),"",I3/J3) -> 0.33 | L3: 1060 | M3: 57.3 | N3: 22196 | O3: =IF(OR(N3="",G3=0),"",N3/G3) -> 0.11731439 | P3: 0.67 | Q3: 0.7 | R3: 46292 | S3: =IF(R3="","",'Como ler'!$B$27-R3) -> 0 | T3: 0 | V3: Gastronomia | W3: Gastronomia, Fitness e wellness, Viagem | X3: Baixa | Y3: =ROUND(IF(K3="",0,MIN(40,40*K3/1.5))+IF(S3="",0,IF(S3<=7,20,IF(S3<=30,12,IF(S3<=90,5,0))))+IF(Q3="",0,MIN(15,Q3*5))+IF(O3="",0,MIN(15,O3*30))+IF(E3="Criador(a)",10,IF(E3="Especialista que cria conteúdo",6,4)),0) -> 46 | Z3: Digital creator | AD3: Itajaí: bio, 2 post(s) marcados | AE3: Itajaí- Santa Catarina (2) | AF3: Itajaí - SC📍 / Hospedagens | Gastronomia / MISTER LAS AMÉRICAS ITAJAÍ 2026 / Embaixador: @lfmen @mancluboficial @3coracoes @maxinutrioficial @academia.ad3 | AG3: https://instagram.com/lucasmirandasc | AH3: Não contatada
A4: Itajaí | C4: @superdicasnaestrada | D4: Super Dicas na Estrada - Lucas e Maitê | E4: Criador(a) | F4: Homem | G4: 100790 | H4: Macro (100k–500k) | J4: =IFERROR(INDEX('Como ler'!$B$20:$B$24,MATCH(H4,'Como ler'!$A$20:$A$24,0)),"") -> 0.01 | K4: =IF(OR(I4="",J4=""),"",I4/J4) | M4: 48.2 | N4: 2518 | O4: =IF(OR(N4="",G4=0),"",N4/G4) -> 0.024982637 | P4: 0.89 | Q4: 1.5 | R4: 46284 | S4: =IF(R4="","",'Como ler'!$B$27-R4) -> 8 | T4: 0 | V4: Dicas locais | W4: Dicas locais, Gastronomia | X4: Baixa | Y4: =ROUND(IF(K4="",0,MIN(40,40*K4/1.5))+IF(S4="",0,IF(S4<=7,20,IF(S4<=30,12,IF(S4<=90,5,0))))+IF(Q4="",0,MIN(15,Q4*5))+IF(O4="",0,MIN(15,O4*30))+IF(E4="Criador(a)",10,IF(E4="Especialista que cria conteúdo",6,4)),0) -> 30 | Z4: Digital creator | AB4: Sim | AC4: whats | AD4: Itajaí: 1 post(s) marcados | AE4: Blumenau, Santa Catarina, Brazil (2), Piçarras (1), Rodeio (1), Itajaí -SC (1) | AF4: 🌎 Super Dicas pelas estradas do Sul do Brasil! / 🚀+ de 600 empresas parceiras! / ⭐️ Divulgue sua marca aqui! / ⬇️ Contato Whats: | AG4: https://instagram.com/superdicasnaestrada | AH4: Não contatada | AI4: Curtidas ocultas: engajamento calculado só com posts visíveis ou indisponível
A5: Itajaí | C5: @raissaarcanjo | D5: Raíssa Arcanjo | E5: Criador(a) | F5: Mulher | G5: 89409 | H5: Média (30k–100k) | I5: 0.0014 | J5: =IFERROR(INDEX('Como ler'!$B$20:$B$24,MATCH(H5,'Como ler'!$A$20:$A$24,0)),"") -> 0.015 | K5: =IF(OR(I5="",J5=""),"",I5/J5) -> 0.093333333 | L5: 264 | M5: 41.7 | N5: 1456 | O5: =IF(OR(N5="",G5=0),"",N5/G5) -> 0.016284714 | P5: 0.67 | Q5: 6.2 | R5: 46289 | S5: =IF(R5="","",'Como ler'!$B$27-R5) -> 3 | T5: 0 | V5: Negócios e empreendedorismo | W5: Negócios e empreendedorismo | X5: Alta | Y5: =ROUND(IF(K5="",0,MIN(40,40*K5/1.5))+IF(S5="",0,IF(S5<=7,20,IF(S5<=30,12,IF(S5<=90,5,0))))+IF(Q5="",0,MIN(15,Q5*5))+IF(O5="",0,MIN(15,O5*30))+IF(E5="Criador(a)",10,IF(E5="Especialista que cria conteúdo",6,4)),0) -> 48 | Z5: Digital creator | AA5: Sim | AB5: Sim | AD5: Itajaí: 4 post(s) marcados | AE5: Itajaí (4), Greenvalley (1), Balneário Shopping (1), Navegantes (1) | AF5: Geralmente posto muitooo. 🗣️ / Palestrante, Mentora, Influenciadora, Empreendedora, Colunista Social. 🧠 / VICIADA EM VER GENTE VENCENDO NA VIDA! 🫀 | AG5: https://instagram.com/raissaarcanjo | AH5: Não contatada
A6: Itajaí | C6: @itajaisc_ | D6: Renildo Figueiredo 😎 | E6: Criador(a) | F6: Homem | G6: 83440 | H6: Média (30k–100k) | I6: 0.0109 | J6: =IFERROR(INDEX('Como ler'!$B$20:$B$24,MATCH(H6,'Como ler'!$A$20:$A$24,0)),"") -> 0.015 | K6: =IF(OR(I6="",J6=""),"",I6/J6) -> 0.72666667 | L6: 1267 | M6: 140 | N6: 9851 | O6: =IF(OR(N6="",G6=0),"",N6/G6) -> 0.11806088 | P6: 0.9 | Q6: 15.8 | R6: 46291 | S6: =IF(R6="","",'Como ler'!$B$27-R6) -> 1 | T6: 0 | V6: Finanças | W6: Finanças, Dicas locais, Entretenimento e humor, Família e maternidade | X6: Média | Y6: =ROUND(IF(K6="",0,MIN(40,40*K6/1.5))+IF(S6="",0,IF(S6<=7,20,IF(S6<=30,12,IF(S6<=90,5,0))))+IF(Q6="",0,MIN(15,Q6*5))+IF(O6="",0,MIN(15,O6*30))+IF(E6="Criador(a)",10,IF(E6="Especialista que cria conteúdo",6,4)),0) -> 68 | AC6: direct | AD6: Itajaí: bio, 7 post(s) marcados | AE6: Itajaí, Santa Catarina, Brasil (6), Parrilla 674 (2), Balneário Piçarras - SC (1), Itajaí (1) | AF6: Um Nortista🛫 vivendo em 🛬Itajaí😎 / 🌴 Itajaí & SC sem filtros / 🏡 Onde morar, passear e investir / 💰 Custo de vida, dicas e lazer / 📲 parceiras via Direct | AG6: https://instagram.com/itajaisc_ | AH6: Não contatada
A7: Itajaí | C7: @nubiakatyoficial | D7: Núbia | Mãe & Blogueira • Itajai | E7: Criador(a) | F7: Mulher | G7: 78728 | H7: Média (30k–100k) | I7: 0.0063 | J7: =IFERROR(INDEX('Como ler'!$B$20:$B$24,MATCH(H7,'Como ler'!$A$20:$A$24,0)),"") -> 0.015 | K7: =IF(OR(I7="",J7=""),"",I7/J7) -> 0.42 | L7: 543 | M7: 26.1 | N7: 5011 | O7: =IF(OR(N7="",G7=0),"",N7/G7) -> 0.063649527 | P7: 0.9 | Q7: 15.8 | R7: 46292 | S7: =IF(R7="","",'Como ler'!$B$27-R7) -> 0 | T7: 0 | V7: Entretenimento e humor | W7: Entretenimento e humor, Família e maternidade | X7: Média | Y7: =ROUND(IF(K7="",0,MIN(40,40*K7/1.5))+IF(S7="",0,IF(S7<=7,20,IF(S7<=30,12,IF(S7<=90,5,0))))+IF(Q7="",0,MIN(15,Q7*5))+IF(O7="",0,MIN(15,O7*30))+IF(E7="Criador(a)",10,IF(E7="Especialista que cria conteúdo",6,4)),0) -> 58 | Z7: Digital creator | AA7: Sim | AD7: Itajaí: bio, 8 post(s) marcados | AE7: Itajaí -SC (7), Itajaí (1) | AF7: 🗣️| FALA MEUX QUIRIDU. TAX TOLO ? / 🩷| MÃE DE DOIS BOCA DE SACOLA / 📍| ITAJAÍ | +70 MILHÕES DE VIEWS TÁ ? | AG7: https://instagram.com/nubiakatyoficial | AH7: Não contatada
A8: Itajaí | C8: @eogriilo | D8: Geovane José - Influencer de Itajaí | E8: Criador(a) | F8: Homem | G8: 76287 | H8: Média (30k–100k) | I8: 0.0016 | J8: =IFERROR(INDEX('Como ler'!$B$20:$B$24,MATCH(H8,'Como ler'!$A$20:$A$24,0)),"") -> 0.015 | K8: =IF(OR(I8="",J8=""),"",I8/J8) -> 0.10666667 | L8: 136 | M8: 16.4 | N8: 2219 | O8: =IF(OR(N8="",G8=0),"",N8/G8) -> 0.029087525 | P8: 0.9 | Q8: 21 | R8: 46292 | S8: =IF(R8="","",'Como ler'!$B$27-R8) -> 0 | T8: 0 | V8: Entretenimento e humor | W8: Entretenimento e humor, Negócios e empreendedorismo | X8: Alta | Y8: =ROUND(IF(K8="",0,MIN(40,40*K8/1.5))+IF(S8="",0,IF(S8<=7,20,IF(S8<=30,12,IF(S8<=90,5,0))))+IF(Q8="",0,MIN(15,Q8*5))+IF(O8="",0,MIN(15,O8*30))+IF(E8="Criador(a)",10,IF(E8="Especialista que cria conteúdo",6,4)),0) -> 49 | Z8: Digital creator | AA8: Sim | AD8: Itajaí: bio, 8 post(s) marcados | AE8: Itajaí -SC (6), São Vicente, Itajaí (2) | AF8: Fala comigo, tropa. / Empresário | Influencer | Dono de Barbearia / Proprietário da @nareguaitajai / Publicidade: @agenciachammma / Itajaí Sc | AG8: https://instagram.com/eogriilo | AH8: Não contatada
A9: Itajaí | C9: @gabryelnuness | D9: Gabryel Nunes - Influenciador de Itajaí | E9: Criador(a) | F9: Homem | G9: 69075 | H9: Média (30k–100k) | I9: 0.0037 | J9: =IFERROR(INDEX('Como ler'!$B$20:$B$24,MATCH(H9,'Como ler'!$A$20:$A$24,0)),"") -> 0.015 | K9: =IF(OR(I9="",J9=""),"",I9/J9) -> 0.24666667 | L9: 430 | M9: 51.8 | N9: 4448 | O9: =IF(OR(N9="",G9=0),"",N9/G9) -> 0.064393775 | P9: 0.83 | Q9: 77 | R9: 46291 | S9: =IF(R9="","",'Como ler'!$B$27-R9) -> 1 | T9: 0 | V9: Negócios e empreendedorismo | W9: Negócios e empreendedorismo, Entretenimento e humor | X9: Alta | Y9: =ROUND(IF(K9="",0,MIN(40,40*K9/1.5))+IF(S9="",0,IF(S9<=7,20,IF(S9<=30,12,IF(S9<=90,5,0))))+IF(Q9="",0,MIN(15,Q9*5))+IF(O9="",0,MIN(15,O9*30))+IF(E9="Criador(a)",10,IF(E9="Especialista que cria conteúdo",6,4)),0) -> 54 | Z9: Digital creator | AD9: Itajaí: 9 post(s) marcados | AE9: Itajaí (9), Estefano Jose Vanolli (1), Pizzaria Herois da Pizza (1) | AF9: 🎙️ FALA COMIGO RAPAZEADA / 🎤 Influencer • Empresário • Comunicador / 📲 Publicidades • @agenciachammma | AG9: https://instagram.com/gabryelnuness | AH9: Não contatada
A10: Itajaí | B10: Balneário Camboriú | C10: @julianadomareski | D10: Juliana Domareski | E10: Especialista que cria conteúdo | F10: Mulher | G10: 65364 | H10: Média (30k–100k) | I10: 0.0039 | J10: =IFERROR(INDEX('Como ler'!$B$20:$B$24,MATCH(H10,'Como ler'!$A$20:$A$24,0)),"") -> 0.015 | K10: =IF(OR(I10="",J10=""),"",I10/J10) -> 0.26 | L10: 339 | M10: 7.1 | N10: 5204 | O10: =IF(OR(N10="",G10=0),"",N10/G10) -> 0.079615691 | P10: 0.7 | Q10: 2.1 | R10: 46291 | S10: =IF(R10="","",'Como ler'!$B$27-R10) -> 1 | T10: 0 | V10: Viagem | W10: Viagem, Negócios e empreendedorismo, Casa e organização | X10: Alta | Y10: =ROUND(IF(K10="",0,MIN(40,40*K10/1.5))+IF(S10="",0,IF(S10<=7,20,IF(S10<=30,12,IF(S10<=90,5,0))))+IF(Q10="",0,MIN(15,Q10*5))+IF(O10="",0,MIN(15,O10*30))+IF(E10="Criador(a)",10,IF(E10="Especialista que cria conteúdo",6,4)),0) -> 46 | Z10: None | AA10: Sim | AB10: Sim | AD10: Itajaí: bio, 2 post(s) marcados; Balneário Camboriú: bio, 2 post(s) marcados | AE10: Imobiliária Terra (3), Balneário Camboriú (2), Praia Brava - Itajaí/SC (2), Copacabana, Rio de Janeiro (1) | AF10: CEO / Grupo Domma | @terra_imobiliaria / Estruturação de operações imobiliárias para quem quer multiplicar capital. / Balneário Camboriú • Praia Brava • SC | AG10: https://instagram.com/julianadomareski | AH10: Não contatada
A11: Itajaí | C11: @gabyoliveirasc | D11: Gabriela Oliveira | Casamento cristão & Vida real | E11: Especialista que cria conteúdo | F11: Mulher | G11: 52669 | H11: Média (30k–100k) | I11: 0.002 | J11: =IFERROR(INDEX('Como ler'!$B$20:$B$24,MATCH(H11,'Como ler'!$A$20:$A$24,0)),"") -> 0.015 | K11: =IF(OR(I11="",J11=""),"",I11/J11) -> 0.13333333 | L11: 92 | M11: 7.3 | N11: 1675 | O11: =IF(OR(N11="",G11=0),"",N11/G11) -> 0.031802389 | P11: 0.27 | Q11: 5 | R11: 46286 | S11: =IF(R11="","",'Como ler'!$B$27-R11) -> 6 | T11: 0 | V11: Relacionamento | W11: Relacionamento, Família e maternidade, Lifestyle, Educação e conhecimento | X11: Média | Y11: =ROUND(IF(K11="",0,MIN(40,40*K11/1.5))+IF(S11="",0,IF(S11<=7,20,IF(S11<=30,12,IF(S11<=90,5,0))))+IF(Q11="",0,MIN(15,Q11*5))+IF(O11="",0,MIN(15,O11*30))+IF(E11="Criador(a)",10,IF(E11="Especialista que cria conteúdo",6,4)),0) -> 46 | Z11: Digital creator | AD11: Itajaí: bio, 2 post(s) marcados | AE11: Itajaí -SC (2) | AF11: Psicóloga • Terapeuta de casais • Esposa / Mãe do Joaquim, à espera do Jonatas 🤰🏻 / ✝️ Fé, casamento & vida real / 📍 Itajaí/SC | AG11: https://instagram.com/gabyoliveirasc | AH11: Não contatada
A12: Itajaí | B12: Balneário Camboriú | C12: @tatypassos__ | D12: Taty Passos | Explore SC | E12: Criador(a) | F12: Mulher | G12: 48271 | H12: Média (30k–100k) | I12: 0.0009 | J12: =IFERROR(INDEX('Como ler'!$B$20:$B$24,MATCH(H12,'Como ler'!$A$20:$A$24,0)),"") -> 0.015 | K12: =IF(OR(I12="",J12=""),"",I12/J12) -> 0.06 | L12: 37 | M12: 7 | N12: 286 | O12: =IF(OR(N12="",G12=0),"",N12/G12) -> 0.0059248824 | P12: 0.56 | Q12: 0.8 | R12: 46292 | S12: =IF(R12="","",'Como ler'!$B$27-R12) -> 0 | T12: 0 | V12: Gastronomia | W12: Gastronomia, Beleza, Entretenimento e humor, Casa e organização | X12: Alta | Y12: =ROUND(IF(K12="",0,MIN(40,40*K12/1.5))+IF(S12="",0,IF(S12<=7,20,IF(S12<=30,12,IF(S12<=90,5,0))))+IF(Q12="",0,MIN(15,Q12*5))+IF(O12="",0,MIN(15,O12*30))+IF(E12="Criador(a)",10,IF(E12="Especialista que cria conteúdo",6,4)),0) -> 36 | Z12: Digital creator | AB12: Sim | AD12: Itajaí: 1 post(s) marcados; Balneário Camboriú: 1 post(s) marcados | AE12: Balneário Piçarras (2), Curitiba, Paraná (1), Balneário Piçarras - SC (1), Itajaí (1) | AF12: 🦋Os padrões de beleza que lutem para se encaixar em mim! / 🚀Foguete tem ré sim, mas não comigo / 🍽️Gastronomia & Humor / @exploresantacatarina @casadataty__ | AG12: https://instagram.com/tatypassos__ | AH12: Não contatada
A13: Itajaí | C13: @toemdrika | D13: Drika | Influenciadora em Santa Catarina | E13: Criador(a) | F13: Mulher | G13: 42854 | H13: Média (30k–100k) | I13: 0.0101 | J13: =IFERROR(INDEX('Como ler'!$B$20:$B$24,MATCH(H13,'Como ler'!$A$20:$A$24,0)),"") -> 0.015 | K13: =IF(OR(I13="",J13=""),"",I13/J13) -> 0.67333333 | L13: 769 | M13: 80.4 | N13: 3651 | O13: =IF(OR(N13="",G13=0),"",N13/G13) -> 0.085196248 | P13: 1 | Q13: 6.4 | R13: 46288 | S13: =IF(R13="","",'Como ler'!$B$27-R13) -> 4 | T13: 1 | U13: @promenacmotoshonda | V13: Fitness e wellness | W13: Fitness e wellness, Lifestyle | X13: Média | Y13: =ROUND(IF(K13="",0,MIN(40,40*K13/1.5))+IF(S13="",0,IF(S13<=7,20,IF(S13<=30,12,IF(S13<=90,5,0))))+IF(Q13="",0,MIN(15,Q13*5))+IF(O13="",0,MIN(15,O13*30))+IF(E13="Criador(a)",10,IF(E13="Especialista que cria conteúdo",6,4)),0) -> 66 | AC13: email | AD13: Itajaí: bio, 3 post(s) marcados | AE13: Itajaí (3), Piçarras (1) | AF13: 📍Baiana em Itajaí / 📧 [e-mail na bio] / 🏋🏾‍♀️Embaixadora @pratiquefitness / Quer se mudar pra SC? Eu te ajudo👇 | AG13: https://instagram.com/toemdrika | AH13: Não contatada
A14: Itajaí | B14: Itapema | C14: @mordomorodrigo_oficial | D14: Mordomo Rodrig️o | E14: Criador(a) | F14: Homem | G14: 27951 | H14: Micro (3k–30k) | I14: 0.0096 | J14: =IFERROR(INDEX('Como ler'!$B$20:$B$24,MATCH(H14,'Como ler'!$A$20:$A$24,0)),"") -> 0.025 | K14: =IF(OR(I14="",J14=""),"",I14/J14) -> 0.384 | L14: 200 | M14: 38.7 | N14: 2117 | O14: =IF(OR(N14="",G14=0),"",N14/G14) -> 0.075739687 | P14: 0.9 | Q14: 1.4 | R14: 46291 | S14: =IF(R14="","",'Como ler'!$B$27-R14) -> 1 | T14: 0 | V14: Relacionamento | W14: Relacionamento | X14: Baixa | Y14: =ROUND(IF(K14="",0,MIN(40,40*K14/1.5))+IF(S14="",0,IF(S14<=7,20,IF(S14<=30,12,IF(S14<=90,5,0))))+IF(Q14="",0,MIN(15,Q14*5))+IF(O14="",0,MIN(15,O14*30))+IF(E14="Criador(a)",10,IF(E14="Especialista que cria conteúdo",6,4)),0) -> 50 | AD14: Itajaí: bio, 1 post(s) marcados; Itapema: 2 post(s) marcados | AE14: Itapema, Santa Catarina, Brazil (2), Florianópolis, Santa Catarina, Brasil (2), Brasil Santa Catarina (1), Praia Brava - Itajaí/SC (1) | AF14: ⚫Influencer/Itajaí SC / PR 😊 / ⚫Mordomo de noivas / ⚫Mordomo das estrelas / ⚫Modelo/Ator/Bailarino / ⚫️❤️🔒🥰 | AG14: https://instagram.com/mordomorodrigo_oficial | AH14: Não contatada
A15: Itajaí | C15: @herique.finatto | D15: Herique Finato | E15: Criador(a) | F15: Homem | G15: 25575 | H15: Micro (3k–30k) | I15: 0.0076 | J15: =IFERROR(INDEX('Como ler'!$B$20:$B$24,MATCH(H15,'Como ler'!$A$20:$A$24,0)),"") -> 0.025 | K15: =IF(OR(I15="",J15=""),"",I15/J15) -> 0.304 | L15: 869 | M15: 2.4 | N15: 3882 | O15: =IF(OR(N15="",G15=0),"",N15/G15) -> 0.15178886 | P15: 0.92 | Q15: 4.8 | R15: 46292 | S15: =IF(R15="","",'Como ler'!$B$27-R15) -> 0 | T15: 0 | V15: Lifestyle | W15: Lifestyle, Fitness e wellness | X15: Média | Y15: =ROUND(IF(K15="",0,MIN(40,40*K15/1.5))+IF(S15="",0,IF(S15<=7,20,IF(S15<=30,12,IF(S15<=90,5,0))))+IF(Q15="",0,MIN(15,Q15*5))+IF(O15="",0,MIN(15,O15*30))+IF(E15="Criador(a)",10,IF(E15="Especialista que cria conteúdo",6,4)),0) -> 58 | AD15: Itajaí: 1 post(s) marcados | AE15: Praia Brava - Itajai (1) | AF15: 🔥 Criador de conteúdo / 🏋🏼 Minha rotina diária nos stories / 🌱Inspirando uma vida saudável e ativa | AG15: https://instagram.com/herique.finatto | AH15: Não contatada
A16: Itajaí | B16: Balneário Camboriú | C16: @shophome.brasil | D16: Shophome | Dicas BC, Itajaí e Região | E16: Página local / guia | F16: Página/marca | G16: 20687 | H16: Micro (3k–30k) | I16: 0.0019 | J16: =IFERROR(INDEX('Como ler'!$B$20:$B$24,MATCH(H16,'Como ler'!$A$20:$A$24,0)),"") -> 0.025 | K16: =IF(OR(I16="",J16=""),"",I16/J16) -> 0.076 | L16: 40 | M16: 7.8 | N16: 867 | O16: =IF(OR(N16="",G16=0),"",N16/G16) -> 0.041910378 | P16: 1 | Q16: 2.4 | R16: 45935 | S16: =IF(R16="","",'Como ler'!$B$27-R16) -> 357 | T16: 0 | V16: Entretenimento e humor | W16: Entretenimento e humor, Dicas locais, Lifestyle, Casa e organização | X16: Alta | Y16: =ROUND(IF(K16="",0,MIN(40,40*K16/1.5))+IF(S16="",0,IF(S16<=7,20,IF(S16<=30,12,IF(S16<=90,5,0))))+IF(Q16="",0,MIN(15,Q16*5))+IF(O16="",0,MIN(15,O16*30))+IF(E16="Criador(a)",10,IF(E16="Especialista que cria conteúdo",6,4)),0) -> 19 | Z16: None | AB16: Sim | AD16: Itajaí: bio; Balneário Camboriú: bio | AF16: 💙Dicas, dia a dia e humor / 📍 Indicações em BC, Itajaí e região / ⬇️ Entre no grupo de ofertas | AG16: https://instagram.com/shophome.brasil | AH16: Não contatada
A17: Itajaí | B17: Balneário Camboriú | C17: @isabelaonofre | D17: Isabela Onofre | E17: Criador(a) | F17: Mulher | G17: 20124 | H17: Micro (3k–30k) | I17: 0.0049 | J17: =IFERROR(INDEX('Como ler'!$B$20:$B$24,MATCH(H17,'Como ler'!$A$20:$A$24,0)),"") -> 0.025 | K17: =IF(OR(I17="",J17=""),"",I17/J17) -> 0.196 | L17: 80 | M17: 32.9 | N17: 845 | O17: =IF(OR(N17="",G17=0),"",N17/G17) -> 0.041989664 | P17: 0.89 | Q17: 5.1 | R17: 46292 | S17: =IF(R17="","",'Como ler'!$B$27-R17) -> 0 | T17: 0 | V17: Fitness e wellness | W17: Fitness e wellness, Dicas locais, Moda | X17: Média | Y17: =ROUND(IF(K17="",0,MIN(40,40*K17/1.5))+IF(S17="",0,IF(S17<=7,20,IF(S17<=30,12,IF(S17<=90,5,0))))+IF(Q17="",0,MIN(15,Q17*5))+IF(O17="",0,MIN(15,O17*30))+IF(E17="Criador(a)",10,IF(E17="Especialista que cria conteúdo",6,4)),0) -> 51 | AA17: Sim | AC17: email | AD17: Balneário Camboriú: 1 post(s) marcados; Itajaí: 3 post(s) marcados | AE17: Itajaí -SC (3), Balneário Camboriú (1), Estação Azul (1), Monthez Hotel & Eventos (1) | AF17: Dicas, treinos, looks e uns surtos de uma geminiana 30+ 💖✌🏻 / “ME DIVERTINDO NO DESCONFORTO” / 💌 Parcerias: [e-mail na bio] | AG17: https://instagram.com/isabelaonofre | AH17: Não contatada
A18: Itajaí | C18: @bevieiraa | D18: Beatriz Vieira | Maquiadora | E18: Criador(a) | F18: Mulher | G18: 17162 | H18: Micro (3k–30k) | I18: 0.0044 | J18: =IFERROR(INDEX('Como ler'!$B$20:$B$24,MATCH(H18,'Como ler'!$A$20:$A$24,0)),"") -> 0.025 | K18: =IF(OR(I18="",J18=""),"",I18/J18) -> 0.176 | L18: 102 | M18: 9.9 | N18: 581 | O18: =IF(OR(N18="",G18=0),"",N18/G18) -> 0.033853863 | P18: 0.67 | Q18: 1.8 | R18: 46291 | S18: =IF(R18="","",'Como ler'!$B$27-R18) -> 1 | T18: 0 | V18: Beleza | W18: Beleza, Viagem, Negócios e empreendedorismo, Educação e conhecimento | X18: Alta | Y18: =ROUND(IF(K18="",0,MIN(40,40*K18/1.5))+IF(S18="",0,IF(S18<=7,20,IF(S18<=30,12,IF(S18<=90,5,0))))+IF(Q18="",0,MIN(15,Q18*5))+IF(O18="",0,MIN(15,O18*30))+IF(E18="Criador(a)",10,IF(E18="Especialista que cria conteúdo",6,4)),0) -> 45 | Z18: Beauty, cosmetic & personal care | AB18: Sim | AD18: Itajaí: bio, 1 post(s) marcados | AE18: Curacao Caribe (1), Itajaí (1), Bloove • Be Vieira (1) | AF18: Beauty, viagens & vida real / Itajaí | SC / Makeup Artist há 12 anos / Fundadora da @bloovebeauty / 💌 Agendamentos • Orçamentos • Cursos • Publicidade ↓ | AG18: https://instagram.com/bevieiraa | AH18: Não contatada
A19: Itajaí | C19: @melissagmenezes | D19: Melissa Menezes | E19: Criador(a) | F19: Mulher | G19: 16490 | H19: Micro (3k–30k) | I19: 0.0101 | J19: =IFERROR(INDEX('Como ler'!$B$20:$B$24,MATCH(H19,'Como ler'!$A$20:$A$24,0)),"") -> 0.025 | K19: =IF(OR(I19="",J19=""),"",I19/J19) -> 0.404 | L19: 162 | M19: 59.8 | N19: 7430 | O19: =IF(OR(N19="",G19=0),"",N19/G19) -> 0.45057611 | P19: 0.18 | Q19: 17.5 | R19: 46292 | S19: =IF(R19="","",'Como ler'!$B$27-R19) -> 0 | T19: 0 | V19: Casa e organização | W19: Casa e organização, Família e maternidade, Educação e conhecimento, Dicas locais | X19: Alta | Y19: =ROUND(IF(K19="",0,MIN(40,40*K19/1.5))+IF(S19="",0,IF(S19<=7,20,IF(S19<=30,12,IF(S19<=90,5,0))))+IF(Q19="",0,MIN(15,Q19*5))+IF(O19="",0,MIN(15,O19*30))+IF(E19="Criador(a)",10,IF(E19="Especialista que cria conteúdo",6,4)),0) -> 69 | Z19: Digital creator | AA19: Sim | AB19: Sim | AD19: Itajaí: bio, 11 post(s) marcados | AE19: Itajaí -SC (6), Itajaí (4), Itajaí, Santa Catarina, Brasil (1) | AF19: Itajai-SC - Vegetariana 🌱 Voluntária da causa animal 🐶💖😺 Maquiadora, Profª de Inglês. Mãe de 4🐶🐶🐶🐶 Lar Temporário do Bento 🐶 | AG19: https://instagram.com/melissagmenezes | AH19: Não contatada
A20: Itajaí | C20: @divulgaitajai | D20: DIVULGA ITAJAÍ | E20: Página local / guia | F20: Página/marca | G20: 15574 | H20: Micro (3k–30k) | I20: 0.0039 | J20: =IFERROR(INDEX('Como ler'!$B$20:$B$24,MATCH(H20,'Como ler'!$A$20:$A$24,0)),"") -> 0.025 | K20: =IF(OR(I20="",J20=""),"",I20/J20) -> 0.156 | L20: 68 | M20: 7.2 | N20: 228 | O20: =IF(OR(N20="",G20=0),"",N20/G20) -> 0.014639784 | P20: 0.36 | Q20: 3.2 | R20: 46290 | S20: =IF(R20="","",'Como ler'!$B$27-R20) -> 2 | T20: 0 | V20: Dicas locais | W20: Dicas locais, Educação e conhecimento | X20: Baixa | Y20: =ROUND(IF(K20="",0,MIN(40,40*K20/1.5))+IF(S20="",0,IF(S20<=7,20,IF(S20<=30,12,IF(S20<=90,5,0))))+IF(Q20="",0,MIN(15,Q20*5))+IF(O20="",0,MIN(15,O20*30))+IF(E20="Criador(a)",10,IF(E20="Especialista que cria conteúdo",6,4)),0) -> 44 | Z20: Community | AB20: Sim | AD20: Itajaí: bio, 5 post(s) marcados | AE20: Itajaí, Santa Catarina, Brasil (2), Alfa Bile (2), Molhes da Barra Itajaí (2), Disk Água Bebí (1) | AF20: 💙 Itajaí por @alfabile / ⚓️ Paisagens | Cotidiano | Arte / ✨ O olhar mais apaixonado pela nossa cidade / 👇 Wallpapers exclusivos e Dicas no Canal | AG20: https://instagram.com/divulgaitajai | AH20: Não contatada | AI20: Curtidas ocultas: engajamento calculado só com posts visíveis ou indisponível
A21: Itajaí | B21: Balneário Camboriú | C21: @solaynesantos | D21: ꜱᴏʟ - Influencer, Social Media & Videomaker | Itajaí | E21: Criador(a) | F21: Mulher | G21: 13517 | H21: Micro (3k–30k) | I21: 0.0056 | J21: =IFERROR(INDEX('Como ler'!$B$20:$B$24,MATCH(H21,'Como ler'!$A$20:$A$24,0)),"") -> 0.025 | K21: =IF(OR(I21="",J21=""),"",I21/J21) -> 0.224 | L21: 591 | M21: 17.8 | N21: 621 | O21: =IF(OR(N21="",G21=0),"",N21/G21) -> 0.045942147 | P21: 0.67 | Q21: 4 | R21: 46290 | S21: =IF(R21="","",'Como ler'!$B$27-R21) -> 2 | T21: 0 | V21: Gastronomia | W21: Gastronomia, Social mídia e conteúdo | X21: Alta | Y21: =ROUND(IF(K21="",0,MIN(40,40*K21/1.5))+IF(S21="",0,IF(S21<=7,20,IF(S21<=30,12,IF(S21<=90,5,0))))+IF(Q21="",0,MIN(15,Q21*5))+IF(O21="",0,MIN(15,O21*30))+IF(E21="Criador(a)",10,IF(E21="Especialista que cria conteúdo",6,4)),0) -> 52 | Z21: Digital creator | AC21: email | AD21: Itajaí: bio, 4 post(s) marcados; Balneário Camboriú: 2 post(s) marcados | AE21: Itajaí, Santa Catarina, Brasil (3), Balneário Camboriú (2), New Shoes Itajaí (1), Central Pádel Br (1) | AF21: 📱Influencer, Social Media & Videomaker / ✈️ Paulista em SC |📍Itajaí SC / 💡Criando conteúdo autêntico para sua marca! / 💌 [e-mail na bio] | AG21: https://instagram.com/solaynesantos | AH21: Não contatada
A22: Itajaí | C22: @brigadeiroealecrim | D22: Brigadeiro e Alecrim ® - Balneário Camboriú | E22: Criador(a) | F22: Mulher | G22: 12449 | H22: Micro (3k–30k) | I22: 0.0036 | J22: =IFERROR(INDEX('Como ler'!$B$20:$B$24,MATCH(H22,'Como ler'!$A$20:$A$24,0)),"") -> 0.025 | K22: =IF(OR(I22="",J22=""),"",I22/J22) -> 0.144 | L22: 45 | M22: 6.3 | N22: 480 | O22: =IF(OR(N22="",G22=0),"",N22/G22) -> 0.038557314 | P22: 0.7 | Q22: 1.4 | R22: 46278 | S22: =IF(R22="","",'Como ler'!$B$27-R22) -> 14 | T22: 0 | V22: Gastronomia | W22: Gastronomia | X22: Baixa | Y22: =ROUND(IF(K22="",0,MIN(40,40*K22/1.5))+IF(S22="",0,IF(S22<=7,20,IF(S22<=30,12,IF(S22<=90,5,0))))+IF(Q22="",0,MIN(15,Q22*5))+IF(O22="",0,MIN(15,O22*30))+IF(E22="Criador(a)",10,IF(E22="Especialista que cria conteúdo",6,4)),0) -> 34 | AB22: Sim | AD22: Itajaí: 7 post(s) marcados | AE22: Itajaí (7), Fazzenda Park Resort (1) | AF22: Depois de 10 anos entre panelas e doces, / resolvi experimentar o outro lado da mesa. / Aqui tem experiências que eu realmente acho que valem a pena! | AG22: https://instagram.com/brigadeiroealecrim | AH22: Não contatada
A23: Itajaí | C23: @eubarbaraabreu | D23: Bárbara Abreu | E23: Criador(a) | F23: Mulher | G23: 12418 | H23: Micro (3k–30k) | J23: =IFERROR(INDEX('Como ler'!$B$20:$B$24,MATCH(H23,'Como ler'!$A$20:$A$24,0)),"") -> 0.025 | K23: =IF(OR(I23="",J23=""),"",I23/J23) | M23: 11 | N23: 178 | O23: =IF(OR(N23="",G23=0),"",N23/G23) -> 0.014334031 | P23: 0.2 | Q23: 0.2 | R23: 46291 | S23: =IF(R23="","",'Como ler'!$B$27-R23) -> 1 | T23: 0 | V23: Beleza | W23: Beleza, Gastronomia | X23: Média | Y23: =ROUND(IF(K23="",0,MIN(40,40*K23/1.5))+IF(S23="",0,IF(S23<=7,20,IF(S23<=30,12,IF(S23<=90,5,0))))+IF(Q23="",0,MIN(15,Q23*5))+IF(O23="",0,MIN(15,O23*30))+IF(E23="Criador(a)",10,IF(E23="Especialista que cria conteúdo",6,4)),0) -> 31 | Z23: Digital creator | AC23: email | AD23: Itajaí: bio, 7 post(s) marcados | AE23: Itajaí (2), Itajaí -SC (2), Laviér Store Itajaí (1), Mercure Itajai Navegantes (1) | AF23: Bem-vinda(o)! / 👑 Miss Supranational Itajaí 2025 / 💌 [e-mail na bio] | AG23: https://instagram.com/eubarbaraabreu | AH23: Não contatada | AI23: Curtidas ocultas: engajamento calculado só com posts visíveis ou indisponível
A24: Itajaí | C24: @omelhordeitajai | E24: Página local / guia | F24: Página/marca | G24: 12104 | H24: Micro (3k–30k) | I24: 0.0051 | J24: =IFERROR(INDEX('Como ler'!$B$20:$B$24,MATCH(H24,'Como ler'!$A$20:$A$24,0)),"") -> 0.025 | K24: =IF(OR(I24="",J24=""),"",I24/J24) -> 0.204 | L24: 94 | M24: 1.8 | N24: 882 | O24: =IF(OR(N24="",G24=0),"",N24/G24) -> 0.072868473 | P24: 0.67 | Q24: 7.7 | R24: 46289 | S24: =IF(R24="","",'Como ler'!$B$27-R24) -> 3 | T24: 0 | V24: Viagem | W24: Viagem | X24: Baixa | Y24: =ROUND(IF(K24="",0,MIN(40,40*K24/1.5))+IF(S24="",0,IF(S24<=7,20,IF(S24<=30,12,IF(S24<=90,5,0))))+IF(Q24="",0,MIN(15,Q24*5))+IF(O24="",0,MIN(15,O24*30))+IF(E24="Criador(a)",10,IF(E24="Especialista que cria conteúdo",6,4)),0) -> 47 | AB24: Sim | AD24: Itajaí: bio | AF24: O destino começa aqui. / Belezas, sabores e experiências de Itajaí. / 🌊 Explore o melhor da cidade / Por: @itajaiconvention | AG24: https://instagram.com/omelhordeitajai | AH24: Não contatada
A25: Itajaí | C25: @lu.monaly | D25: Luciana Monaly | E25: Criador(a) | F25: Mulher | G25: 11743 | H25: Micro (3k–30k) | I25: 0.0063 | J25: =IFERROR(INDEX('Como ler'!$B$20:$B$24,MATCH(H25,'Como ler'!$A$20:$A$24,0)),"") -> 0.025 | K25: =IF(OR(I25="",J25=""),"",I25/J25) -> 0.252 | L25: 143 | M25: 4.8 | N25: 1539 | O25: =IF(OR(N25="",G25=0),"",N25/G25) -> 0.1310568 | P25: 0.91 | Q25: 0.9 | R25: 46291 | S25: =IF(R25="","",'Como ler'!$B$27-R25) -> 1 | T25: 0 | X25: Baixa | Y25: =ROUND(IF(K25="",0,MIN(40,40*K25/1.5))+IF(S25="",0,IF(S25<=7,20,IF(S25<=30,12,IF(S25<=90,5,0))))+IF(Q25="",0,MIN(15,Q25*5))+IF(O25="",0,MIN(15,O25*30))+IF(E25="Criador(a)",10,IF(E25="Especialista que cria conteúdo",6,4)),0) -> 45 | AD25: Itajaí: bio, 10 post(s) marcados | AE25: Itajaí -SC (6), Santa Catarina Itajai (4) | AF25: Itajaí SC / Modelo / Maquiadora- @monaly.makeup / Publicidade e Propaganda, Atriz por: @escolawolfmaya🎬 | AG25: https://instagram.com/lu.monaly | AH25: Não contatada
A26: Itajaí | C26: @cademinhascoisas | D26: Cadê Minhas Coisas? • Soluções em Organização | E26: Especialista que cria conteúdo | F26: Página/marca | G26: 10806 | H26: Micro (3k–30k) | I26: 0.0038 | J26: =IFERROR(INDEX('Como ler'!$B$20:$B$24,MATCH(H26,'Como ler'!$A$20:$A$24,0)),"") -> 0.025 | K26: =IF(OR(I26="",J26=""),"",I26/J26) -> 0.152 | L26: 50 | M26: 4.8 | N26: 376 | O26: =IF(OR(N26="",G26=0),"",N26/G26) -> 0.034795484 | P26: 0.78 | Q26: 2.7 | R26: 46245 | S26: =IF(R26="","",'Como ler'!$B$27-R26) -> 47 | T26: 0 | V26: Casa e organização | W26: Casa e organização, Família e maternidade | X26: Alta | Y26: =ROUND(IF(K26="",0,MIN(40,40*K26/1.5))+IF(S26="",0,IF(S26<=7,20,IF(S26<=30,12,IF(S26<=90,5,0))))+IF(Q26="",0,MIN(15,Q26*5))+IF(O26="",0,MIN(15,O26*30))+IF(E26="Criador(a)",10,IF(E26="Especialista que cria conteúdo",6,4)),0) -> 30 | AA26: Sim | AB26: Sim | AD26: Itajaí: bio | AF26: Desde 2013 transformando lares (e vidas!) 💖 / 📍 Curitiba | Itajaí | BC / Para orçamentos, clique no link abaixo 👇🏼 | AG26: https://instagram.com/cademinhascoisas | AH26: Não contatada
A27: Itajaí | C27: @bruna_alika | D27: Bruna Alika | E27: Criador(a) | F27: Mulher | G27: 10620 | H27: Micro (3k–30k) | I27: 0.0017 | J27: =IFERROR(INDEX('Como ler'!$B$20:$B$24,MATCH(H27,'Como ler'!$A$20:$A$24,0)),"") -> 0.025 | K27: =IF(OR(I27="",J27=""),"",I27/J27) -> 0.068 | L27: 23 | M27: 2.5 | N27: 414 | O27: =IF(OR(N27="",G27=0),"",N27/G27) -> 0.038983051 | P27: 1 | Q27: 3.5 | R27: 46292 | S27: =IF(R27="","",'Como ler'!$B$27-R27) -> 0 | T27: 0 | V27: Negócios e empreendedorismo | W27: Negócios e empreendedorismo, Família e maternidade, Gastronomia | X27: Alta | Y27: =ROUND(IF(K27="",0,MIN(40,40*K27/1.5))+IF(S27="",0,IF(S27<=7,20,IF(S27<=30,12,IF(S27<=90,5,0))))+IF(Q27="",0,MIN(15,Q27*5))+IF(O27="",0,MIN(15,O27*30))+IF(E27="Criador(a)",10,IF(E27="Especialista que cria conteúdo",6,4)),0) -> 48 | Z27: Digital creator | AB27: Sim | AD27: Itajaí: bio, 6 post(s) marcados | AE27: Itajaí (6), Arena Bombinhas (2) | AF27: Mulher Multifunções ligada no 220🤣 / + 15mil já dançaram comigo / 💻CEO @tourpexero / 💃@grupofloreser_ / ✨Dança @prefeituradeitajai / 🙏Mãe de 3 / Parceria | AG27: https://instagram.com/bruna_alika | AH27: Não contatada
A28: Itajaí | C28: @millycristt | D28: Emilly Cristine | StoryMaker e VideoMaker | E28: Especialista que cria conteúdo | F28: Mulher | G28: 10401 | H28: Micro (3k–30k) | I28: 0.0358 | J28: =IFERROR(INDEX('Como ler'!$B$20:$B$24,MATCH(H28,'Como ler'!$A$20:$A$24,0)),"") -> 0.025 | K28: =IF(OR(I28="",J28=""),"",I28/J28) -> 1.432 | L28: 994 | M28: 47.2 | N28: 4044 | O28: =IF(OR(N28="",G28=0),"",N28/G28) -> 0.38880877 | P28: 0.64 | Q28: 1.3 | R28: 46289 | S28: =IF(R28="","",'Como ler'!$B$27-R28) -> 3 | T28: 0 | V28: Social mídia e conteúdo | W28: Social mídia e conteúdo | X28: Alta | Y28: =ROUND(IF(K28="",0,MIN(40,40*K28/1.5))+IF(S28="",0,IF(S28<=7,20,IF(S28<=30,12,IF(S28<=90,5,0))))+IF(Q28="",0,MIN(15,Q28*5))+IF(O28="",0,MIN(15,O28*30))+IF(E28="Criador(a)",10,IF(E28="Especialista que cria conteúdo",6,4)),0) -> 82 | AB28: Sim | AD28: Itajaí: bio | AE28: Santa Catarina (1) | AF28: 🚀 | Transformo a sua ideia em um conteúdo impactante / 🤳🏼 | Fotografia • Vídeo • Real Time / 📍 | Itajaí e região / Eternize seu momento ⬇️ | AG28: https://instagram.com/millycristt | AH28: Não contatada
A29: Itajaí | C29: @thais_araujo.7 | D29: Thais | E29: Criador(a) | F29: Mulher | G29: 10330 | H29: Micro (3k–30k) | I29: 0.0251 | J29: =IFERROR(INDEX('Como ler'!$B$20:$B$24,MATCH(H29,'Como ler'!$A$20:$A$24,0)),"") -> 0.025 | K29: =IF(OR(I29="",J29=""),"",I29/J29) -> 1.004 | L29: 301 | M29: 9.9 | N29: 2782 | O29: =IF(OR(N29="",G29=0),"",N29/G29) -> 0.26931268 | P29: 0.43 | Q29: 0 | R29: 46267 | S29: =IF(R29="","",'Como ler'!$B$27-R29) -> 25 | T29: 0 | V29: UGC | W29: UGC, Dicas locais | X29: Alta | Y29: =ROUND(IF(K29="",0,MIN(40,40*K29/1.5))+IF(S29="",0,IF(S29<=7,20,IF(S29<=30,12,IF(S29<=90,5,0))))+IF(Q29="",0,MIN(15,Q29*5))+IF(O29="",0,MIN(15,O29*30))+IF(E29="Criador(a)",10,IF(E29="Especialista que cria conteúdo",6,4)),0) -> 57 | Z29: Digital creator | AB29: Sim | AD29: Itajaí: bio | AE29: Speedway Music Park (1), Chile (1), Lagoa Misteriosa (1) | AF29: 🌎 Lugares, sabores & aventuras / ✨ Transformando experiências em histórias / 📍 Itajaí • SC | UGC Creator / Bora viver essa experiência comigo? | AG29: https://instagram.com/thais_araujo.7 | AH29: Não contatada
A30: Itajaí | C30: @gabxmelo | D30: Gabi Melo 🌻 | E30: Criador(a) | F30: Mulher | G30: 9953 | H30: Micro (3k–30k) | I30: 0.0202 | J30: =IFERROR(INDEX('Como ler'!$B$20:$B$24,MATCH(H30,'Como ler'!$A$20:$A$24,0)),"") -> 0.025 | K30: =IF(OR(I30="",J30=""),"",I30/J30) -> 0.808 | L30: 255 | M30: 16.5 | O30: =IF(OR(N30="",G30=0),"",N30/G30) | P30: 0 | Q30: 0.3 | R30: 46258 | S30: =IF(R30="","",'Como ler'!$B$27-R30) -> 34 | T30: 0 | V30: Moda | W30: Moda | X30: Média | Y30: =ROUND(IF(K30="",0,MIN(40,40*K30/1.5))+IF(S30="",0,IF(S30<=7,20,IF(S30<=30,12,IF(S30<=90,5,0))))+IF(Q30="",0,MIN(15,Q30*5))+IF(O30="",0,MIN(15,O30*30))+IF(E30="Criador(a)",10,IF(E30="Especialista que cria conteúdo",6,4)),0) -> 38 | Z30: Personal blog | AD30: Itajaí: 3 post(s) marcados | AE30: Itajaí -SC (1), Praia Brava - Itajaí/SC (1), Santa Catarina Itajai (1) | AF30: SC 📍 / Comércio exterior 🛳️ / 🏳️‍🌈 | AG30: https://instagram.com/gabxmelo | AH30: Não contatada
A31: Itajaí | C31: @joanakathelen | D31: Joana Kathelen | E31: Criador(a) | F31: Mulher | G31: 9612 | H31: Micro (3k–30k) | I31: 0.0031 | J31: =IFERROR(INDEX('Como ler'!$B$20:$B$24,MATCH(H31,'Como ler'!$A$20:$A$24,0)),"") -> 0.025 | K31: =IF(OR(I31="",J31=""),"",I31/J31) -> 0.124 | L31: 28 | M31: 3.7 | N31: 336 | O31: =IF(OR(N31="",G31=0),"",N31/G31) -> 0.034956305 | P31: 0.5 | Q31: 0.2 | R31: 46263 | S31: =IF(R31="","",'Como ler'!$B$27-R31) -> 29 | T31: 0 | V31: Família e maternidade | W31: Família e maternidade | X31: Média | Y31: =ROUND(IF(K31="",0,MIN(40,40*K31/1.5))+IF(S31="",0,IF(S31<=7,20,IF(S31<=30,12,IF(S31<=90,5,0))))+IF(Q31="",0,MIN(15,Q31*5))+IF(O31="",0,MIN(15,O31*30))+IF(E31="Criador(a)",10,IF(E31="Especialista que cria conteúdo",6,4)),0) -> 27 | AD31: Itajaí: 11 post(s) marcados | AE31: Itajaí (8), Centro De Itajai Santa Catarina. (3) | AF31: 🌸 Mãe de dois príncipes / 💙@heitorbitencourt1 / 💚@henriquebitencourt2 / 💼 @serpa.log | AG31: https://instagram.com/joanakathelen | AH31: Não contatada
A32: Itajaí | C32: @n1kx_x | D32: Nicolly Machado - UGC Creator | E32: Criador(a) | F32: Mulher | G32: 9577 | H32: Micro (3k–30k) | I32: 0.0242 | J32: =IFERROR(INDEX('Como ler'!$B$20:$B$24,MATCH(H32,'Como ler'!$A$20:$A$24,0)),"") -> 0.025 | K32: =IF(OR(I32="",J32=""),"",I32/J32) -> 0.968 | L32: 258 | M32: 14.4 | O32: =IF(OR(N32="",G32=0),"",N32/G32) | P32: 0 | Q32: 0.1 | R32: 46253 | S32: =IF(R32="","",'Como ler'!$B$27-R32) -> 39 | T32: 0 | V32: UGC | W32: UGC, Casa e organização | X32: Alta | Y32: =ROUND(IF(K32="",0,MIN(40,40*K32/1.5))+IF(S32="",0,IF(S32<=7,20,IF(S32<=30,12,IF(S32<=90,5,0))))+IF(Q32="",0,MIN(15,Q32*5))+IF(O32="",0,MIN(15,O32*30))+IF(E32="Criador(a)",10,IF(E32="Especialista que cria conteúdo",6,4)),0) -> 41 | Z32: Public figure | AD32: Itajaí: 1 post(s) marcados | AE32: Goiânia, Brazil (1), Piscina Natural da Barra da Lagoa (1), Ilha da Magia - Floripa (1), Trancoso, Bahia, Brazil (1) | AF32: Design de interiores / 💼@campeche.joias | AG32: https://instagram.com/n1kx_x | AH32: Não contatada
A33: Itajaí | B33: Balneário Camboriú | C33: @itajaimilgr4u | D33: Itajai Mil Grau | E33: Página local / guia | F33: Página/marca | G33: 7887 | H33: Micro (3k–30k) | I33: 0.0075 | J33: =IFERROR(INDEX('Como ler'!$B$20:$B$24,MATCH(H33,'Como ler'!$A$20:$A$24,0)),"") -> 0.025 | K33: =IF(OR(I33="",J33=""),"",I33/J33) -> 0.3 | L33: 70 | M33: 5.8 | N33: 102 | O33: =IF(OR(N33="",G33=0),"",N33/G33) -> 0.012932674 | P33: 0.58 | Q33: 1.1 | R33: 46235 | S33: =IF(R33="","",'Como ler'!$B$27-R33) -> 57 | T33: 0 | V33: Moda | W33: Moda, Entretenimento e humor | X33: Baixa | Y33: =ROUND(IF(K33="",0,MIN(40,40*K33/1.5))+IF(S33="",0,IF(S33<=7,20,IF(S33<=30,12,IF(S33<=90,5,0))))+IF(Q33="",0,MIN(15,Q33*5))+IF(O33="",0,MIN(15,O33*30))+IF(E33="Criador(a)",10,IF(E33="Especialista que cria conteúdo",6,4)),0) -> 23 | Z33: Digital creator | AD33: Itajaí: bio, 6 post(s) marcados; Balneário Camboriú: 1 post(s) marcados | AE33: Itajaí -SC (4), Itajaí (1), Praia Do Atalaia - Itajaí (1), Balneário Camboriú - Praia (1) | AF33: Entretenimento, humor e curiosidades de Itajaí e Região / 🎯Conectando moradores,turistas e marcas locais / 💌Anuncie sua empresa com estilo e alcance real⚓ | AG33: https://instagram.com/itajaimilgr4u | AH33: Não contatada
A34: Itajaí | C34: @danielipickering | D34: Dani Pickering | E34: Criador(a) | F34: Mulher | G34: 7430 | H34: Micro (3k–30k) | I34: 0.0106 | J34: =IFERROR(INDEX('Como ler'!$B$20:$B$24,MATCH(H34,'Como ler'!$A$20:$A$24,0)),"") -> 0.025 | K34: =IF(OR(I34="",J34=""),"",I34/J34) -> 0.424 | L34: 82 | M34: 13.2 | N34: 653 | O34: =IF(OR(N34="",G34=0),"",N34/G34) -> 0.087886945 | P34: 0.75 | Q34: 0.3 | R34: 46292 | S34: =IF(R34="","",'Como ler'!$B$27-R34) -> 0 | T34: 0 | V34: Família e maternidade | W34: Família e maternidade, Fitness e wellness, Lifestyle, Negócios e empreendedorismo | X34: Alta | Y34: =ROUND(IF(K34="",0,MIN(40,40*K34/1.5))+IF(S34="",0,IF(S34<=7,20,IF(S34<=30,12,IF(S34<=90,5,0))))+IF(Q34="",0,MIN(15,Q34*5))+IF(O34="",0,MIN(15,O34*30))+IF(E34="Criador(a)",10,IF(E34="Especialista que cria conteúdo",6,4)),0) -> 45 | AD34: Itajaí: 4 post(s) marcados | AE34: Itajaí (3), Itajaí -SC (1), Greenvalley (1) | AF34: Mãe da Kali 💓 / Movimento, trabalho e vida real ✨ / Marketing do Grupo Health Brasil / @healthycann @healthimporter / @healthimporter @nexpurepharma | AG34: https://instagram.com/danielipickering | AH34: Não contatada
A35: Itajaí | C35: @ana_paula_videomaker | D35: VIDEOMAKER MOBILE | ITAJAÍ | E35: Especialista que cria conteúdo | F35: Mulher | G35: 7365 | H35: Micro (3k–30k) | I35: 0.0036 | J35: =IFERROR(INDEX('Como ler'!$B$20:$B$24,MATCH(H35,'Como ler'!$A$20:$A$24,0)),"") -> 0.025 | K35: =IF(OR(I35="",J35=""),"",I35/J35) -> 0.144 | L35: 41 | M35: 4.9 | N35: 228 | O35: =IF(OR(N35="",G35=0),"",N35/G35) -> 0.03095723 | P35: 1 | Q35: 0.4 | R35: 46099 | S35: =IF(R35="","",'Como ler'!$B$27-R35) -> 193 | T35: 5 | U35: @ericaalme_, @lucasfelipexavier, @mariana_talamini, @esquina_doacairs | V35: Social mídia e conteúdo | W35: Social mídia e conteúdo, Relacionamento | X35: Alta | Y35: =ROUND(IF(K35="",0,MIN(40,40*K35/1.5))+IF(S35="",0,IF(S35<=7,20,IF(S35<=30,12,IF(S35<=90,5,0))))+IF(Q35="",0,MIN(15,Q35*5))+IF(O35="",0,MIN(15,O35*30))+IF(E35="Criador(a)",10,IF(E35="Especialista que cria conteúdo",6,4)),0) -> 13 | Z35: Reel creator | AD35: Itajaí: bio | AE35: Itaipava Club Residence (1) | AF35: 🎥 Videomaker Mobile | Itajaí-SC / 🎬 Transformo momentos em memória pelo celular 📲 ✨ Capto emoções reais em vídeo / 📱 Acesse o link e veja meu portfólio ⬇️ | AG35: https://instagram.com/ana_paula_videomaker | AH35: Não contatada
A36: Itajaí | C36: @marcelabontorin | D36: Marcela Bontorin | Estrategista de Imagem e Mentora | E36: Especialista que cria conteúdo | F36: Mulher | G36: 6620 | H36: Micro (3k–30k) | I36: 0.0115 | J36: =IFERROR(INDEX('Como ler'!$B$20:$B$24,MATCH(H36,'Como ler'!$A$20:$A$24,0)),"") -> 0.025 | K36: =IF(OR(I36="",J36=""),"",I36/J36) -> 0.46 | L36: 61 | M36: 18.5 | N36: 961 | O36: =IF(OR(N36="",G36=0),"",N36/G36) -> 0.14516616 | P36: 0.27 | Q36: 0.1 | R36: 46289 | S36: =IF(R36="","",'Como ler'!$B$27-R36) -> 3 | T36: 0 | V36: Negócios e empreendedorismo | W36: Negócios e empreendedorismo, Social mídia e conteúdo, Moda | X36: Alta | Y36: =ROUND(IF(K36="",0,MIN(40,40*K36/1.5))+IF(S36="",0,IF(S36<=7,20,IF(S36<=30,12,IF(S36<=90,5,0))))+IF(Q36="",0,MIN(15,Q36*5))+IF(O36="",0,MIN(15,O36*30))+IF(E36="Criador(a)",10,IF(E36="Especialista que cria conteúdo",6,4)),0) -> 43 | Z36: None | AA36: Sim | AB36: Sim | AD36: Itajaí: 2 post(s) marcados | AE36: Estaleiro Guest House (1), Luvcoffee (1), Itajaí -SC (1), Santa Catarina Itajai (1) | AF36: “Autoridade não se veste, se constrói” / Empreendedora | Mentora | Palestrante / @ecossdosucesso @arlinkinternet @moda_circula_ @literariasdovale | AG36: https://instagram.com/marcelabontorin | AH36: Não contatada
A37: Itajaí | C37: @tonsdeana | D37: Ana Antonelo | Comunicadora de Moda | E37: Criador(a) | F37: Mulher | G37: 6134 | H37: Micro (3k–30k) | J37: =IFERROR(INDEX('Como ler'!$B$20:$B$24,MATCH(H37,'Como ler'!$A$20:$A$24,0)),"") -> 0.025 | K37: =IF(OR(I37="",J37=""),"",I37/J37) | M37: 19 | N37: 388 | O37: =IF(OR(N37="",G37=0),"",N37/G37) -> 0.063253994 | P37: 0.7 | Q37: 10.5 | R37: 46292 | S37: =IF(R37="","",'Como ler'!$B$27-R37) -> 0 | T37: 0 | V37: Moda | W37: Moda | X37: Média | Y37: =ROUND(IF(K37="",0,MIN(40,40*K37/1.5))+IF(S37="",0,IF(S37<=7,20,IF(S37<=30,12,IF(S37<=90,5,0))))+IF(Q37="",0,MIN(15,Q37*5))+IF(O37="",0,MIN(15,O37*30))+IF(E37="Criador(a)",10,IF(E37="Especialista que cria conteúdo",6,4)),0) -> 47 | Z37: None | AB37: Sim | AD37: Itajaí: 9 post(s) marcados | AE37: Itajaí, Santa Catarina, Brasil (8), Joinville Santa Catarina (1), Mercado Velho Itajaí (1) | AF37: Hoje eu acordei querendo te irritar, / será que eu consigo? 👀 / Aqui tem moda com borogodó & muito brechó! ✨ / Crio conteúdos autênticos para sua marca 🫵🏻 | AG37: https://instagram.com/tonsdeana | AH37: Não contatada | AI37: Curtidas ocultas: engajamento calculado só com posts visíveis ou indisponível
A38: Itajaí | C38: @brunasamanthas | D38: Bruna Samantha | Corretora de Imóveis | E38: Especialista que cria conteúdo | F38: Mulher | G38: 5771 | H38: Micro (3k–30k) | I38: 0.0113 | J38: =IFERROR(INDEX('Como ler'!$B$20:$B$24,MATCH(H38,'Como ler'!$A$20:$A$24,0)),"") -> 0.025 | K38: =IF(OR(I38="",J38=""),"",I38/J38) -> 0.452 | L38: 58 | M38: 7.3 | N38: 392 | O38: =IF(OR(N38="",G38=0),"",N38/G38) -> 0.067925836 | P38: 0.83 | Q38: 0.4 | R38: 46265 | S38: =IF(R38="","",'Como ler'!$B$27-R38) -> 27 | T38: 0 | V38: Finanças | W38: Finanças, Viagem, Negócios e empreendedorismo, Família e maternidade | X38: Alta | Y38: =ROUND(IF(K38="",0,MIN(40,40*K38/1.5))+IF(S38="",0,IF(S38<=7,20,IF(S38<=30,12,IF(S38<=90,5,0))))+IF(Q38="",0,MIN(15,Q38*5))+IF(O38="",0,MIN(15,O38*30))+IF(E38="Criador(a)",10,IF(E38="Especialista que cria conteúdo",6,4)),0) -> 34 | Z38: Digital creator | AB38: Sim | AD38: Itajaí: bio, 6 post(s) marcados | AE38: Praia Brava - Itajaí/SC (6) | AF38: Imóveis únicos, localizações desejadas. / Investimentos inteligentes. / Corretora Associada @jeancarloexclusive / 📍Itajaí | Praia Brava | BC / CRECI SC 68926F | AG38: https://instagram.com/brunasamanthas | AH38: Não contatada
A39: Itajaí | B39: Itapema | C39: @andreza.marinho_22 | D39: Andreza Marinho | Atleta | E39: Criador(a) | F39: Mulher | G39: 5648 | H39: Micro (3k–30k) | I39: 0.0282 | J39: =IFERROR(INDEX('Como ler'!$B$20:$B$24,MATCH(H39,'Como ler'!$A$20:$A$24,0)),"") -> 0.025 | K39: =IF(OR(I39="",J39=""),"",I39/J39) -> 1.128 | L39: 148 | M39: 6.8 | N39: 1382 | O39: =IF(OR(N39="",G39=0),"",N39/G39) -> 0.24468839 | P39: 0.5 | Q39: 0.6 | R39: 46290 | S39: =IF(R39="","",'Como ler'!$B$27-R39) -> 2 | T39: 0 | V39: Fitness e wellness | W39: Fitness e wellness | X39: Baixa | Y39: =ROUND(IF(K39="",0,MIN(40,40*K39/1.5))+IF(S39="",0,IF(S39<=7,20,IF(S39<=30,12,IF(S39<=90,5,0))))+IF(Q39="",0,MIN(15,Q39*5))+IF(O39="",0,MIN(15,O39*30))+IF(E39="Criador(a)",10,IF(E39="Especialista que cria conteúdo",6,4)),0) -> 70 | Z39: Personal blog | AD39: Itajaí: bio; Itapema: 1 post(s) marcados | AE39: Hard Rock Cafe Itapema (1) | AF39: 🏃🏻‍♀️ Corredora | Itajaí-SC / 🏅 9 pódios em 1 ano / 📈 Evolução, disciplina & constância / 🧸 Respeita o pace fofo / 🤝 Parcerias & patrocínios | AG39: https://instagram.com/andreza.marinho_22 | AH39: Não contatada
A40: Itajaí | B40: Itapema | C40: @brunoleon.blm | D40: Bruno Leon | Corrida e Vida Real | E40: Criador(a) | F40: Homem | G40: 4593 | H40: Micro (3k–30k) | I40: 0.047 | J40: =IFERROR(INDEX('Como ler'!$B$20:$B$24,MATCH(H40,'Como ler'!$A$20:$A$24,0)),"") -> 0.025 | K40: =IF(OR(I40="",J40=""),"",I40/J40) -> 1.88 | L40: 285 | M40: 40.6 | N40: 2529 | O40: =IF(OR(N40="",G40=0),"",N40/G40) -> 0.55062051 | P40: 0.67 | Q40: 2.3 | R40: 46291 | S40: =IF(R40="","",'Como ler'!$B$27-R40) -> 1 | T40: 0 | V40: Fitness e wellness | W40: Fitness e wellness, Lifestyle, Negócios e empreendedorismo, Família e maternidade | X40: Alta | Y40: =ROUND(IF(K40="",0,MIN(40,40*K40/1.5))+IF(S40="",0,IF(S40<=7,20,IF(S40<=30,12,IF(S40<=90,5,0))))+IF(Q40="",0,MIN(15,Q40*5))+IF(O40="",0,MIN(15,O40*30))+IF(E40="Criador(a)",10,IF(E40="Especialista que cria conteúdo",6,4)),0) -> 97 | Z40: Athlete | AB40: Sim | AD40: Itajaí: 2 post(s) marcados; Itapema: 1 post(s) marcados | AE40: Pista De Atletismo De Itajai (2), Itapema, Brazil (1), Beira Mar.. Floripa.. (1), Maratona Internacional de Floripa (1) | AF40: ✞ JESUS ✞ / 👶🏻 Pai da Milena - 610g 🎀 / 🏅MARATONISTA - 02:49:28 / CEO 🏃🏻 @assessoria.leon / 💍 @luujohann / 💼 @donaruiva.pijamas / Faça parte da ASSESSORIA ⬇️ | AG40: https://instagram.com/brunoleon.blm | AH40: Não contatada
A41: Itajaí | C41: @karinawbauer | D41: Karina Bauer | Real Estate | E41: Especialista que cria conteúdo | F41: Mulher | G41: 4422 | H41: Micro (3k–30k) | I41: 0.0096 | J41: =IFERROR(INDEX('Como ler'!$B$20:$B$24,MATCH(H41,'Como ler'!$A$20:$A$24,0)),"") -> 0.025 | K41: =IF(OR(I41="",J41=""),"",I41/J41) -> 0.384 | L41: 53 | M41: 12.4 | N41: 638 | O41: =IF(OR(N41="",G41=0),"",N41/G41) -> 0.14427861 | P41: 0.5 | Q41: 3.2 | R41: 46286 | S41: =IF(R41="","",'Como ler'!$B$27-R41) -> 6 | T41: 0 | V41: Viagem | W41: Viagem, Finanças, Casa e organização, Educação e conhecimento | X41: Alta | Y41: =ROUND(IF(K41="",0,MIN(40,40*K41/1.5))+IF(S41="",0,IF(S41<=7,20,IF(S41<=30,12,IF(S41<=90,5,0))))+IF(Q41="",0,MIN(15,Q41*5))+IF(O41="",0,MIN(15,O41*30))+IF(E41="Criador(a)",10,IF(E41="Especialista que cria conteúdo",6,4)),0) -> 56 | Z41: Digital creator | AB41: Sim | AD41: Itajaí: bio | AF41: Curadoria de imóveis & oportunidades / Patrimônio • Investimento / 📍 Praia Brava, Itajaí • Florianópolis | SC / ↓ Atendimento exclusivo | AG41: https://instagram.com/karinawbauer | AH41: Não contatada
A42: Itajaí | B42: Balneário Camboriú | C42: @rurikdrone | D42: Rurik | Filmmaker | E42: Especialista que cria conteúdo | F42: Homem | G42: 4378 | H42: Micro (3k–30k) | I42: 0.0046 | J42: =IFERROR(INDEX('Como ler'!$B$20:$B$24,MATCH(H42,'Como ler'!$A$20:$A$24,0)),"") -> 0.025 | K42: =IF(OR(I42="",J42=""),"",I42/J42) -> 0.184 | L42: 51 | M42: 0.3 | N42: 318 | O42: =IF(OR(N42="",G42=0),"",N42/G42) -> 0.072635907 | P42: 0.33 | Q42: 2.3 | R42: 46239 | S42: =IF(R42="","",'Como ler'!$B$27-R42) -> 53 | T42: 0 | V42: Viagem | W42: Viagem, Dicas locais | X42: Baixa | Y42: =ROUND(IF(K42="",0,MIN(40,40*K42/1.5))+IF(S42="",0,IF(S42<=7,20,IF(S42<=30,12,IF(S42<=90,5,0))))+IF(Q42="",0,MIN(15,Q42*5))+IF(O42="",0,MIN(15,O42*30))+IF(E42="Criador(a)",10,IF(E42="Especialista que cria conteúdo",6,4)),0) -> 30 | Z42: Digital creator | AB42: Sim | AD42: Itajaí: bio, 10 post(s) marcados; Balneário Camboriú: 2 post(s) marcados | AE42: Itajaí (5), Praia Brava - Itajaí/SC (4), Balneário Camboriú (2), Praia Brava - Itajaí SC (1) | AF42: 📍 Itajaí & Litoral SC / 🎥 Fotografia aérea | Imóveis | Tours 360 / 🏙️ Descobrindo lugares incríveis. / 🔗 Projetos e parcerias 👇 | AG42: https://instagram.com/rurikdrone | AH42: Não contatada
A43: Itajaí | C43: @annacarolgarimpo | D43: Anna Carol | Influenciadora e UGC Creator- Itajaí | E43: Criador(a) | F43: Mulher | G43: 3941 | H43: Micro (3k–30k) | I43: 0.0192 | J43: =IFERROR(INDEX('Como ler'!$B$20:$B$24,MATCH(H43,'Como ler'!$A$20:$A$24,0)),"") -> 0.025 | K43: =IF(OR(I43="",J43=""),"",I43/J43) -> 0.768 | L43: 209 | M43: 12.9 | N43: 1163 | O43: =IF(OR(N43="",G43=0),"",N43/G43) -> 0.29510277 | P43: 0.7 | Q43: 3.5 | R43: 46289 | S43: =IF(R43="","",'Como ler'!$B$27-R43) -> 3 | T43: 0 | V43: Beleza | W43: Beleza, UGC, Lifestyle, Dicas locais | X43: Alta | Y43: =ROUND(IF(K43="",0,MIN(40,40*K43/1.5))+IF(S43="",0,IF(S43<=7,20,IF(S43<=30,12,IF(S43<=90,5,0))))+IF(Q43="",0,MIN(15,Q43*5))+IF(O43="",0,MIN(15,O43*30))+IF(E43="Criador(a)",10,IF(E43="Especialista que cria conteúdo",6,4)),0) -> 74 | Z43: Digital creator | AB43: Sim | AD43: Itajaí: 6 post(s) marcados | AE43: Itajaí (6), Espinheiros, Santa Catarina (1), Conforto visual (1), Canela - Serra Gaúcha/rs (1) | AF43: Oi amigas, / Dicas | Beleza | Lifestyle / & um pouquinho de tudo que me faz ser eu / ✨🧚‍♀️🌞🧜🏼‍♀️🔮 | AG43: https://instagram.com/annacarolgarimpo | AH43: Não contatada
A44: Itajaí | C44: @enfbapereira | D44: Bárbara Pereira | E44: Criador(a) | F44: Mulher | G44: 3759 | H44: Micro (3k–30k) | I44: 0.0067 | J44: =IFERROR(INDEX('Como ler'!$B$20:$B$24,MATCH(H44,'Como ler'!$A$20:$A$24,0)),"") -> 0.025 | K44: =IF(OR(I44="",J44=""),"",I44/J44) -> 0.268 | L44: 45 | M44: 2.7 | N44: 202 | O44: =IF(OR(N44="",G44=0),"",N44/G44) -> 0.053737696 | P44: 0.58 | Q44: 1.6 | R44: 46291 | S44: =IF(R44="","",'Como ler'!$B$27-R44) -> 1 | T44: 0 | V44: Lifestyle | W44: Lifestyle, Dicas locais | X44: Média | Y44: =ROUND(IF(K44="",0,MIN(40,40*K44/1.5))+IF(S44="",0,IF(S44<=7,20,IF(S44<=30,12,IF(S44<=90,5,0))))+IF(Q44="",0,MIN(15,Q44*5))+IF(O44="",0,MIN(15,O44*30))+IF(E44="Criador(a)",10,IF(E44="Especialista que cria conteúdo",6,4)),0) -> 47 | Z44: Personal blog | AB44: Sim | AD44: Itajaí: 2 post(s) marcados | AE44: Itajaí -SC (1), Igreja Matriz Itajai (1), Brusque, Santa Catarina (1), Limeira Baixa (1) | AF44: Corpo ativo • equilíbrio • fé sem rótulo / Vida real, sem romantizar. / Enf. do Trabalho em formação 🩺 / Profissional: @enfermagemvivasc | AG44: https://instagram.com/enfbapereira | AH44: Não contatada
A45: Itajaí | B45: Balneário Camboriú | C45: @isabbelle_m | D45: Isabelle Moraes | RE/MAX | E45: Especialista que cria conteúdo | F45: Mulher | G45: 3647 | H45: Micro (3k–30k) | I45: 0.0337 | J45: =IFERROR(INDEX('Como ler'!$B$20:$B$24,MATCH(H45,'Como ler'!$A$20:$A$24,0)),"") -> 0.025 | K45: =IF(OR(I45="",J45=""),"",I45/J45) -> 1.348 | L45: 105 | M45: 16.9 | N45: 428 | O45: =IF(OR(N45="",G45=0),"",N45/G45) -> 0.11735673 | P45: 0.33 | Q45: 0.9 | R45: 46286 | S45: =IF(R45="","",'Como ler'!$B$27-R45) -> 6 | T45: 0 | V45: Negócios e empreendedorismo | W45: Negócios e empreendedorismo | X45: Alta | Y45: =ROUND(IF(K45="",0,MIN(40,40*K45/1.5))+IF(S45="",0,IF(S45<=7,20,IF(S45<=30,12,IF(S45<=90,5,0))))+IF(Q45="",0,MIN(15,Q45*5))+IF(O45="",0,MIN(15,O45*30))+IF(E45="Criador(a)",10,IF(E45="Especialista que cria conteúdo",6,4)),0) -> 70 | AB45: Sim | AC45: direct | AD45: Itajaí: bio; Balneário Camboriú: 1 post(s) marcados | AE45: Chile (2), Balneário Camboriú (1), Cajón del Maipo (1) | AF45: Franqueada @remaxdreamon / Transição de carreira com estrutura, formação e direção para corretores / 📍BC• Itajaí • NVT / 📩Fale comigo no direct | AG45: https://instagram.com/isabbelle_m | AH45: Não contatada
A46: Itajaí | C46: @eudanielabonet | D46: Daniela Bonet | E46: Criador(a) | F46: Mulher | G46: 3375 | H46: Micro (3k–30k) | I46: 0.0166 | J46: =IFERROR(INDEX('Como ler'!$B$20:$B$24,MATCH(H46,'Como ler'!$A$20:$A$24,0)),"") -> 0.025 | K46: =IF(OR(I46="",J46=""),"",I46/J46) -> 0.664 | L46: 54 | M46: 8.4 | N46: 372 | O46: =IF(OR(N46="",G46=0),"",N46/G46) -> 0.11022222 | P46: 0.55 | Q46: 0.1 | R46: 46290 | S46: =IF(R46="","",'Como ler'!$B$27-R46) -> 2 | T46: 0 | V46: Viagem | W46: Viagem | X46: Baixa | Y46: =ROUND(IF(K46="",0,MIN(40,40*K46/1.5))+IF(S46="",0,IF(S46<=7,20,IF(S46<=30,12,IF(S46<=90,5,0))))+IF(Q46="",0,MIN(15,Q46*5))+IF(O46="",0,MIN(15,O46*30))+IF(E46="Criador(a)",10,IF(E46="Especialista que cria conteúdo",6,4)),0) -> 52 | AD46: Itajaí: 4 post(s) marcados | AE46: Itajaí (3), Grindelwald First 2200m, First Cliff Walk (1), Itajaí -SC (1), Marrocos (1) | AF46: 📍SC | AG46: https://instagram.com/eudanielabonet | AH46: Não contatada
A47: Itajaí | C47: @psicologademae | D47: Terapia gestação, depressão pós-parto. Grupo de mães Itajaí/BC | E47: Especialista que cria conteúdo | F47: Mulher | G47: 3121 | H47: Micro (3k–30k) | I47: 0.0061 | J47: =IFERROR(INDEX('Como ler'!$B$20:$B$24,MATCH(H47,'Como ler'!$A$20:$A$24,0)),"") -> 0.025 | K47: =IF(OR(I47="",J47=""),"",I47/J47) -> 0.244 | L47: 21 | M47: 7 | N47: 226 | O47: =IF(OR(N47="",G47=0),"",N47/G47) -> 0.072412688 | P47: 0.44 | Q47: 1.2 | R47: 46287 | S47: =IF(R47="","",'Como ler'!$B$27-R47) -> 5 | T47: 0 | V47: Educação e conhecimento | W47: Educação e conhecimento, Família e maternidade | X47: Média | Y47: =ROUND(IF(K47="",0,MIN(40,40*K47/1.5))+IF(S47="",0,IF(S47<=7,20,IF(S47<=30,12,IF(S47<=90,5,0))))+IF(Q47="",0,MIN(15,Q47*5))+IF(O47="",0,MIN(15,O47*30))+IF(E47="Criador(a)",10,IF(E47="Especialista que cria conteúdo",6,4)),0) -> 41 | Z47: Psychologist | AB47: Sim | AD47: Itajaí: bio, 4 post(s) marcados | AE47: Itajaí, Santa Catarina, Brasil (2), Praia Central - Baln. Camburiu (2), Itajaí -SC (2), Curitiba (1) | AF47: 🛋️Terapia para mulheres que querem se reencontrar após a maternidade / 🤰Pré-natal psicológico para gestantes / 📍Atendimentos on-line, Itajaí e BC / Clique⤵️ | AG47: https://instagram.com/psicologademae | AH47: Não contatada
A48: Itajaí | C48: @rafaeldoutore | D48: Rafael Dias Inácio | E48: Criador(a) | F48: Homem | G48: 2821 | H48: Nano (1k–3k) | I48: 0.0349 | J48: =IFERROR(INDEX('Como ler'!$B$20:$B$24,MATCH(H48,'Como ler'!$A$20:$A$24,0)),"") -> 0.04 | K48: =IF(OR(I48="",J48=""),"",I48/J48) -> 0.8725 | L48: 89 | M48: 4.9 | N48: 984 | O48: =IF(OR(N48="",G48=0),"",N48/G48) -> 0.34881248 | P48: 0.25 | Q48: 0.3 | R48: 46275 | S48: =IF(R48="","",'Como ler'!$B$27-R48) -> 17 | T48: 0 | X48: Baixa | Y48: =ROUND(IF(K48="",0,MIN(40,40*K48/1.5))+IF(S48="",0,IF(S48<=7,20,IF(S48<=30,12,IF(S48<=90,5,0))))+IF(Q48="",0,MIN(15,Q48*5))+IF(O48="",0,MIN(15,O48*30))+IF(E48="Criador(a)",10,IF(E48="Especialista que cria conteúdo",6,4)),0) -> 57 | AD48: Itajaí: 1 post(s) marcados | AE48: Kartódromo dos Ingleses (6), Autódromo de Tarumã (1), MRT / RG3 suspension Brasil (1), HONDA-TAKAI (FL) ITAJAI (1) | AF48: 🏍️ Rider / 🏆 2x Catarinense Motovelocidade 25 - 26 / 🏆 Endurance 12H 25 🏎️ - 2H 26 🏍️ / 🎮 PRO / 👔 Lawyer / ⚖️ Pós D. do Trabalho | Previdenciário | Sucessório | AG48: https://instagram.com/rafaeldoutore | AH48: Não contatada
A49: Itajaí | C49: @treinador_veiga | D49: 🇧🇷 𝕀𝕤𝕣𝕒𝕖𝕝 𝕍𝕖𝕚𝕘𝕒 🇧🇷 | E49: Especialista que cria conteúdo | F49: Homem | G49: 2614 | H49: Nano (1k–3k) | I49: 0.0042 | J49: =IFERROR(INDEX('Como ler'!$B$20:$B$24,MATCH(H49,'Como ler'!$A$20:$A$24,0)),"") -> 0.04 | K49: =IF(OR(I49="",J49=""),"",I49/J49) -> 0.105 | L49: 19 | M49: 2.1 | N49: 198 | O49: =IF(OR(N49="",G49=0),"",N49/G49) -> 0.075745983 | P49: 0.11 | Q49: 1.1 | R49: 46286 | S49: =IF(R49="","",'Como ler'!$B$27-R49) -> 6 | T49: 0 | V49: Fitness e wellness | W49: Fitness e wellness, Lifestyle, Família e maternidade | X49: Média | Y49: =ROUND(IF(K49="",0,MIN(40,40*K49/1.5))+IF(S49="",0,IF(S49<=7,20,IF(S49<=30,12,IF(S49<=90,5,0))))+IF(Q49="",0,MIN(15,Q49*5))+IF(O49="",0,MIN(15,O49*30))+IF(E49="Criador(a)",10,IF(E49="Especialista que cria conteúdo",6,4)),0) -> 37 | Z49: Entrepreneur | AD49: Itajaí: 9 post(s) marcados | AE49: Itajaí -SC (7), Bistek Itajaí (2) | AF49: 🌄 𝕃𝔾ℕ𝔻: 𝟙𝟘𝟙𝟙𝟝𝟟 - ℂℝ𝔼𝔽/𝕊ℂ: 𝟘𝟚𝟙𝟟𝟚𝟜 / 🧬 ℂ𝕠𝕒𝕔𝕙 𝕖𝕞 𝕡𝕣𝕖𝕤𝕔𝕣𝕚çõ𝕖𝕤 𝕖𝕤𝕡𝕖𝕔𝕚𝕒𝕝 / 💼 @studiogv_ / 💕@kahh_farias | AG49: https://instagram.com/treinador_veiga | AH49: Não contatada
A50: Itajaí | C50: @clebercoragem | D50: Cleber Coragem | E50: Especialista que cria conteúdo | F50: Homem | G50: 2377 | H50: Nano (1k–3k) | I50: 0.0093 | J50: =IFERROR(INDEX('Como ler'!$B$20:$B$24,MATCH(H50,'Como ler'!$A$20:$A$24,0)),"") -> 0.04 | K50: =IF(OR(I50="",J50=""),"",I50/J50) -> 0.2325 | L50: 24 | M50: 2.6 | N50: 72 | O50: =IF(OR(N50="",G50=0),"",N50/G50) -> 0.030290282 | P50: 0.67 | Q50: 2.8 | R50: 46280 | S50: =IF(R50="","",'Como ler'!$B$27-R50) -> 12 | T50: 0 | V50: Negócios e empreendedorismo | W50: Negócios e empreendedorismo, Educação e conhecimento, Família e maternidade | X50: Alta | Y50: =ROUND(IF(K50="",0,MIN(40,40*K50/1.5))+IF(S50="",0,IF(S50<=7,20,IF(S50<=30,12,IF(S50<=90,5,0))))+IF(Q50="",0,MIN(15,Q50*5))+IF(O50="",0,MIN(15,O50*30))+IF(E50="Criador(a)",10,IF(E50="Especialista que cria conteúdo",6,4)),0) -> 39 | AB50: Sim | AD50: Itajaí: 1 post(s) marcados | AE50: Itajaí (1) | AF50: 🏆 SIM, VOCÊ PODE! ACREDITE / ❤️‍🔥 Mentor e Terapeuta / 💪🏾 Transformando vidas | AG50: https://instagram.com/clebercoragem | AH50: Não contatada
A51: Itajaí | C51: @amandadumbrofsqui | D51: Amanda Dumbrofsqui | E51: Criador(a) | F51: Mulher | G51: 2266 | H51: Nano (1k–3k) | I51: 0.0677 | J51: =IFERROR(INDEX('Como ler'!$B$20:$B$24,MATCH(H51,'Como ler'!$A$20:$A$24,0)),"") -> 0.04 | K51: =IF(OR(I51="",J51=""),"",I51/J51) -> 1.6925 | L51: 257 | M51: 10.2 | N51: 1874 | O51: =IF(OR(N51="",G51=0),"",N51/G51) -> 0.82700794 | P51: 0.83 | Q51: 5.9 | R51: 46289 | S51: =IF(R51="","",'Como ler'!$B$27-R51) -> 3 | T51: 0 | V51: Lifestyle | W51: Lifestyle, Gastronomia, Dicas locais | X51: Média | Y51: =ROUND(IF(K51="",0,MIN(40,40*K51/1.5))+IF(S51="",0,IF(S51<=7,20,IF(S51<=30,12,IF(S51<=90,5,0))))+IF(Q51="",0,MIN(15,Q51*5))+IF(O51="",0,MIN(15,O51*30))+IF(E51="Criador(a)",10,IF(E51="Especialista que cria conteúdo",6,4)),0) -> 100 | AD51: Itajaí: bio, 5 post(s) marcados | AE51: Itajaí, Santa Catarina, Brasil (5), Italiana Garden Café (1), Beto Carrero World (1) | AF51: 📍SC / publicitária, criativa, fã de itajaí, aspirante a uma vida de Heleninha & outras coisas mais ✨ / pode reparar a bagunça 🧚🏼‍♀️ | AG51: https://instagram.com/amandadumbrofsqui | AH51: Não contatada
A52: Itajaí | C52: @leandrogatelli_personal | D52: Leandro Gatelli | E52: Especialista que cria conteúdo | F52: Homem | G52: 2203 | H52: Nano (1k–3k) | I52: 0.0045 | J52: =IFERROR(INDEX('Como ler'!$B$20:$B$24,MATCH(H52,'Como ler'!$A$20:$A$24,0)),"") -> 0.04 | K52: =IF(OR(I52="",J52=""),"",I52/J52) -> 0.1125 | L52: 12 | M52: 1.4 | O52: =IF(OR(N52="",G52=0),"",N52/G52) | P52: 0 | Q52: 1.3 | R52: 46286 | S52: =IF(R52="","",'Como ler'!$B$27-R52) -> 6 | T52: 0 | V52: Fitness e wellness | W52: Fitness e wellness, Educação e conhecimento, Lifestyle, Negócios e empreendedorismo | X52: Alta | Y52: =ROUND(IF(K52="",0,MIN(40,40*K52/1.5))+IF(S52="",0,IF(S52<=7,20,IF(S52<=30,12,IF(S52<=90,5,0))))+IF(Q52="",0,MIN(15,Q52*5))+IF(O52="",0,MIN(15,O52*30))+IF(E52="Criador(a)",10,IF(E52="Especialista que cria conteúdo",6,4)),0) -> 36 | Z52: Coach | AB52: Sim | AD52: Itajaí: 11 post(s) marcados | AE52: Itajaí -SC (10), Bistek Itajaí (1) | AF52: 🏋️‍♂️ Sócio fundador da GVs Studio / 🎓 Licenciatura Plena em Educação Física / 📚 +13 anos de experiência na área / 🎯 Musculação para Grupos Especiais | AG52: https://instagram.com/leandrogatelli_personal | AH52: Não contatada
A53: Itajaí | B53: Balneário Camboriú | C53: @ddiegoo.martins | D53: Diego Martins | E53: Especialista que cria conteúdo | F53: Homem | G53: 2109 | H53: Nano (1k–3k) | I53: 0.0133 | J53: =IFERROR(INDEX('Como ler'!$B$20:$B$24,MATCH(H53,'Como ler'!$A$20:$A$24,0)),"") -> 0.04 | K53: =IF(OR(I53="",J53=""),"",I53/J53) -> 0.3325 | L53: 32 | M53: 2.8 | N53: 61 | O53: =IF(OR(N53="",G53=0),"",N53/G53) -> 0.028923661 | P53: 0.27 | Q53: 2.2 | R53: 46291 | S53: =IF(R53="","",'Como ler'!$B$27-R53) -> 1 | T53: 0 | V53: Negócios e empreendedorismo | W53: Negócios e empreendedorismo, Educação e conhecimento, Casa e organização, Gastronomia | X53: Alta | Y53: =ROUND(IF(K53="",0,MIN(40,40*K53/1.5))+IF(S53="",0,IF(S53<=7,20,IF(S53<=30,12,IF(S53<=90,5,0))))+IF(Q53="",0,MIN(15,Q53*5))+IF(O53="",0,MIN(15,O53*30))+IF(E53="Criador(a)",10,IF(E53="Especialista que cria conteúdo",6,4)),0) -> 47 | AB53: Sim | AD53: Itajaí: bio; Balneário Camboriú: 1 post(s) marcados | AE53: Mexico City, Mexico (3), São João Batista, Santa Catarina (2), Balneário Camboriú (1), Centro Cultural Teatro Usiminas (1) | AF53: 🎤 Palestrante / 📈 Desenvolvimento de líderes / 🫶🏼 Presidente @abrh.sc / 👨‍🏫 Professor @senacitajai / 🍷Apaixonado por café e vinho | AG53: https://instagram.com/ddiegoo.martins | AH53: Não contatada
A54: Itajaí | C54: @silviaandreamota | D54: SILVIA MOTA | E54: Especialista que cria conteúdo | F54: Mulher | G54: 2074 | H54: Nano (1k–3k) | I54: 0.0068 | J54: =IFERROR(INDEX('Como ler'!$B$20:$B$24,MATCH(H54,'Como ler'!$A$20:$A$24,0)),"") -> 0.04 | K54: =IF(OR(I54="",J54=""),"",I54/J54) -> 0.17 | L54: 12 | M54: 1.2 | N54: 4 | O54: =IF(OR(N54="",G54=0),"",N54/G54) -> 0.0019286403 | P54: 0.11 | Q54: 0.5 | R54: 46288 | S54: =IF(R54="","",'Como ler'!$B$27-R54) -> 4 | T54: 0 | V54: Família e maternidade | W54: Família e maternidade, Relacionamento, Lifestyle, Fitness e wellness | X54: Média | Y54: =ROUND(IF(K54="",0,MIN(40,40*K54/1.5))+IF(S54="",0,IF(S54<=7,20,IF(S54<=30,12,IF(S54<=90,5,0))))+IF(Q54="",0,MIN(15,Q54*5))+IF(O54="",0,MIN(15,O54*30))+IF(E54="Criador(a)",10,IF(E54="Especialista que cria conteúdo",6,4)),0) -> 33 | Z54: Personal Coach | AB54: Sim | AD54: Itajaí: 1 post(s) marcados | AE54: Espinheiros, Santa Catarina (1), PIBI - Primeira Igreja Batista em Itajaí (1) | AF54: • Cristã •Esposa • Mãe / • Te ajudo a liderar sua rotina com propósito 🎯 / Mais de 2k Mulheres Impactadas | AG54: https://instagram.com/silviaandreamota | AH54: Não contatada
A55: Itajaí | C55: @doulacriscurvello | D55: Doula Itajaí | Ed. Perinatal | Maternidade Cristã | E55: Especialista que cria conteúdo | F55: Mulher | G55: 2028 | H55: Nano (1k–3k) | I55: 0.1706 | J55: =IFERROR(INDEX('Como ler'!$B$20:$B$24,MATCH(H55,'Como ler'!$A$20:$A$24,0)),"") -> 0.04 | K55: =IF(OR(I55="",J55=""),"",I55/J55) -> 4.265 | L55: 611 | M55: 23.3 | N55: 8807 | O55: =IF(OR(N55="",G55=0),"",N55/G55) -> 4.3427022 | P55: 0.09 | Q55: 0.2 | R55: 46266 | S55: =IF(R55="","",'Como ler'!$B$27-R55) -> 26 | T55: 0 | V55: Família e maternidade | W55: Família e maternidade, Relacionamento | X55: Média | Y55: =ROUND(IF(K55="",0,MIN(40,40*K55/1.5))+IF(S55="",0,IF(S55<=7,20,IF(S55<=30,12,IF(S55<=90,5,0))))+IF(Q55="",0,MIN(15,Q55*5))+IF(O55="",0,MIN(15,O55*30))+IF(E55="Criador(a)",10,IF(E55="Especialista que cria conteúdo",6,4)),0) -> 74 | AB55: Sim | AD55: Itajaí: 4 post(s) marcados | AE55: Itajaí -SC (3), Itajaí (1) | AF55: Ajudo mulheres viverem uma maternidade sobre[natural]💡📖 / 👩‍❤️‍💋‍👨Esposa | Mãe de 6 👦🏻👦🏻👦🏻👧🏼👦🏻👶🏻 / 🫂Apoio físico, emocional e espiritual / Fale comigo💜👇🏻 | AG55: https://instagram.com/doulacriscurvello | AH55: Não contatada
A56: Itajaí | C56: @personalorganizer.karen | D56: KAREN COLAMARIA - Personal Organizer Designer™️ | Mentora | E56: Especialista que cria conteúdo | F56: Mulher | G56: 2025 | H56: Nano (1k–3k) | J56: =IFERROR(INDEX('Como ler'!$B$20:$B$24,MATCH(H56,'Como ler'!$A$20:$A$24,0)),"") -> 0.04 | K56: =IF(OR(I56="",J56=""),"",I56/J56) | M56: 0 | O56: =IF(OR(N56="",G56=0),"",N56/G56) | P56: 0 | Q56: 3.1 | R56: 46288 | S56: =IF(R56="","",'Como ler'!$B$27-R56) -> 4 | T56: 0 | V56: Casa e organização | W56: Casa e organização, Viagem, Negócios e empreendedorismo | X56: Alta | Y56: =ROUND(IF(K56="",0,MIN(40,40*K56/1.5))+IF(S56="",0,IF(S56<=7,20,IF(S56<=30,12,IF(S56<=90,5,0))))+IF(Q56="",0,MIN(15,Q56*5))+IF(O56="",0,MIN(15,O56*30))+IF(E56="Criador(a)",10,IF(E56="Especialista que cria conteúdo",6,4)),0) -> 41 | Z56: Entrepreneur | AB56: Sim | AD56: Itajaí: 1 post(s) marcados | AE56: Curitiba, Paraná (2), Navegantes, Santa Catarina, Brasil (1), Brava Beach - Praia Brava (1), Curitiba, Brazil (1) | AF56: ● PRIMEIRA e ÚNICA Personal Organizer DESIGNER™ do BRASIL / ● Escritório SC e SP / ● 10 anos de Expertise / ● CRIADORA Organização Sensorial™ e Hotel Style™ | AG56: https://instagram.com/personalorganizer.karen | AH56: Não contatada | AI56: Curtidas ocultas: engajamento calculado só com posts visíveis ou indisponível
A57: Itajaí | C57: @byleticiagartner | D57: Letícia Rauber Gartner - Projeto de Influenciadora em Itajaí | E57: Criador(a) | F57: Mulher | G57: 1693 | H57: Nano (1k–3k) | I57: 0.031 | J57: =IFERROR(INDEX('Como ler'!$B$20:$B$24,MATCH(H57,'Como ler'!$A$20:$A$24,0)),"") -> 0.04 | K57: =IF(OR(I57="",J57=""),"",I57/J57) -> 0.775 | L57: 129 | M57: 7.3 | N57: 622 | O57: =IF(OR(N57="",G57=0),"",N57/G57) -> 0.36739516 | P57: 0.83 | Q57: 0.6 | R57: 46279 | S57: =IF(R57="","",'Como ler'!$B$27-R57) -> 13 | T57: 0 | V57: Família e maternidade | W57: Família e maternidade | X57: Média | Y57: =ROUND(IF(K57="",0,MIN(40,40*K57/1.5))+IF(S57="",0,IF(S57<=7,20,IF(S57<=30,12,IF(S57<=90,5,0))))+IF(Q57="",0,MIN(15,Q57*5))+IF(O57="",0,MIN(15,O57*30))+IF(E57="Criador(a)",10,IF(E57="Especialista que cria conteúdo",6,4)),0) -> 57 | Z57: Personal blog | AD57: Itajaí: 3 post(s) marcados | AE57: Itajaí (3), Brasil (1), Santa Catarina, Brasil (1) | AF57: Bastidores de uma vida entre eventos, trabalho e maternidade 🤎 / Acompanhe nos storys 🔥 / 💍 @matheusg.gartner / 💼 @gartnereventos | AG57: https://instagram.com/byleticiagartner | AH57: Não contatada
A58: Itajaí | C58: @o.clebernunes | D58: Cleber Nunes | E58: Criador(a) | F58: Homem | G58: 1399 | H58: Nano (1k–3k) | I58: 0.0172 | J58: =IFERROR(INDEX('Como ler'!$B$20:$B$24,MATCH(H58,'Como ler'!$A$20:$A$24,0)),"") -> 0.04 | K58: =IF(OR(I58="",J58=""),"",I58/J58) -> 0.43 | L58: 24269 | M58: 136.3 | N58: 718 | O58: =IF(OR(N58="",G58=0),"",N58/G58) -> 0.51322373 | P58: 0.83 | Q58: 0.5 | R58: 46292 | S58: =IF(R58="","",'Como ler'!$B$27-R58) -> 0 | T58: 0 | V58: Relacionamento | W58: Relacionamento | X58: Baixa | Y58: =ROUND(IF(K58="",0,MIN(40,40*K58/1.5))+IF(S58="",0,IF(S58<=7,20,IF(S58<=30,12,IF(S58<=90,5,0))))+IF(Q58="",0,MIN(15,Q58*5))+IF(O58="",0,MIN(15,O58*30))+IF(E58="Criador(a)",10,IF(E58="Especialista que cria conteúdo",6,4)),0) -> 59 | AB58: Sim | AC58: email | AD58: Itajaí: 5 post(s) marcados | AE58: Itajaí -SC (5) | AF58: Tudo aleatório mas que faz sentido🤔😅 / Marido • Corredor amador • Futuro Surfista / [e-mail na bio] 📨 | AG58: https://instagram.com/o.clebernunes | AH58: Não contatada
A59: Itajaí | C59: @brunamarqes | D59: Bruna Marques | Estrategista do Reino | E59: Especialista que cria conteúdo | F59: Mulher | G59: 1347 | H59: Nano (1k–3k) | I59: 0.0475 | J59: =IFERROR(INDEX('Como ler'!$B$20:$B$24,MATCH(H59,'Como ler'!$A$20:$A$24,0)),"") -> 0.04 | K59: =IF(OR(I59="",J59=""),"",I59/J59) -> 1.1875 | L59: 52 | M59: 26.4 | N59: 187 | O59: =IF(OR(N59="",G59=0),"",N59/G59) -> 0.13882702 | P59: 0.64 | Q59: 1.3 | R59: 46287 | S59: =IF(R59="","",'Como ler'!$B$27-R59) -> 5 | T59: 0 | V59: Social mídia e conteúdo | W59: Social mídia e conteúdo, Educação e conhecimento | X59: Alta | Y59: =ROUND(IF(K59="",0,MIN(40,40*K59/1.5))+IF(S59="",0,IF(S59<=7,20,IF(S59<=30,12,IF(S59<=90,5,0))))+IF(Q59="",0,MIN(15,Q59*5))+IF(O59="",0,MIN(15,O59*30))+IF(E59="Criador(a)",10,IF(E59="Especialista que cria conteúdo",6,4)),0) -> 68 | AD59: Itajaí: 1 post(s) marcados | AE59: Marlborough, Massachusetts (1), Itajaí (1) | AF59: Ativo o Posicionamento de mulheres que carregam uma mensagem do Reino. / IDENTIDADE 》AUTOGOVERNO 》CHAMADO / Da essência ao legado ❤️‍🔥 | AG59: https://instagram.com/brunamarqes | AH59: Não contatada
A60: Balneário Camboriú | B60: Itajaí | C60: @ondeirbc | D60: Mell - Onde ir Balneário Camboriú | E60: Criador(a) | F60: Mulher | G60: 119845 | H60: Macro (100k–500k) | I60: 0.0038 | J60: =IFERROR(INDEX('Como ler'!$B$20:$B$24,MATCH(H60,'Como ler'!$A$20:$A$24,0)),"") -> 0.01 | K60: =IF(OR(I60="",J60=""),"",I60/J60) -> 0.38 | L60: 489 | M60: 24.9 | N60: 9245 | O60: =IF(OR(N60="",G60=0),"",N60/G60) -> 0.077141308 | P60: 0.75 | Q60: 1.6 | R60: 46289 | S60: =IF(R60="","",'Como ler'!$B$27-R60) -> 3 | T60: 0 | V60: Gastronomia | W60: Gastronomia, Dicas locais | X60: Baixa | Y60: =ROUND(IF(K60="",0,MIN(40,40*K60/1.5))+IF(S60="",0,IF(S60<=7,20,IF(S60<=30,12,IF(S60<=90,5,0))))+IF(Q60="",0,MIN(15,Q60*5))+IF(O60="",0,MIN(15,O60*30))+IF(E60="Criador(a)",10,IF(E60="Especialista que cria conteúdo",6,4)),0) -> 50 | AA60: Sim | AB60: Sim | AC60: direct | AD60: Balneário Camboriú: 2 post(s) marcados; Itajaí: 1 post(s) marcados | AE60: Balneário Camboriú (2), Itajaí (1) | AF60: 🙋🏻‍♀️Sou a Mell! Falo tudo que você precisa saber antes de entrar num restaurante! / 🏅Referência em dicas desde 2016 / 💌Parcerias link bio ou direct | AG60: https://instagram.com/ondeirbc | AH60: Não contatada
A61: Balneário Camboriú | B61: Itajaí | C61: @coisasquecomo | D61: Tábata (Coisas Que Como) | E61: Criador(a) | F61: Mulher | G61: 96473 | H61: Média (30k–100k) | I61: 0.0045 | J61: =IFERROR(INDEX('Como ler'!$B$20:$B$24,MATCH(H61,'Como ler'!$A$20:$A$24,0)),"") -> 0.015 | K61: =IF(OR(I61="",J61=""),"",I61/J61) -> 0.3 | L61: 574 | M61: 23.2 | N61: 6330 | O61: =IF(OR(N61="",G61=0),"",N61/G61) -> 0.065614213 | P61: 1 | Q61: 5.1 | R61: 46291 | S61: =IF(R61="","",'Como ler'!$B$27-R61) -> 1 | T61: 3 | U61: @superkochoficial, @lojaskoerich | V61: Gastronomia | W61: Gastronomia, Entretenimento e humor, Casa e organização | X61: Alta | Y61: =ROUND(IF(K61="",0,MIN(40,40*K61/1.5))+IF(S61="",0,IF(S61<=7,20,IF(S61<=30,12,IF(S61<=90,5,0))))+IF(Q61="",0,MIN(15,Q61*5))+IF(O61="",0,MIN(15,O61*30))+IF(E61="Criador(a)",10,IF(E61="Especialista que cria conteúdo",6,4)),0) -> 55 | AA61: Sim | AD61: Itajaí: bio, 2 post(s) marcados; Balneário Camboriú: bio, 3 post(s) marcados | AE61: Balneário Camboriú (3), Itajaí (2), Beto Carrero World (1) | AF61: 👩‍🍳 Tábata, Cozinheira Profissional fazendo reviews de restaurantes e receitas com humor / 📍Balneário Camboriú, Itajaí e por SC | AG61: https://instagram.com/coisasquecomo | AH61: Não contatada
A62: Balneário Camboriú | B62: Itajaí | C62: @eucarolinaalbuquerque | D62: Carolina Albuquerque | E62: Criador(a) | F62: Mulher | G62: 91438 | H62: Média (30k–100k) | I62: 0.0013 | J62: =IFERROR(INDEX('Como ler'!$B$20:$B$24,MATCH(H62,'Como ler'!$A$20:$A$24,0)),"") -> 0.015 | K62: =IF(OR(I62="",J62=""),"",I62/J62) -> 0.086666667 | L62: 190 | M62: 22.2 | N62: 1811 | O62: =IF(OR(N62="",G62=0),"",N62/G62) -> 0.01980577 | P62: 0.45 | Q62: 3.2 | R62: 46291 | S62: =IF(R62="","",'Como ler'!$B$27-R62) -> 1 | T62: 0 | V62: Gastronomia | W62: Gastronomia, Lifestyle, Negócios e empreendedorismo | X62: Alta | Y62: =ROUND(IF(K62="",0,MIN(40,40*K62/1.5))+IF(S62="",0,IF(S62<=7,20,IF(S62<=30,12,IF(S62<=90,5,0))))+IF(Q62="",0,MIN(15,Q62*5))+IF(O62="",0,MIN(15,O62*30))+IF(E62="Criador(a)",10,IF(E62="Especialista que cria conteúdo",6,4)),0) -> 48 | AA62: Sim | AD62: Balneário Camboriú: 3 post(s) marcados; Itajaí: 1 post(s) marcados | AE62: Balneário Camboriú (3), Buenos Aires, Argentina (1), Puerto Madero (1), Praia Brava - Itajaí SC (1) | AF62: Minha rotina: Experiências, Jesus, Receitas & muito Café ☕️ / Do Direito para as telas: influenciadora e empresária @aurahclube 🪐🤎 | AG62: https://instagram.com/eucarolinaalbuquerque | AH62: Não contatada
